Workbook
Name nr_AllowedMonths: '[1]3_Master_Data'!$D$2:$D$4
Name nr_CostCenters: '[1]3_Master_Data'!$O$2:$O$6
Name nr_Countries: '[1]3_Master_Data'!$A$2:$A$6
Name nr_EntityTypes: '[1]3_Master_Data'!$F$2:$F$5
Name nr_PaymentTypes: '[1]3_Master_Data'!$I$2:$I$5
Name nr_ProjectCodes: '[1]3_Master_Data'!$Q$2:$Q$5

Sheet 05_Control_Dashboard
A1: AP CONTROL SUMMARY | D1: EOR CONTROL SUMMARY
A2: Total Transactions | B2: =COUNTA('02_Validation_Engine'!A:A)-1 -> 350 | D2: Total EOR Invoices | E2: =COUNTA('04_EOR_Reconciliation'!E:E)-1 -> 12
A3: Blocked Transactions | B3: =COUNTIF('02_Validation_Engine'!W:W,"Fail") -> 15 | D3: Total EOR Invoice Value | E3: =SUM('04_EOR_Reconciliation'!K:K) -> 1642753.6
A4: Ready For Approval | B4: =COUNTIF('02_Validation_Engine'!X:X,"Yes") -> 335 | D4: Unreconciled Invoices | E4: =COUNTIF('04_EOR_Reconciliation'!K:K,"Not Reconciled") -> 0
A5: Approval Rate % | B5: =IF(B2=0,0,B4/B2) -> 0.95714286 | D5: Control Status | E5: =IF(E4=0,"All EOR invoices reconciled","Attention Required") -> All EOR invoices reconciled
A6: Required Field Errors | B6: =COUNTIF('02_Validation_Engine'!P:P,"Fail") -> 5
A7: Amount Errors | B7: =COUNTIF('02_Validation_Engine'!Q:Q,"Fail") -> 5
A8: Bank Errors | B8: =COUNTIF('02_Validation_Engine'!U:U,"Fail") -> 2
A9: Duplicate Errors | B9: =COUNTIF('02_Validation_Engine'!V:V,"Fail") -> 2
A10: Currency Errors | B10: =COUNTIF('02_Validation_Engine'!R:R,"Fail") -> 1
A11: VAT Errors | B11: =COUNTIF('02_Validation_Engine'!T:T,"Fail") -> 1
A12: Exchange Rate Errors | B12: =COUNTIF('02_Validation_Engine'!S:S,"Fail") -> 0

Sheet 04_EOR_Reconciliation
A1: Month | B1: Country | C1: Currency | D1: EOR_Provider | E1: Invoice_Number | F1: Invoice_Date | G1: Employee_Count | H1: Expected_Payroll | I1: Employer_Tax_% | J1: Service_Fee_% | K1: Invoice_Total | L1: Paid_Amount | M1: Variance | N1: Status
A2: 46023 | B2: Jordan | C2: JOD | D2: =IF(B2="Jordan","Oyster", IF(B2="Germany","Oyster", IF(B2="USA","Remote", IF(B2="UAE","Deel","")))) -> Oyster | E2: =UPPER(LEFT(D2,3) & "-" & LEFT(B2,2) & "-" & TEXT(A2,"MMYY")) -> OYS-JO-0126 | F2: =EOMONTH(A2,0) -> 46053 | G2: =COUNTIFS( '02_Validation_Engine'!$G:$G,$A2, '02_Validation_Engine'!$D:$D,$B2, '02_Validation_Engine'!$C:$C,"Employee", '02_Validation_Engine'!$W:$W,"Pass", '02_Validation_Engine'!$X:$X,"Yes" ) -> 15 | H2: =SUMIFS( '02_Validation_Engine'!$M:$M, '02_Validation_Engine'!$G:$G,$A2, '02_Validation_Engine'!$D:$D,$B2, '02_Validation_Engine'!$C:$C,"Employee", '02_Validation_Engine'!$W:$W,"Pass", '02_Validation_Engine'!$X:$X,"Yes" ) -> 27437.82 | I2: 0.15 | J2: 0.05 | K2: =H2*(1+I2+J2) -> 32925.384 | L2: ='04_EOR_Reconciliation'!K2 -> 32925.384 | M2: =EOR[[#This Row],[Invoice_Total]]-EOR[[#This Row],[Paid_Amount]] -> 0 | N2: =IF(K2=L2,"Reconciled","Not Reconciled") -> Reconciled
A3: 46023 | B3: USA | C3: USD | D3: =IF(B3="Jordan","Oyster", IF(B3="Germany","Oyster", IF(B3="USA","Remote", IF(B3="UAE","Deel","")))) -> Remote | E3: =UPPER(LEFT(D3,3) & "-" & LEFT(B3,2) & "-" & TEXT(A3,"MMYY")) -> REM-US-0126 | F3: =EOMONTH(A3,0) -> 46053 | G3: =COUNTIFS( '02_Validation_Engine'!$G:$G,$A3, '02_Validation_Engine'!$D:$D,$B3, '02_Validation_Engine'!$C:$C,"Employee", '02_Validation_Engine'!$W:$W,"Pass", '02_Validation_Engine'!$X:$X,"Yes" ) -> 18 | H3: =SUMIFS( '02_Validation_Engine'!$M:$M, '02_Validation_Engine'!$G:$G,$A3, '02_Validation_Engine'!$D:$D,$B3, '02_Validation_Engine'!$C:$C,"Employee", '02_Validation_Engine'!$W:$W,"Pass", '02_Validation_Engine'!$X:$X,"Yes" ) -> 127990.64 | I3: 0.15 | J3: 0.05 | K3: =H3*(1+I3+J3) -> 153588.77 | L3: ='04_EOR_Reconciliation'!K3 -> 153588.77 | M3: =EOR[[#This Row],[Invoice_Total]]-EOR[[#This Row],[Paid_Amount]] -> 0 | N3: =IF(K3=L3,"Reconciled","Not Reconciled") -> Reconciled
A4: 46023 | B4: Germany | C4: EUR | D4: =IF(B4="Jordan","Oyster", IF(B4="Germany","Oyster", IF(B4="USA","Remote", IF(B4="UAE","Deel","")))) -> Oyster | E4: =UPPER(LEFT(D4,3) & "-" & LEFT(B4,2) & "-" & TEXT(A4,"MMYY")) -> OYS-GE-0126 | F4: =EOMONTH(A4,0) -> 46053 | G4: =COUNTIFS( '02_Validation_Engine'!$G:$G,$A4, '02_Validation_Engine'!$D:$D,$B4, '02_Validation_Engine'!$C:$C,"Employee", '02_Validation_Engine'!$W:$W,"Pass", '02_Validation_Engine'!$X:$X,"Yes" ) -> 12 | H4: =SUMIFS( '02_Validation_Engine'!$M:$M, '02_Validation_Engine'!$G:$G,$A4, '02_Validation_Engine'!$D:$D,$B4, '02_Validation_Engine'!$C:$C,"Employee", '02_Validation_Engine'!$W:$W,"Pass", '02_Validation_Engine'!$X:$X,"Yes" ) -> 72844.14 | I4: 0.15 | J4: 0.05 | K4: =H4*(1+I4+J4) -> 87412.968 | L4: ='04_EOR_Reconciliation'!K4 -> 87412.968 | M4: =EOR[[#This Row],[Invoice_Total]]-EOR[[#This Row],[Paid_Amount]] -> 0 | N4: =IF(K4=L4,"Reconciled","Not Reconciled") -> Reconciled
A5: 46023 | B5: UAE | C5: AED | D5: =IF(B5="Jordan","Oyster", IF(B5="Germany","Oyster", IF(B5="USA","Remote", IF(B5="UAE","Deel","")))) -> Deel | E5: =UPPER(LEFT(D5,3) & "-" & LEFT(B5,2) & "-" & TEXT(A5,"MMYY")) -> DEE-UA-0126 | F5: =EOMONTH(A5,0) -> 46053 | G5: =COUNTIFS( '02_Validation_Engine'!$G:$G,$A5, '02_Validation_Engine'!$D:$D,$B5, '02_Validation_Engine'!$C:$C,"Employee", '02_Validation_Engine'!$W:$W,"Pass", '02_Validation_Engine'!$X:$X,"Yes" ) -> 17 | H5: =SUMIFS( '02_Validation_Engine'!$M:$M, '02_Validation_Engine'!$G:$G,$A5, '02_Validation_Engine'!$D:$D,$B5, '02_Validation_Engine'!$C:$C,"Employee", '02_Validation_Engine'!$W:$W,"Pass", '02_Validation_Engine'!$X:$X,"Yes" ) -> 371120.55 | I5: 0.15 | J5: 0.05 | K5: =H5*(1+I5+J5) -> 445344.66 | L5: ='04_EOR_Reconciliation'!K5 -> 445344.66 | M5: =EOR[[#This Row],[Invoice_Total]]-EOR[[#This Row],[Paid_Amount]] -> 0 | N5: =IF(K5=L5,"Reconciled","Not Reconciled") -> Reconciled
A6: 46054 | B6: Jordan | C6: JOD | D6: =IF(B6="Jordan","Oyster", IF(B6="Germany","Oyster", IF(B6="USA","Remote", IF(B6="UAE","Deel","")))) -> Oyster | E6: =UPPER(LEFT(D6,3) & "-" & LEFT(B6,2) & "-" & TEXT(A6,"MMYY")) -> OYS-JO-0226 | F6: =EOMONTH(A6,0) -> 46081 | G6: =COUNTIFS( '02_Validation_Engine'!$G:$G,$A6, '02_Validation_Engine'!$D:$D,$B6, '02_Validation_Engine'!$C:$C,"Employee", '02_Validation_Engine'!$W:$W,"Pass", '02_Validation_Engine'!$X:$X,"Yes" ) -> 15 | H6: =SUMIFS( '02_Validation_Engine'!$M:$M, '02_Validation_Engine'!$G:$G,$A6, '02_Validation_Engine'!$D:$D,$B6, '02_Validation_Engine'!$C:$C,"Employee", '02_Validation_Engine'!$W:$W,"Pass", '02_Validation_Engine'!$X:$X,"Yes" ) -> 27442.47 | I6: 0.15 | J6: 0.05 | K6: =H6*(1+I6+J6) -> 32930.964 | L6: ='04_EOR_Reconciliation'!K6 -> 32930.964 | M6: =EOR[[#This Row],[Invoice_Total]]-EOR[[#This Row],[Paid_Amount]] -> 0 | N6: =IF(K6=L6,"Reconciled","Not Reconciled") -> Reconciled
A7: 46054 | B7: USA | C7: USD | D7: =IF(B7="Jordan","Oyster", IF(B7="Germany","Oyster", IF(B7="USA","Remote", IF(B7="UAE","Deel","")))) -> Remote | E7: =UPPER(LEFT(D7,3) & "-" & LEFT(B7,2) & "-" & TEXT(A7,"MMYY")) -> REM-US-0226 | F7: =EOMONTH(A7,0) -> 46081 | G7: =COUNTIFS( '02_Validation_Engine'!$G:$G,$A7, '02_Validation_Engine'!$D:$D,$B7, '02_Validation_Engine'!$C:$C,"Employee", '02_Validation_Engine'!$W:$W,"Pass", '02_Validation_Engine'!$X:$X,"Yes" ) -> 13 | H7: =SUMIFS( '02_Validation_Engine'!$M:$M, '02_Validation_Engine'!$G:$G,$A7, '02_Validation_Engine'!$D:$D,$B7, '02_Validation_Engine'!$C:$C,"Employee", '02_Validation_Engine'!$W:$W,"Pass", '02_Validation_Engine'!$X:$X,"Yes" ) -> 92854.43 | I7: 0.15 | J7: 0.05 | K7: =H7*(1+I7+J7) -> 111425.32 | L7: ='04_EOR_Reconciliation'!K7 -> 111425.32 | M7: =EOR[[#This Row],[Invoice_Total]]-EOR[[#This Row],[Paid_Amount]] -> 0 | N7: =IF(K7=L7,"Reconciled","Not Reconciled") -> Reconciled
A8: 46054 | B8: Germany | C8: EUR | D8: =IF(B8="Jordan","Oyster", IF(B8="Germany","Oyster", IF(B8="USA","Remote", IF(B8="UAE","Deel","")))) -> Oyster | E8: =UPPER(LEFT(D8,3) & "-" & LEFT(B8,2) & "-" & TEXT(A8,"MMYY")) -> OYS-GE-0226 | F8: =EOMONTH(A8,0) -> 46081 | G8: =COUNTIFS( '02_Validation_Engine'!$G:$G,$A8, '02_Validation_Engine'!$D:$D,$B8, '02_Validation_Engine'!$C:$C,"Employee", '02_Validation_Engine'!$W:$W,"Pass", '02_Validation_Engine'!$X:$X,"Yes" ) -> 13 | H8: =SUMIFS( '02_Validation_Engine'!$M:$M, '02_Validation_Engine'!$G:$G,$A8, '02_Validation_Engine'!$D:$D,$B8, '02_Validation_Engine'!$C:$C,"Employee", '02_Validation_Engine'!$W:$W,"Pass", '02_Validation_Engine'!$X:$X,"Yes" ) -> 78234.17 | I8: 0.15 | J8: 0.05 | K8: =H8*(1+I8+J8) -> 93881.004 | L8: ='04_EOR_Reconciliation'!K8 -> 93881.004 | M8: =EOR[[#This Row],[Invoice_Total]]-EOR[[#This Row],[Paid_Amount]] -> 0 | N8: =IF(K8=L8,"Reconciled","Not Reconciled") -> Reconciled
A9: 46054 | B9: UAE | C9: AED | D9: =IF(B9="Jordan","Oyster", IF(B9="Germany","Oyster", IF(B9="USA","Remote", IF(B9="UAE","Deel","")))) -> Deel | E9: =UPPER(LEFT(D9,3) & "-" & LEFT(B9,2) & "-" & TEXT(A9,"MMYY")) -> DEE-UA-0226 | F9: =EOMONTH(A9,0) -> 46081 | G9: =COUNTIFS( '02_Validation_Engine'!$G:$G,$A9, '02_Validation_Engine'!$D:$D,$B9, '02_Validation_Engine'!$C:$C,"Employee", '02_Validation_Engine'!$W:$W,"Pass", '02_Validation_Engine'!$X:$X,"Yes" ) -> 10 | H9: =SUMIFS( '02_Validation_Engine'!$M:$M, '02_Validation_Engine'!$G:$G,$A9, '02_Validation_Engine'!$D:$D,$B9, '02_Validation_Engine'!$C:$C,"Employee", '02_Validation_Engine'!$W:$W,"Pass", '02_Validation_Engine'!$X:$X,"Yes" ) -> 226770.84 | I9: 0.15 | J9: 0.05 | K9: =H9*(1+I9+J9) -> 272125.01 | L9: ='04_EOR_Reconciliation'!K9 -> 272125.01 | M9: =EOR[[#This Row],[Invoice_Total]]-EOR[[#This Row],[Paid_Amount]] -> 0 | N9: =IF(K9=L9,"Reconciled","Not Reconciled") -> Reconciled
A10: 46082 | B10: Jordan | C10: JOD | D10: =IF(B10="Jordan","Oyster", IF(B10="Germany","Oyster", IF(B10="USA","Remote", IF(B10="UAE","Deel","")))) -> Oyster | E10: =UPPER(LEFT(D10,3) & "-" & LEFT(B10,2) & "-" & TEXT(A10,"MMYY")) -> OYS-JO-0326 | F10: =EOMONTH(A10,0) -> 46112 | G10: =COUNTIFS( '02_Validation_Engine'!$G:$G,$A10, '02_Validation_Engine'!$D:$D,$B10, '02_Validation_Engine'!$C:$C,"Employee", '02_Validation_Engine'!$W:$W,"Pass", '02_Validation_Engine'!$X:$X,"Yes" ) -> 10 | H10: =SUMIFS( '02_Validation_Engine'!$M:$M, '02_Validation_Engine'!$G:$G,$A10, '02_Validation_Engine'!$D:$D,$B10, '02_Validation_Engine'!$C:$C,"Employee", '02_Validation_Engine'!$W:$W,"Pass", '02_Validation_Engine'!$X:$X,"Yes" ) -> 18005.8 | I10: 0.15 | J10: 0.05 | K10: =H10*(1+I10+J10) -> 21606.96 | L10: ='04_EOR_Reconciliation'!K10 -> 21606.96 | M10: =EOR[[#This Row],[Invoice_Total]]-EOR[[#This Row],[Paid_Amount]] -> 0 | N10: =IF(K10=L10,"Reconciled","Not Reconciled") -> Reconciled
A11: 46082 | B11: USA | C11: USD | D11: =IF(B11="Jordan","Oyster", IF(B11="Germany","Oyster", IF(B11="USA","Remote", IF(B11="UAE","Deel","")))) -> Remote | E11: =UPPER(LEFT(D11,3) & "-" & LEFT(B11,2) & "-" & TEXT(A11,"MMYY")) -> REM-US-0326 | F11: =EOMONTH(A11,0) -> 46112 | G11: =COUNTIFS( '02_Validation_Engine'!$G:$G,$A11, '02_Validation_Engine'!$D:$D,$B11, '02_Validation_Engine'!$C:$C,"Employee", '02_Validation_Engine'!$W:$W,"Pass", '02_Validation_Engine'!$X:$X,"Yes" ) -> 12 | H11: =SUMIFS( '02_Validation_Engine'!$M:$M, '02_Validation_Engine'!$G:$G,$A11, '02_Validation_Engine'!$D:$D,$B11, '02_Validation_Engine'!$C:$C,"Employee", '02_Validation_Engine'!$W:$W,"Pass", '02_Validation_Engine'!$X:$X,"Yes" ) -> 86738.08 | I11: 0.15 | J11: 0.05 | K11: =H11*(1+I11+J11) -> 104085.7 | L11: ='04_EOR_Reconciliation'!K11 -> 104085.7 | M11: =EOR[[#This Row],[Invoice_Total]]-EOR[[#This Row],[Paid_Amount]] -> 0 | N11: =IF(K11=L11,"Reconciled","Not Reconciled") -> Reconciled
A12: 46082 | B12: Germany | C12: EUR | D12: =IF(B12="Jordan","Oyster", IF(B12="Germany","Oyster", IF(B12="USA","Remote", IF(B12="UAE","Deel","")))) -> Oyster | E12: =UPPER(LEFT(D12,3) & "-" & LEFT(B12,2) & "-" & TEXT(A12,"MMYY")) -> OYS-GE-0326 | F12: =EOMONTH(A12,0) -> 46112 | G12: =COUNTIFS( '02_Validation_Engine'!$G:$G,$A12, '02_Validation_Engine'!$D:$D,$B12, '02_Validation_Engine'!$C:$C,"Employee", '02_Validation_Engine'!$W:$W,"Pass", '02_Validation_Engine'!$X:$X,"Yes" ) -> 10 | H12: =SUMIFS( '02_Validation_Engine'!$M:$M, '02_Validation_Engine'!$G:$G,$A12, '02_Validation_Engine'!$D:$D,$B12, '02_Validation_Engine'!$C:$C,"Employee", '02_Validation_Engine'!$W:$W,"Pass", '02_Validation_Engine'!$X:$X,"Yes" ) -> 61273.14 | I12: 0.15 | J12: 0.05 | K12: =H12*(1+I12+J12) -> 73527.768 | L12: ='04_EOR_Reconciliation'!K12 -> 73527.768 | M12: =EOR[[#This Row],[Invoice_Total]]-EOR[[#This Row],[Paid_Amount]] -> 0 | N12: =IF(K12=L12,"Reconciled","Not Reconciled") -> Reconciled
A13: 46082 | B13: UAE | C13: AED | D13: =IF(B13="Jordan","Oyster", IF(B13="Germany","Oyster", IF(B13="USA","Remote", IF(B13="UAE","Deel","")))) -> Deel | E13: =UPPER(LEFT(D13,3) & "-" & LEFT(B13,2) & "-" & TEXT(A13,"MMYY")) -> DEE-UA-0326 | F13: =EOMONTH(A13,0) -> 46112 | G13: =COUNTIFS( '02_Validation_Engine'!$G:$G,$A13, '02_Validation_Engine'!$D:$D,$B13, '02_Validation_Engine'!$C:$C,"Employee", '02_Validation_Engine'!$W:$W,"Pass", '02_Validation_Engine'!$X:$X,"Yes" ) -> 8 | H13: =SUMIFS( '02_Validation_Engine'!$M:$M, '02_Validation_Engine'!$G:$G,$A13, '02_Validation_Engine'!$D:$D,$B13, '02_Validation_Engine'!$C:$C,"Employee", '02_Validation_Engine'!$W:$W,"Pass", '02_Validation_Engine'!$X:$X,"Yes" ) -> 178249.22 | I13: 0.15 | J13: 0.05 | K13: =H13*(1+I13+J13) -> 213899.06 | L13: ='04_EOR_Reconciliation'!K13 -> 213899.06 | M13: =EOR[[#This Row],[Invoice_Total]]-EOR[[#This Row],[Paid_Amount]] -> 0 | N13: =IF(K13=L13,"Reconciled","Not Reconciled") -> Reconciled

Sheet 03_Payment_Batch
A1: Record_ID | B1: Month | C1: Payment_Type | D1: Name | E1: Country | F1: Currency | G1: Gross_Amount | H1: Exchange_Rate | I1: Amount_CHF | J1: Bank_Account
A2: 1 | B2: =IFERROR(VLOOKUP($A2,'02_Validation_Engine'!$A:$X,7,FALSE),"") -> Feb-2026 | C2: Payroll | D2: Omar Müller | E2: Jordan | F2: JOD | G2: 1687.14 | H2: 1.08643 | I2: 1832.96 | J2: JO-IBAN-00024690
A3: 3 | B3: =IFERROR(VLOOKUP($A3,'02_Validation_Engine'!$A:$X,7,FALSE),"") -> Feb-2026 | C3: Payroll | D3: David Wilson | E3: USA | F3: USD | G3: 7521.5 | H3: 0.77018 | I3: 5792.91 | J3: US-RT-000004936-AC-0000022712
A4: 4 | B4: =IFERROR(VLOOKUP($A4,'02_Validation_Engine'!$A:$X,7,FALSE),"") -> Mar-2026 | C4: Payroll | D4: John Smith | E4: USA | F4: USD | G4: 7077 | H4: 0.77018 | I4: 5450.56 | J4: US-RT-000006170-AC-0000028390
A5: 5 | B5: =IFERROR(VLOOKUP($A5,'02_Validation_Engine'!$A:$X,7,FALSE),"") -> Feb-2026 | C5: Payroll | D5: Anna Khan | E5: Germany | F5: EUR | G5: 5455.2 | H5: 0.90888 | I5: 4958.12 | J5: DE890000000000081474
A6: 6 | B6: =IFERROR(VLOOKUP($A6,'02_Validation_Engine'!$A:$X,7,FALSE),"") -> Jan-2026 | C6: Payroll | D6: David Haddad | E6: Germany | F6: EUR | G6: 5775 | H6: 0.90888 | I6: 5248.78 | J6: DE890000000000095053
A7: 7 | B7: =IFERROR(VLOOKUP($A7,'02_Validation_Engine'!$A:$X,7,FALSE),"") -> Mar-2026 | C7: Payroll | D7: Anna Taylor | E7: Jordan | F7: JOD | G7: 1837.8 | H7: 1.08643 | I7: 1996.64 | J7: JO-IBAN-00098760
A8: 8 | B8: =IFERROR(VLOOKUP($A8,'02_Validation_Engine'!$A:$X,7,FALSE),"") -> Mar-2026 | C8: Payroll | D8: David Khan | E8: Germany | F8: EUR | G8: 6138.6 | H8: 0.90888 | I8: 5579.25 | J8: DE890000000000122211
A9: 9 | B9: =IFERROR(VLOOKUP($A9,'02_Validation_Engine'!$A:$X,7,FALSE),"") -> Mar-2026 | C9: Payroll | D9: Lina Wilson | E9: USA | F9: USD | G9: 7459.9 | H9: 0.77018 | I9: 5745.47 | J9: US-RT-000012340-AC-0000056780
A10: 10 | B10: =IFERROR(VLOOKUP($A10,'02_Validation_Engine'!$A:$X,7,FALSE),"") -> Mar-2026 | C10: Payroll | D10: Michael Wilson | E10: USA | F10: USD | G10: 7142.8 | H10: 0.77018 | I10: 5501.24 | J10: US-RT-000013574-AC-0000062458
A11: 11 | B11: =IFERROR(VLOOKUP($A11,'02_Validation_Engine'!$A:$X,7,FALSE),"") -> Feb-2026 | C11: Payroll | D11: David Smith | E11: Jordan | F11: JOD | G11: 1971.72 | H11: 1.08643 | I11: 2142.14 | J11: JO-IBAN-00148140
A12: 12 | B12: =IFERROR(VLOOKUP($A12,'02_Validation_Engine'!$A:$X,7,FALSE),"") -> Jan-2026 | C12: Payroll | D12: Michael Wilson | E12: USA | F12: USD | G12: 7249.94 | H12: 0.77018 | I12: 5583.76 | J12: US-RT-000013574-AC-0000062458
A13: 13 | B13: =IFERROR(VLOOKUP($A13,'02_Validation_Engine'!$A:$X,7,FALSE),"") -> Jan-2026 | C13: Payroll | D13: Julia Smith | E13: Switzerland | F13: CHF | G13: 6364.8 | H13: 1 | I13: 6364.8 | J13: CH930000000000320840
... A331: 349 | B331: =IFERROR(VLOOKUP($A331,'02_Validation_Engine'!$A:$X,7,FALSE),"") -> Mar-2026 | C331: Grant_Disbursement | D331: Regional Advocacy Network | E331: Switzerland | F331: CHF | G331: 51885.6 | H331: 1 | I331: 51885.6 | J331: JO-IBAN-01296225

Sheet 02_Validation_Engine
A1: Record_ID | B1: Payment_Type | C1: Entity_Type | D1: Country | E1: Name | F1: Bank_Account | G1: Month | H1: Currency | I1: Net_Amount | J1: VAT_Applicable | K1: VAT_Rate | L1: VAT_Amount | M1: Gross_Amount | N1: Exchange_Rate | O1: Amount_CHF | P1: RequiredField_Validation | Q1: Amount_Validation | R1: Currency_Validation | S1: ExchangeRate_Validation | T1: VAT_Validation | U1: Bank_Validation | V1: Duplicate_Validation | W1: Validation_Result | X1: Ready_For_Approval
A2: =RawTable[[#This Row],[Record_ID]] -> 1 | B2: =RawTable[[#This Row],[Payment_Type]] -> Payroll | C2: =RawTable[[#This Row],[Entity_Type]] -> Employee | D2: =RawTable[[#This Row],[Country]] -> Jordan | E2: =RawTable[[#This Row],[Name]] -> Omar Müller | F2: =RawTable[[#This Row],[Bank_Account]] -> JO-IBAN-00024690 | G2: =RawTable[[#This Row],[Month]] -> Feb-2026 | H2: =RawTable[[#This Row],[Currency]] -> JOD | I2: =RawTable[[#This Row],[Net_Amount]] -> 1687.14 | J2: =RawTable[[#This Row],[VAT_Applicable]] -> No | K2: =RawTable[[#This Row],[VAT_Rate]] -> 0 | L2: =RawTable[[#This Row],[VAT_Amount]] -> 0 | M2: =RawTable[[#This Row],[Gross_Amount]] -> 1687.14 | N2: =RawTable[[#This Row],[Exchange_Rate]] -> 1.08643 | O2: =RawTable[[#This Row],[Amount_CHF]] -> 1832.96 | P2: =IF( OR(ValidationTable[[#This Row],[Record_ID]]="",ValidationTable[[#This Row],[Payment_Type]]="",ValidationTable[[#This Row],[Entity_Type]]="", ValidationTable[[#This Row],[Country]]="", ValidationTable[[#This Row],[Name]]="", ValidationTable[[#This Row],[Month]]="", ValidationTable[[#This Row],[Currency]]="" ), "Fail", "Pass" ) -> Pass | Q2: =IF( OR(ValidationTable[[#This Row],[Net_Amount]]<=0, ROUND(ValidationTable[[#This Row],[Net_Amount]]+ValidationTable[[#This Row],[VAT_Amount]],2)<>ROUND(ValidationTable[[#This Row],[Gross_Amount]],2) ), "Fail", "Pass" ) -> Pass | R2: =IF(ValidationTable[[#This Row],[Currency]]="","Fail","Pass") -> Pass | S2: =IF( ValidationTable[[#This Row],[Currency]]="CHF", IF(ValidationTable[[#This Row],[Exchange_Rate]]<>1,"Fail","Pass"), IF(ValidationTable[[#This Row],[Exchange_Rate]]<=0,"Fail","Pass") ) -> Pass | T2: =IF(ValidationTable[[#This Row],[VAT_Applicable]]="Yes", IF( ROUND(ValidationTable[[#This Row],[Net_Amount]]*ValidationTable[[#This Row],[VAT_Rate]],2)<>ROUND(ValidationTable[[#This Row],[VAT_Amount]],2), "Fail", "Pass" ), IF( OR(ValidationTable[[#This Row],[VAT_Rate]]<>0,ValidationTable[[#This Row],[VAT_Amount]]<>0 ), "Fail", "Pass" ) ) -> Pass | U2: =IF(LEN(TRIM(ValidationTable[[#This Row],[Bank_Account]]))=0,"Fail","Pass") -> Pass | V2: =IF( COUNTIF(ValidationTable[Record_ID],ValidationTable[[#This Row],[Record_ID]])>1, "Fail", "Pass" ) -> Pass | W2: =IF( COUNTIF(ValidationTable[[#This Row],[RequiredField_Validation]]:ValidationTable[[#This Row],[Duplicate_Validation]],"Fail")>0, "Fail", "Pass" ) -> Pass | X2: =IF(ValidationTable[[#This Row],[Validation_Result]]="Pass","Yes","No") -> Yes
A3: =RawTable[[#This Row],[Record_ID]] -> 2 | B3: =RawTable[[#This Row],[Payment_Type]] -> Payroll | C3: =RawTable[[#This Row],[Entity_Type]] -> Employee | D3: =RawTable[[#This Row],[Country]] -> USA | E3: =RawTable[[#This Row],[Name]] -> Ahmed Schmidt | F3: =RawTable[[#This Row],[Bank_Account]] -> US-RT-000003702-AC-0000017034 | G3: =RawTable[[#This Row],[Month]] -> Mar-2026 | H3: =RawTable[[#This Row],[Currency]] -> USD | I3: =RawTable[[#This Row],[Net_Amount]] -> 0 | J3: =RawTable[[#This Row],[VAT_Applicable]] -> No | K3: =RawTable[[#This Row],[VAT_Rate]] -> 0 | L3: =RawTable[[#This Row],[VAT_Amount]] -> 0 | M3: =RawTable[[#This Row],[Gross_Amount]] -> 0 | N3: =RawTable[[#This Row],[Exchange_Rate]] -> 0.77018 | O3: =RawTable[[#This Row],[Amount_CHF]] -> 0 | P3: =IF( OR(ValidationTable[[#This Row],[Record_ID]]="",ValidationTable[[#This Row],[Payment_Type]]="",ValidationTable[[#This Row],[Entity_Type]]="", ValidationTable[[#This Row],[Country]]="", ValidationTable[[#This Row],[Name]]="", ValidationTable[[#This Row],[Month]]="", ValidationTable[[#This Row],[Currency]]="" ), "Fail", "Pass" ) -> Pass | Q3: =IF( OR(ValidationTable[[#This Row],[Net_Amount]]<=0, ROUND(ValidationTable[[#This Row],[Net_Amount]]+ValidationTable[[#This Row],[VAT_Amount]],2)<>ROUND(ValidationTable[[#This Row],[Gross_Amount]],2) ), "Fail", "Pass" ) -> Fail | R3: =IF(ValidationTable[[#This Row],[Currency]]="","Fail","Pass") -> Pass | S3: =IF( ValidationTable[[#This Row],[Currency]]="CHF", IF(ValidationTable[[#This Row],[Exchange_Rate]]<>1,"Fail","Pass"), IF(ValidationTable[[#This Row],[Exchange_Rate]]<=0,"Fail","Pass") ) -> Pass | T3: =IF(ValidationTable[[#This Row],[VAT_Applicable]]="Yes", IF( ROUND(ValidationTable[[#This Row],[Net_Amount]]*ValidationTable[[#This Row],[VAT_Rate]],2)<>ROUND(ValidationTable[[#This Row],[VAT_Amount]],2), "Fail", "Pass" ), IF( OR(ValidationTable[[#This Row],[VAT_Rate]]<>0,ValidationTable[[#This Row],[VAT_Amount]]<>0 ), "Fail", "Pass" ) ) -> Pass | U3: =IF(LEN(TRIM(ValidationTable[[#This Row],[Bank_Account]]))=0,"Fail","Pass") -> Pass | V3: =IF( COUNTIF(ValidationTable[Record_ID],ValidationTable[[#This Row],[Record_ID]])>1, "Fail", "Pass" ) -> Pass | W3: =IF( COUNTIF(ValidationTable[[#This Row],[RequiredField_Validation]]:ValidationTable[[#This Row],[Duplicate_Validation]],"Fail")>0, "Fail", "Pass" ) -> Fail | X3: =IF(ValidationTable[[#This Row],[Validation_Result]]="Pass","Yes","No") -> No
A4: =RawTable[[#This Row],[Record_ID]] -> 3 | B4: =RawTable[[#This Row],[Payment_Type]] -> Payroll | C4: =RawTable[[#This Row],[Entity_Type]] -> Employee | D4: =RawTable[[#This Row],[Country]] -> USA | E4: =RawTable[[#This Row],[Name]] -> David Wilson | F4: =RawTable[[#This Row],[Bank_Account]] -> US-RT-000004936-AC-0000022712 | G4: =RawTable[[#This Row],[Month]] -> Feb-2026 | H4: =RawTable[[#This Row],[Currency]] -> USD | I4: =RawTable[[#This Row],[Net_Amount]] -> 7521.5 | J4: =RawTable[[#This Row],[VAT_Applicable]] -> No | K4: =RawTable[[#This Row],[VAT_Rate]] -> 0 | L4: =RawTable[[#This Row],[VAT_Amount]] -> 0 | M4: =RawTable[[#This Row],[Gross_Amount]] -> 7521.5 | N4: =RawTable[[#This Row],[Exchange_Rate]] -> 0.77018 | O4: =RawTable[[#This Row],[Amount_CHF]] -> 5792.91 | P4: =IF( OR(ValidationTable[[#This Row],[Record_ID]]="",ValidationTable[[#This Row],[Payment_Type]]="",ValidationTable[[#This Row],[Entity_Type]]="", ValidationTable[[#This Row],[Country]]="", ValidationTable[[#This Row],[Name]]="", ValidationTable[[#This Row],[Month]]="", ValidationTable[[#This Row],[Currency]]="" ), "Fail", "Pass" ) -> Pass | Q4: =IF( OR(ValidationTable[[#This Row],[Net_Amount]]<=0, ROUND(ValidationTable[[#This Row],[Net_Amount]]+ValidationTable[[#This Row],[VAT_Amount]],2)<>ROUND(ValidationTable[[#This Row],[Gross_Amount]],2) ), "Fail", "Pass" ) -> Pass | R4: =IF(ValidationTable[[#This Row],[Currency]]="","Fail","Pass") -> Pass | S4: =IF( ValidationTable[[#This Row],[Currency]]="CHF", IF(ValidationTable[[#This Row],[Exchange_Rate]]<>1,"Fail","Pass"), IF(ValidationTable[[#This Row],[Exchange_Rate]]<=0,"Fail","Pass") ) -> Pass | T4: =IF(ValidationTable[[#This Row],[VAT_Applicable]]="Yes", IF( ROUND(ValidationTable[[#This Row],[Net_Amount]]*ValidationTable[[#This Row],[VAT_Rate]],2)<>ROUND(ValidationTable[[#This Row],[VAT_Amount]],2), "Fail", "Pass" ), IF( OR(ValidationTable[[#This Row],[VAT_Rate]]<>0,ValidationTable[[#This Row],[VAT_Amount]]<>0 ), "Fail", "Pass" ) ) -> Pass | U4: =IF(LEN(TRIM(ValidationTable[[#This Row],[Bank_Account]]))=0,"Fail","Pass") -> Pass | V4: =IF( COUNTIF(ValidationTable[Record_ID],ValidationTable[[#This Row],[Record_ID]])>1, "Fail", "Pass" ) -> Pass | W4: =IF( COUNTIF(ValidationTable[[#This Row],[RequiredField_Validation]]:ValidationTable[[#This Row],[Duplicate_Validation]],"Fail")>0, "Fail", "Pass" ) -> Pass | X4: =IF(ValidationTable[[#This Row],[Validation_Result]]="Pass","Yes","No") -> Yes
A5: =RawTable[[#This Row],[Record_ID]] -> 4 | B5: =RawTable[[#This Row],[Payment_Type]] -> Payroll | C5: =RawTable[[#This Row],[Entity_Type]] -> Employee | D5: =RawTable[[#This Row],[Country]] -> USA | E5: =RawTable[[#This Row],[Name]] -> John Smith | F5: =RawTable[[#This Row],[Bank_Account]] -> US-RT-000006170-AC-0000028390 | G5: =RawTable[[#This Row],[Month]] -> Mar-2026 | H5: =RawTable[[#This Row],[Currency]] -> USD | I5: =RawTable[[#This Row],[Net_Amount]] -> 7077 | J5: =RawTable[[#This Row],[VAT_Applicable]] -> No | K5: =RawTable[[#This Row],[VAT_Rate]] -> 0 | L5: =RawTable[[#This Row],[VAT_Amount]] -> 0 | M5: =RawTable[[#This Row],[Gross_Amount]] -> 7077 | N5: =RawTable[[#This Row],[Exchange_Rate]] -> 0.77018 | O5: =RawTable[[#This Row],[Amount_CHF]] -> 5450.56 | P5: =IF( OR(ValidationTable[[#This Row],[Record_ID]]="",ValidationTable[[#This Row],[Payment_Type]]="",ValidationTable[[#This Row],[Entity_Type]]="", ValidationTable[[#This Row],[Country]]="", ValidationTable[[#This Row],[Name]]="", ValidationTable[[#This Row],[Month]]="", ValidationTable[[#This Row],[Currency]]="" ), "Fail", "Pass" ) -> Pass | Q5: =IF( OR(ValidationTable[[#This Row],[Net_Amount]]<=0, ROUND(ValidationTable[[#This Row],[Net_Amount]]+ValidationTable[[#This Row],[VAT_Amount]],2)<>ROUND(ValidationTable[[#This Row],[Gross_Amount]],2) ), "Fail", "Pass" ) -> Pass | R5: =IF(ValidationTable[[#This Row],[Currency]]="","Fail","Pass") -> Pass | S5: =IF( ValidationTable[[#This Row],[Currency]]="CHF", IF(ValidationTable[[#This Row],[Exchange_Rate]]<>1,"Fail","Pass"), IF(ValidationTable[[#This Row],[Exchange_Rate]]<=0,"Fail","Pass") ) -> Pass | T5: =IF(ValidationTable[[#This Row],[VAT_Applicable]]="Yes", IF( ROUND(ValidationTable[[#This Row],[Net_Amount]]*ValidationTable[[#This Row],[VAT_Rate]],2)<>ROUND(ValidationTable[[#This Row],[VAT_Amount]],2), "Fail", "Pass" ), IF( OR(ValidationTable[[#This Row],[VAT_Rate]]<>0,ValidationTable[[#This Row],[VAT_Amount]]<>0 ), "Fail", "Pass" ) ) -> Pass | U5: =IF(LEN(TRIM(ValidationTable[[#This Row],[Bank_Account]]))=0,"Fail","Pass") -> Pass | V5: =IF( COUNTIF(ValidationTable[Record_ID],ValidationTable[[#This Row],[Record_ID]])>1, "Fail", "Pass" ) -> Pass | W5: =IF( COUNTIF(ValidationTable[[#This Row],[RequiredField_Validation]]:ValidationTable[[#This Row],[Duplicate_Validation]],"Fail")>0, "Fail", "Pass" ) -> Pass | X5: =IF(ValidationTable[[#This Row],[Validation_Result]]="Pass","Yes","No") -> Yes
A6: =RawTable[[#This Row],[Record_ID]] -> 5 | B6: =RawTable[[#This Row],[Payment_Type]] -> Payroll | C6: =RawTable[[#This Row],[Entity_Type]] -> Employee | D6: =RawTable[[#This Row],[Country]] -> Germany | E6: =RawTable[[#This Row],[Name]] -> Anna Khan | F6: =RawTable[[#This Row],[Bank_Account]] -> DE890000000000081474 | G6: =RawTable[[#This Row],[Month]] -> Feb-2026 | H6: =RawTable[[#This Row],[Currency]] -> EUR | I6: =RawTable[[#This Row],[Net_Amount]] -> 5455.2 | J6: =RawTable[[#This Row],[VAT_Applicable]] -> No | K6: =RawTable[[#This Row],[VAT_Rate]] -> 0 | L6: =RawTable[[#This Row],[VAT_Amount]] -> 0 | M6: =RawTable[[#This Row],[Gross_Amount]] -> 5455.2 | N6: =RawTable[[#This Row],[Exchange_Rate]] -> 0.90888 | O6: =RawTable[[#This Row],[Amount_CHF]] -> 4958.12 | P6: =IF( OR(ValidationTable[[#This Row],[Record_ID]]="",ValidationTable[[#This Row],[Payment_Type]]="",ValidationTable[[#This Row],[Entity_Type]]="", ValidationTable[[#This Row],[Country]]="", ValidationTable[[#This Row],[Name]]="", ValidationTable[[#This Row],[Month]]="", ValidationTable[[#This Row],[Currency]]="" ), "Fail", "Pass" ) -> Pass | Q6: =IF( OR(ValidationTable[[#This Row],[Net_Amount]]<=0, ROUND(ValidationTable[[#This Row],[Net_Amount]]+ValidationTable[[#This Row],[VAT_Amount]],2)<>ROUND(ValidationTable[[#This Row],[Gross_Amount]],2) ), "Fail", "Pass" ) -> Pass | R6: =IF(ValidationTable[[#This Row],[Currency]]="","Fail","Pass") -> Pass | S6: =IF( ValidationTable[[#This Row],[Currency]]="CHF", IF(ValidationTable[[#This Row],[Exchange_Rate]]<>1,"Fail","Pass"), IF(ValidationTable[[#This Row],[Exchange_Rate]]<=0,"Fail","Pass") ) -> Pass | T6: =IF(ValidationTable[[#This Row],[VAT_Applicable]]="Yes", IF( ROUND(ValidationTable[[#This Row],[Net_Amount]]*ValidationTable[[#This Row],[VAT_Rate]],2)<>ROUND(ValidationTable[[#This Row],[VAT_Amount]],2), "Fail", "Pass" ), IF( OR(ValidationTable[[#This Row],[VAT_Rate]]<>0,ValidationTable[[#This Row],[VAT_Amount]]<>0 ), "Fail", "Pass" ) ) -> Pass | U6: =IF(LEN(TRIM(ValidationTable[[#This Row],[Bank_Account]]))=0,"Fail","Pass") -> Pass | V6: =IF( COUNTIF(ValidationTable[Record_ID],ValidationTable[[#This Row],[Record_ID]])>1, "Fail", "Pass" ) -> Pass | W6: =IF( COUNTIF(ValidationTable[[#This Row],[RequiredField_Validation]]:ValidationTable[[#This Row],[Duplicate_Validation]],"Fail")>0, "Fail", "Pass" ) -> Pass | X6: =IF(ValidationTable[[#This Row],[Validation_Result]]="Pass","Yes","No") -> Yes
A7: =RawTable[[#This Row],[Record_ID]] -> 6 | B7: =RawTable[[#This Row],[Payment_Type]] -> Payroll | C7: =RawTable[[#This Row],[Entity_Type]] -> Employee | D7: =RawTable[[#This Row],[Country]] -> Germany | E7: =RawTable[[#This Row],[Name]] -> David Haddad | F7: =RawTable[[#This Row],[Bank_Account]] -> DE890000000000095053 | G7: =RawTable[[#This Row],[Month]] -> Jan-2026 | H7: =RawTable[[#This Row],[Currency]] -> EUR | I7: =RawTable[[#This Row],[Net_Amount]] -> 5775 | J7: =RawTable[[#This Row],[VAT_Applicable]] -> No | K7: =RawTable[[#This Row],[VAT_Rate]] -> 0 | L7: =RawTable[[#This Row],[VAT_Amount]] -> 0 | M7: =RawTable[[#This Row],[Gross_Amount]] -> 5775 | N7: =RawTable[[#This Row],[Exchange_Rate]] -> 0.90888 | O7: =RawTable[[#This Row],[Amount_CHF]] -> 5248.78 | P7: =IF( OR(ValidationTable[[#This Row],[Record_ID]]="",ValidationTable[[#This Row],[Payment_Type]]="",ValidationTable[[#This Row],[Entity_Type]]="", ValidationTable[[#This Row],[Country]]="", ValidationTable[[#This Row],[Name]]="", ValidationTable[[#This Row],[Month]]="", ValidationTable[[#This Row],[Currency]]="" ), "Fail", "Pass" ) -> Pass | Q7: =IF( OR(ValidationTable[[#This Row],[Net_Amount]]<=0, ROUND(ValidationTable[[#This Row],[Net_Amount]]+ValidationTable[[#This Row],[VAT_Amount]],2)<>ROUND(ValidationTable[[#This Row],[Gross_Amount]],2) ), "Fail", "Pass" ) -> Pass | R7: =IF(ValidationTable[[#This Row],[Currency]]="","Fail","Pass") -> Pass | S7: =IF( ValidationTable[[#This Row],[Currency]]="CHF", IF(ValidationTable[[#This Row],[Exchange_Rate]]<>1,"Fail","Pass"), IF(ValidationTable[[#This Row],[Exchange_Rate]]<=0,"Fail","Pass") ) -> Pass | T7: =IF(ValidationTable[[#This Row],[VAT_Applicable]]="Yes", IF( ROUND(ValidationTable[[#This Row],[Net_Amount]]*ValidationTable[[#This Row],[VAT_Rate]],2)<>ROUND(ValidationTable[[#This Row],[VAT_Amount]],2), "Fail", "Pass" ), IF( OR(ValidationTable[[#This Row],[VAT_Rate]]<>0,ValidationTable[[#This Row],[VAT_Amount]]<>0 ), "Fail", "Pass" ) ) -> Pass | U7: =IF(LEN(TRIM(ValidationTable[[#This Row],[Bank_Account]]))=0,"Fail","Pass") -> Pass | V7: =IF( COUNTIF(ValidationTable[Record_ID],ValidationTable[[#This Row],[Record_ID]])>1, "Fail", "Pass" ) -> Pass | W7: =IF( COUNTIF(ValidationTable[[#This Row],[RequiredField_Validation]]:ValidationTable[[#This Row],[Duplicate_Validation]],"Fail")>0, "Fail", "Pass" ) -> Pass | X7: =IF(ValidationTable[[#This Row],[Validation_Result]]="Pass","Yes","No") -> Yes
A8: =RawTable[[#This Row],[Record_ID]] -> 7 | B8: =RawTable[[#This Row],[Payment_Type]] -> Payroll | C8: =RawTable[[#This Row],[Entity_Type]] -> Employee | D8: =RawTable[[#This Row],[Country]] -> Jordan | E8: =RawTable[[#This Row],[Name]] -> Anna Taylor | F8: =RawTable[[#This Row],[Bank_Account]] -> JO-IBAN-00098760 | G8: =RawTable[[#This Row],[Month]] -> Mar-2026 | H8: =RawTable[[#This Row],[Currency]] -> JOD | I8: =RawTable[[#This Row],[Net_Amount]] -> 1837.8 | J8: =RawTable[[#This Row],[VAT_Applicable]] -> No | K8: =RawTable[[#This Row],[VAT_Rate]] -> 0 | L8: =RawTable[[#This Row],[VAT_Amount]] -> 0 | M8: =RawTable[[#This Row],[Gross_Amount]] -> 1837.8 | N8: =RawTable[[#This Row],[Exchange_Rate]] -> 1.08643 | O8: =RawTable[[#This Row],[Amount_CHF]] -> 1996.64 | P8: =IF( OR(ValidationTable[[#This Row],[Record_ID]]="",ValidationTable[[#This Row],[Payment_Type]]="",ValidationTable[[#This Row],[Entity_Type]]="", ValidationTable[[#This Row],[Country]]="", ValidationTable[[#This Row],[Name]]="", ValidationTable[[#This Row],[Month]]="", ValidationTable[[#This Row],[Currency]]="" ), "Fail", "Pass" ) -> Pass | Q8: =IF( OR(ValidationTable[[#This Row],[Net_Amount]]<=0, ROUND(ValidationTable[[#This Row],[Net_Amount]]+ValidationTable[[#This Row],[VAT_Amount]],2)<>ROUND(ValidationTable[[#This Row],[Gross_Amount]],2) ), "Fail", "Pass" ) -> Pass | R8: =IF(ValidationTable[[#This Row],[Currency]]="","Fail","Pass") -> Pass | S8: =IF( ValidationTable[[#This Row],[Currency]]="CHF", IF(ValidationTable[[#This Row],[Exchange_Rate]]<>1,"Fail","Pass"), IF(ValidationTable[[#This Row],[Exchange_Rate]]<=0,"Fail","Pass") ) -> Pass | T8: =IF(ValidationTable[[#This Row],[VAT_Applicable]]="Yes", IF( ROUND(ValidationTable[[#This Row],[Net_Amount]]*ValidationTable[[#This Row],[VAT_Rate]],2)<>ROUND(ValidationTable[[#This Row],[VAT_Amount]],2), "Fail", "Pass" ), IF( OR(ValidationTable[[#This Row],[VAT_Rate]]<>0,ValidationTable[[#This Row],[VAT_Amount]]<>0 ), "Fail", "Pass" ) ) -> Pass | U8: =IF(LEN(TRIM(ValidationTable[[#This Row],[Bank_Account]]))=0,"Fail","Pass") -> Pass | V8: =IF( COUNTIF(ValidationTable[Record_ID],ValidationTable[[#This Row],[Record_ID]])>1, "Fail", "Pass" ) -> Pass | W8: =IF( COUNTIF(ValidationTable[[#This Row],[RequiredField_Validation]]:ValidationTable[[#This Row],[Duplicate_Validation]],"Fail")>0, "Fail", "Pass" ) -> Pass | X8: =IF(ValidationTable[[#This Row],[Validation_Result]]="Pass","Yes","No") -> Yes
A9: =RawTable[[#This Row],[Record_ID]] -> 8 | B9: =RawTable[[#This Row],[Payment_Type]] -> Payroll | C9: =RawTable[[#This Row],[Entity_Type]] -> Employee | D9: =RawTable[[#This Row],[Country]] -> Germany | E9: =RawTable[[#This Row],[Name]] -> David Khan | F9: =RawTable[[#This Row],[Bank_Account]] -> DE890000000000122211 | G9: =RawTable[[#This Row],[Month]] -> Mar-2026 | H9: =RawTable[[#This Row],[Currency]] -> EUR | I9: =RawTable[[#This Row],[Net_Amount]] -> 6138.6 | J9: =RawTable[[#This Row],[VAT_Applicable]] -> No | K9: =RawTable[[#This Row],[VAT_Rate]] -> 0 | L9: =RawTable[[#This Row],[VAT_Amount]] -> 0 | M9: =RawTable[[#This Row],[Gross_Amount]] -> 6138.6 | N9: =RawTable[[#This Row],[Exchange_Rate]] -> 0.90888 | O9: =RawTable[[#This Row],[Amount_CHF]] -> 5579.25 | P9: =IF( OR(ValidationTable[[#This Row],[Record_ID]]="",ValidationTable[[#This Row],[Payment_Type]]="",ValidationTable[[#This Row],[Entity_Type]]="", ValidationTable[[#This Row],[Country]]="", ValidationTable[[#This Row],[Name]]="", ValidationTable[[#This Row],[Month]]="", ValidationTable[[#This Row],[Currency]]="" ), "Fail", "Pass" ) -> Pass | Q9: =IF( OR(ValidationTable[[#This Row],[Net_Amount]]<=0, ROUND(ValidationTable[[#This Row],[Net_Amount]]+ValidationTable[[#This Row],[VAT_Amount]],2)<>ROUND(ValidationTable[[#This Row],[Gross_Amount]],2) ), "Fail", "Pass" ) -> Pass | R9: =IF(ValidationTable[[#This Row],[Currency]]="","Fail","Pass") -> Pass | S9: =IF( ValidationTable[[#This Row],[Currency]]="CHF", IF(ValidationTable[[#This Row],[Exchange_Rate]]<>1,"Fail","Pass"), IF(ValidationTable[[#This Row],[Exchange_Rate]]<=0,"Fail","Pass") ) -> Pass | T9: =IF(ValidationTable[[#This Row],[VAT_Applicable]]="Yes", IF( ROUND(ValidationTable[[#This Row],[Net_Amount]]*ValidationTable[[#This Row],[VAT_Rate]],2)<>ROUND(ValidationTable[[#This Row],[VAT_Amount]],2), "Fail", "Pass" ), IF( OR(ValidationTable[[#This Row],[VAT_Rate]]<>0,ValidationTable[[#This Row],[VAT_Amount]]<>0 ), "Fail", "Pass" ) ) -> Pass | U9: =IF(LEN(TRIM(ValidationTable[[#This Row],[Bank_Account]]))=0,"Fail","Pass") -> Pass | V9: =IF( COUNTIF(ValidationTable[Record_ID],ValidationTable[[#This Row],[Record_ID]])>1, "Fail", "Pass" ) -> Pass | W9: =IF( COUNTIF(ValidationTable[[#This Row],[RequiredField_Validation]]:ValidationTable[[#This Row],[Duplicate_Validation]],"Fail")>0, "Fail", "Pass" ) -> Pass | X9: =IF(ValidationTable[[#This Row],[Validation_Result]]="Pass","Yes","No") -> Yes
A10: =RawTable[[#This Row],[Record_ID]] -> 9 | B10: =RawTable[[#This Row],[Payment_Type]] -> Payroll | C10: =RawTable[[#This Row],[Entity_Type]] -> Employee | D10: =RawTable[[#This Row],[Country]] -> USA | E10: =RawTable[[#This Row],[Name]] -> Lina Wilson | F10: =RawTable[[#This Row],[Bank_Account]] -> US-RT-000012340-AC-0000056780 | G10: =RawTable[[#This Row],[Month]] -> Mar-2026 | H10: =RawTable[[#This Row],[Currency]] -> USD | I10: =RawTable[[#This Row],[Net_Amount]] -> 7459.9 | J10: =RawTable[[#This Row],[VAT_Applicable]] -> No | K10: =RawTable[[#This Row],[VAT_Rate]] -> 0 | L10: =RawTable[[#This Row],[VAT_Amount]] -> 0 | M10: =RawTable[[#This Row],[Gross_Amount]] -> 7459.9 | N10: =RawTable[[#This Row],[Exchange_Rate]] -> 0.77018 | O10: =RawTable[[#This Row],[Amount_CHF]] -> 5745.47 | P10: =IF( OR(ValidationTable[[#This Row],[Record_ID]]="",ValidationTable[[#This Row],[Payment_Type]]="",ValidationTable[[#This Row],[Entity_Type]]="", ValidationTable[[#This Row],[Country]]="", ValidationTable[[#This Row],[Name]]="", ValidationTable[[#This Row],[Month]]="", ValidationTable[[#This Row],[Currency]]="" ), "Fail", "Pass" ) -> Pass | Q10: =IF( OR(ValidationTable[[#This Row],[Net_Amount]]<=0, ROUND(ValidationTable[[#This Row],[Net_Amount]]+ValidationTable[[#This Row],[VAT_Amount]],2)<>ROUND(ValidationTable[[#This Row],[Gross_Amount]],2) ), "Fail", "Pass" ) -> Pass | R10: =IF(ValidationTable[[#This Row],[Currency]]="","Fail","Pass") -> Pass | S10: =IF( ValidationTable[[#This Row],[Currency]]="CHF", IF(ValidationTable[[#This Row],[Exchange_Rate]]<>1,"Fail","Pass"), IF(ValidationTable[[#This Row],[Exchange_Rate]]<=0,"Fail","Pass") ) -> Pass | T10: =IF(ValidationTable[[#This Row],[VAT_Applicable]]="Yes", IF( ROUND(ValidationTable[[#This Row],[Net_Amount]]*ValidationTable[[#This Row],[VAT_Rate]],2)<>ROUND(ValidationTable[[#This Row],[VAT_Amount]],2), "Fail", "Pass" ), IF( OR(ValidationTable[[#This Row],[VAT_Rate]]<>0,ValidationTable[[#This Row],[VAT_Amount]]<>0 ), "Fail", "Pass" ) ) -> Pass | U10: =IF(LEN(TRIM(ValidationTable[[#This Row],[Bank_Account]]))=0,"Fail","Pass") -> Pass | V10: =IF( COUNTIF(ValidationTable[Record_ID],ValidationTable[[#This Row],[Record_ID]])>1, "Fail", "Pass" ) -> Pass | W10: =IF( COUNTIF(ValidationTable[[#This Row],[RequiredField_Validation]]:ValidationTable[[#This Row],[Duplicate_Validation]],"Fail")>0, "Fail", "Pass" ) -> Pass | X10: =IF(ValidationTable[[#This Row],[Validation_Result]]="Pass","Yes","No") -> Yes
A11: =RawTable[[#This Row],[Record_ID]] -> 10 | B11: =RawTable[[#This Row],[Payment_Type]] -> Payroll | C11: =RawTable[[#This Row],[Entity_Type]] -> Employee | D11: =RawTable[[#This Row],[Country]] -> USA | E11: =RawTable[[#This Row],[Name]] -> Michael Wilson | F11: =RawTable[[#This Row],[Bank_Account]] -> US-RT-000013574-AC-0000062458 | G11: =RawTable[[#This Row],[Month]] -> Mar-2026 | H11: =RawTable[[#This Row],[Currency]] -> USD | I11: =RawTable[[#This Row],[Net_Amount]] -> 7142.8 | J11: =RawTable[[#This Row],[VAT_Applicable]] -> No | K11: =RawTable[[#This Row],[VAT_Rate]] -> 0 | L11: =RawTable[[#This Row],[VAT_Amount]] -> 0 | M11: =RawTable[[#This Row],[Gross_Amount]] -> 7142.8 | N11: =RawTable[[#This Row],[Exchange_Rate]] -> 0.77018 | O11: =RawTable[[#This Row],[Amount_CHF]] -> 5501.24 | P11: =IF( OR(ValidationTable[[#This Row],[Record_ID]]="",ValidationTable[[#This Row],[Payment_Type]]="",ValidationTable[[#This Row],[Entity_Type]]="", ValidationTable[[#This Row],[Country]]="", ValidationTable[[#This Row],[Name]]="", ValidationTable[[#This Row],[Month]]="", ValidationTable[[#This Row],[Currency]]="" ), "Fail", "Pass" ) -> Pass | Q11: =IF( OR(ValidationTable[[#This Row],[Net_Amount]]<=0, ROUND(ValidationTable[[#This Row],[Net_Amount]]+ValidationTable[[#This Row],[VAT_Amount]],2)<>ROUND(ValidationTable[[#This Row],[Gross_Amount]],2) ), "Fail", "Pass" ) -> Pass | R11: =IF(ValidationTable[[#This Row],[Currency]]="","Fail","Pass") -> Pass | S11: =IF( ValidationTable[[#This Row],[Currency]]="CHF", IF(ValidationTable[[#This Row],[Exchange_Rate]]<>1,"Fail","Pass"), IF(ValidationTable[[#This Row],[Exchange_Rate]]<=0,"Fail","Pass") ) -> Pass | T11: =IF(ValidationTable[[#This Row],[VAT_Applicable]]="Yes", IF( ROUND(ValidationTable[[#This Row],[Net_Amount]]*ValidationTable[[#This Row],[VAT_Rate]],2)<>ROUND(ValidationTable[[#This Row],[VAT_Amount]],2), "Fail", "Pass" ), IF( OR(ValidationTable[[#This Row],[VAT_Rate]]<>0,ValidationTable[[#This Row],[VAT_Amount]]<>0 ), "Fail", "Pass" ) ) -> Pass | U11: =IF(LEN(TRIM(ValidationTable[[#This Row],[Bank_Account]]))=0,"Fail","Pass") -> Pass | V11: =IF( COUNTIF(ValidationTable[Record_ID],ValidationTable[[#This Row],[Record_ID]])>1, "Fail", "Pass" ) -> Pass | W11: =IF( COUNTIF(ValidationTable[[#This Row],[RequiredField_Validation]]:ValidationTable[[#This Row],[Duplicate_Validation]],"Fail")>0, "Fail", "Pass" ) -> Pass | X11: =IF(ValidationTable[[#This Row],[Validation_Result]]="Pass","Yes","No") -> Yes
A12: =RawTable[[#This Row],[Record_ID]] -> 11 | B12: =RawTable[[#This Row],[Payment_Type]] -> Payroll | C12: =RawTable[[#This Row],[Entity_Type]] -> Employee | D12: =RawTable[[#This Row],[Country]] -> Jordan | E12: =RawTable[[#This Row],[Name]] -> David Smith | F12: =RawTable[[#This Row],[Bank_Account]] -> JO-IBAN-00148140 | G12: =RawTable[[#This Row],[Month]] -> Feb-2026 | H12: =RawTable[[#This Row],[Currency]] -> JOD | I12: =RawTable[[#This Row],[Net_Amount]] -> 1971.72 | J12: =RawTable[[#This Row],[VAT_Applicable]] -> No | K12: =RawTable[[#This Row],[VAT_Rate]] -> 0 | L12: =RawTable[[#This Row],[VAT_Amount]] -> 0 | M12: =RawTable[[#This Row],[Gross_Amount]] -> 1971.72 | N12: =RawTable[[#This Row],[Exchange_Rate]] -> 1.08643 | O12: =RawTable[[#This Row],[Amount_CHF]] -> 2142.14 | P12: =IF( OR(ValidationTable[[#This Row],[Record_ID]]="",ValidationTable[[#This Row],[Payment_Type]]="",ValidationTable[[#This Row],[Entity_Type]]="", ValidationTable[[#This Row],[Country]]="", ValidationTable[[#This Row],[Name]]="", ValidationTable[[#This Row],[Month]]="", ValidationTable[[#This Row],[Currency]]="" ), "Fail", "Pass" ) -> Pass | Q12: =IF( OR(ValidationTable[[#This Row],[Net_Amount]]<=0, ROUND(ValidationTable[[#This Row],[Net_Amount]]+ValidationTable[[#This Row],[VAT_Amount]],2)<>ROUND(ValidationTable[[#This Row],[Gross_Amount]],2) ), "Fail", "Pass" ) -> Pass | R12: =IF(ValidationTable[[#This Row],[Currency]]="","Fail","Pass") -> Pass | S12: =IF( ValidationTable[[#This Row],[Currency]]="CHF", IF(ValidationTable[[#This Row],[Exchange_Rate]]<>1,"Fail","Pass"), IF(ValidationTable[[#This Row],[Exchange_Rate]]<=0,"Fail","Pass") ) -> Pass | T12: =IF(ValidationTable[[#This Row],[VAT_Applicable]]="Yes", IF( ROUND(ValidationTable[[#This Row],[Net_Amount]]*ValidationTable[[#This Row],[VAT_Rate]],2)<>ROUND(ValidationTable[[#This Row],[VAT_Amount]],2), "Fail", "Pass" ), IF( OR(ValidationTable[[#This Row],[VAT_Rate]]<>0,ValidationTable[[#This Row],[VAT_Amount]]<>0 ), "Fail", "Pass" ) ) -> Pass | U12: =IF(LEN(TRIM(ValidationTable[[#This Row],[Bank_Account]]))=0,"Fail","Pass") -> Pass | V12: =IF( COUNTIF(ValidationTable[Record_ID],ValidationTable[[#This Row],[Record_ID]])>1, "Fail", "Pass" ) -> Pass | W12: =IF( COUNTIF(ValidationTable[[#This Row],[RequiredField_Validation]]:ValidationTable[[#This Row],[Duplicate_Validation]],"Fail")>0, "Fail", "Pass" ) -> Pass | X12: =IF(ValidationTable[[#This Row],[Validation_Result]]="Pass","Yes","No") -> Yes
A13: =RawTable[[#This Row],[Record_ID]] -> 12 | B13: =RawTable[[#This Row],[Payment_Type]] -> Payroll | C13: =RawTable[[#This Row],[Entity_Type]] -> Employee | D13: =RawTable[[#This Row],[Country]] -> USA | E13: =RawTable[[#This Row],[Name]] -> Michael Wilson | F13: =RawTable[[#This Row],[Bank_Account]] -> US-RT-000013574-AC-0000062458 | G13: =RawTable[[#This Row],[Month]] -> Jan-2026 | H13: =RawTable[[#This Row],[Currency]] -> USD | I13: =RawTable[[#This Row],[Net_Amount]] -> 7249.94 | J13: =RawTable[[#This Row],[VAT_Applicable]] -> No | K13: =RawTable[[#This Row],[VAT_Rate]] -> 0 | L13: =RawTable[[#This Row],[VAT_Amount]] -> 0 | M13: =RawTable[[#This Row],[Gross_Amount]] -> 7249.94 | N13: =RawTable[[#This Row],[Exchange_Rate]] -> 0.77018 | O13: =RawTable[[#This Row],[Amount_CHF]] -> 5583.76 | P13: =IF( OR(ValidationTable[[#This Row],[Record_ID]]="",ValidationTable[[#This Row],[Payment_Type]]="",ValidationTable[[#This Row],[Entity_Type]]="", ValidationTable[[#This Row],[Country]]="", ValidationTable[[#This Row],[Name]]="", ValidationTable[[#This Row],[Month]]="", ValidationTable[[#This Row],[Currency]]="" ), "Fail", "Pass" ) -> Pass | Q13: =IF( OR(ValidationTable[[#This Row],[Net_Amount]]<=0, ROUND(ValidationTable[[#This Row],[Net_Amount]]+ValidationTable[[#This Row],[VAT_Amount]],2)<>ROUND(ValidationTable[[#This Row],[Gross_Amount]],2) ), "Fail", "Pass" ) -> Pass | R13: =IF(ValidationTable[[#This Row],[Currency]]="","Fail","Pass") -> Pass | S13: =IF( ValidationTable[[#This Row],[Currency]]="CHF", IF(ValidationTable[[#This Row],[Exchange_Rate]]<>1,"Fail","Pass"), IF(ValidationTable[[#This Row],[Exchange_Rate]]<=0,"Fail","Pass") ) -> Pass | T13: =IF(ValidationTable[[#This Row],[VAT_Applicable]]="Yes", IF( ROUND(ValidationTable[[#This Row],[Net_Amount]]*ValidationTable[[#This Row],[VAT_Rate]],2)<>ROUND(ValidationTable[[#This Row],[VAT_Amount]],2), "Fail", "Pass" ), IF( OR(ValidationTable[[#This Row],[VAT_Rate]]<>0,ValidationTable[[#This Row],[VAT_Amount]]<>0 ), "Fail", "Pass" ) ) -> Pass | U13: =IF(LEN(TRIM(ValidationTable[[#This Row],[Bank_Account]]))=0,"Fail","Pass") -> Pass | V13: =IF( COUNTIF(ValidationTable[Record_ID],ValidationTable[[#This Row],[Record_ID]])>1, "Fail", "Pass" ) -> Pass | W13: =IF( COUNTIF(ValidationTable[[#This Row],[RequiredField_Validation]]:ValidationTable[[#This Row],[Duplicate_Validation]],"Fail")>0, "Fail", "Pass" ) -> Pass | X13: =IF(ValidationTable[[#This Row],[Validation_Result]]="Pass","Yes","No") -> Yes
... A132: =RawTable[[#This Row],[Record_ID]] -> 131 | B132: =RawTable[[#This Row],[Payment_Type]] -> Payroll | C132: =RawTable[[#This Row],[Entity_Type]] -> Employee | D132: =RawTable[[#This Row],[Country]] -> USA | E132: =RawTable[[#This Row],[Name]] -> John Müller | F132: =RawTable[[#This Row],[Bank_Account]] -> CH930000000001382080 | G132: =RawTable[[#This Row],[Month]] -> Mar-2026 | H132: =RawTable[[#This Row],[Currency]] -> USD | I132: =RawTable[[#This Row],[Net_Amount]] -> 6871.25 | J132: =RawTable[[#This Row],[VAT_Applicable]] -> No | K132: =RawTable[[#This Row],[VAT_Rate]] -> 0 | L132: =RawTable[[#This Row],[VAT_Amount]] -> 0 | M132: =RawTable[[#This Row],[Gross_Amount]] -> 6871.25 | N132: =RawTable[[#This Row],[Exchange_Rate]] -> 0.77018 | O132: =RawTable[[#This Row],[Amount_CHF]] -> 5292.1 | P132: =IF( OR(ValidationTable[[#This Row],[Record_ID]]="",ValidationTable[[#This Row],[Payment_Type]]="",ValidationTable[[#This Row],[Entity_Type]]="", ValidationTable[[#This Row],[Country]]="", ValidationTable[[#This Row],[Name]]="", ValidationTable[[#This Row],[Month]]="", ValidationTable[[#This Row],[Currency]]="" ), "Fail", "Pass" ) -> Pass | Q132: =IF( OR(ValidationTable[[#This Row],[Net_Amount]]<=0, ROUND(ValidationTable[[#This Row],[Net_Amount]]+ValidationTable[[#This Row],[VAT_Amount]],2)<>ROUND(ValidationTable[[#This Row],[Gross_Amount]],2) ), "Fail", "Pass" ) -> Pass | R132: =IF(ValidationTable[[#This Row],[Currency]]="","Fail","Pass") -> Pass | S132: =IF( ValidationTable[[#This Row],[Currency]]="CHF", IF(ValidationTable[[#This Row],[Exchange_Rate]]<>1,"Fail","Pass"), IF(ValidationTable[[#This Row],[Exchange_Rate]]<=0,"Fail","Pass") ) -> Pass | T132: =IF(ValidationTable[[#This Row],[VAT_Applicable]]="Yes", IF( ROUND(ValidationTable[[#This Row],[Net_Amount]]*ValidationTable[[#This Row],[VAT_Rate]],2)<>ROUND(ValidationTable[[#This Row],[VAT_Amount]],2), "Fail", "Pass" ), IF( OR(ValidationTable[[#This Row],[VAT_Rate]]<>0,ValidationTable[[#This Row],[VAT_Amount]]<>0 ), "Fail", "Pass" ) ) -> Pass | U132: =IF(LEN(TRIM(ValidationTable[[#This Row],[Bank_Account]]))=0,"Fail","Pass") -> Pass | V132: =IF( COUNTIF(ValidationTable[Record_ID],ValidationTable[[#This Row],[Record_ID]])>1, "Fail", "Pass" ) -> Pass | W132: =IF( COUNTIF(ValidationTable[[#This Row],[RequiredField_Validation]]:ValidationTable[[#This Row],[Duplicate_Validation]],"Fail")>0, "Fail", "Pass" ) -> Pass | X132: =IF(ValidationTable[[#This Row],[Validation_Result]]="Pass","Yes","No") -> Yes
A133: =RawTable[[#This Row],[Record_ID]] -> 132 | B133: =RawTable[[#This Row],[Payment_Type]] -> Payroll | C133: =RawTable[[#This Row],[Entity_Type]] -> Employee | D133: =RawTable[[#This Row],[Country]] -> USA | E133: =RawTable[[#This Row],[Name]] -> John Taylor | F133: =RawTable[[#This Row],[Bank_Account]] -> US-RT-000085146-AC-0000391782 | G133: =RawTable[[#This Row],[Month]] -> Jan-2026 | I133: =RawTable[[#This Row],[Net_Amount]] -> 6836.9 | J133: =RawTable[[#This Row],[VAT_Applicable]] -> No | K133: =RawTable[[#This Row],[VAT_Rate]] -> 0 | L133: =RawTable[[#This Row],[VAT_Amount]] -> 0 | M133: =RawTable[[#This Row],[Gross_Amount]] -> 6836.9 | N133: =RawTable[[#This Row],[Exchange_Rate]] | O133: =RawTable[[#This Row],[Amount_CHF]] | P133: =IF( OR(ValidationTable[[#This Row],[Record_ID]]="",ValidationTable[[#This Row],[Payment_Type]]="",ValidationTable[[#This Row],[Entity_Type]]="", ValidationTable[[#This Row],[Country]]="", ValidationTable[[#This Row],[Name]]="", ValidationTable[[#This Row],[Month]]="", ValidationTable[[#This Row],[Currency]]="" ), "Fail", "Pass" ) -> Fail | Q133: =IF( OR(ValidationTable[[#This Row],[Net_Amount]]<=0, ROUND(ValidationTable[[#This Row],[Net_Amount]]+ValidationTable[[#This Row],[VAT_Amount]],2)<>ROUND(ValidationTable[[#This Row],[Gross_Amount]],2) ), "Fail", "Pass" ) -> Pass | R133: =IF(ValidationTable[[#This Row],[Currency]]="","Fail","Pass") -> Fail | S133: =IF( ValidationTable[[#This Row],[Currency]]="CHF", IF(ValidationTable[[#This Row],[Exchange_Rate]]<>1,"Fail","Pass"), IF(ValidationTable[[#This Row],[Exchange_Rate]]<=0,"Fail","Pass") ) -> Pass | T133: =IF(ValidationTable[[#This Row],[VAT_Applicable]]="Yes", IF( ROUND(ValidationTable[[#This Row],[Net_Amount]]*ValidationTable[[#This Row],[VAT_Rate]],2)<>ROUND(ValidationTable[[#This Row],[VAT_Amount]],2), "Fail", "Pass" ), IF( OR(ValidationTable[[#This Row],[VAT_Rate]]<>0,ValidationTable[[#This Row],[VAT_Amount]]<>0 ), "Fail", "Pass" ) ) -> Pass | U133: =IF(LEN(TRIM(ValidationTable[[#This Row],[Bank_Account]]))=0,"Fail","Pass") -> Pass | V133: =IF( COUNTIF(ValidationTable[Record_ID],ValidationTable[[#This Row],[Record_ID]])>1, "Fail", "Pass" ) -> Pass | W133: =IF( COUNTIF(ValidationTable[[#This Row],[RequiredField_Validation]]:ValidationTable[[#This Row],[Duplicate_Validation]],"Fail")>0, "Fail", "Pass" ) -> Fail | X133: =IF(ValidationTable[[#This Row],[Validation_Result]]="Pass","Yes","No") -> No
A134: =RawTable[[#This Row],[Record_ID]] -> 133 | B134: =RawTable[[#This Row],[Payment_Type]] -> Payroll | C134: =RawTable[[#This Row],[Entity_Type]] -> Employee | D134: =RawTable[[#This Row],[Country]] -> Jordan | E134: =RawTable[[#This Row],[Name]] -> Michael Taylor | F134: =RawTable[[#This Row],[Bank_Account]] -> US-RT-000024680-AC-0000113560 | G134: =RawTable[[#This Row],[Month]] -> Jan-2026 | H134: =RawTable[[#This Row],[Currency]] -> JOD | I134: =RawTable[[#This Row],[Net_Amount]] -> 1919.34 | J134: =RawTable[[#This Row],[VAT_Applicable]] -> No | K134: =RawTable[[#This Row],[VAT_Rate]] -> 0 | L134: =RawTable[[#This Row],[VAT_Amount]] -> 0 | M134: =RawTable[[#This Row],[Gross_Amount]] -> 1919.34 | N134: =RawTable[[#This Row],[Exchange_Rate]] -> 1.08643 | O134: =RawTable[[#This Row],[Amount_CHF]] -> 2085.23 | P134: =IF( OR(ValidationTable[[#This Row],[Record_ID]]="",ValidationTable[[#This Row],[Payment_Type]]="",ValidationTable[[#This Row],[Entity_Type]]="", ValidationTable[[#This Row],[Country]]="", ValidationTable[[#This Row],[Name]]="", ValidationTable[[#This Row],[Month]]="", ValidationTable[[#This Row],[Currency]]="" ), "Fail", "Pass" ) -> Pass | Q134: =IF( OR(ValidationTable[[#This Row],[Net_Amount]]<=0, ROUND(ValidationTable[[#This Row],[Net_Amount]]+ValidationTable[[#This Row],[VAT_Amount]],2)<>ROUND(ValidationTable[[#This Row],[Gross_Amount]],2) ), "Fail", "Pass" ) -> Pass | R134: =IF(ValidationTable[[#This Row],[Currency]]="","Fail","Pass") -> Pass | S134: =IF( ValidationTable[[#This Row],[Currency]]="CHF", IF(ValidationTable[[#This Row],[Exchange_Rate]]<>1,"Fail","Pass"), IF(ValidationTable[[#This Row],[Exchange_Rate]]<=0,"Fail","Pass") ) -> Pass | T134: =IF(ValidationTable[[#This Row],[VAT_Applicable]]="Yes", IF( ROUND(ValidationTable[[#This Row],[Net_Amount]]*ValidationTable[[#This Row],[VAT_Rate]],2)<>ROUND(ValidationTable[[#This Row],[VAT_Amount]],2), "Fail", "Pass" ), IF( OR(ValidationTable[[#This Row],[VAT_Rate]]<>0,ValidationTable[[#This Row],[VAT_Amount]]<>0 ), "Fail", "Pass" ) ) -> Pass | U134: =IF(LEN(TRIM(ValidationTable[[#This Row],[Bank_Account]]))=0,"Fail","Pass") -> Pass | V134: =IF( COUNTIF(ValidationTable[Record_ID],ValidationTable[[#This Row],[Record_ID]])>1, "Fail", "Pass" ) -> Pass | W134: =IF( COUNTIF(ValidationTable[[#This Row],[RequiredField_Validation]]:ValidationTable[[#This Row],[Duplicate_Validation]],"Fail")>0, "Fail", "Pass" ) -> Pass | X134: =IF(ValidationTable[[#This Row],[Validation_Result]]="Pass","Yes","No") -> Yes
A135: =RawTable[[#This Row],[Record_ID]] -> 134 | B135: =RawTable[[#This Row],[Payment_Type]] -> Payroll | C135: =RawTable[[#This Row],[Entity_Type]] -> Employee | D135: =RawTable[[#This Row],[Country]] -> Jordan | E135: =RawTable[[#This Row],[Name]] -> Omar Khan | F135: =RawTable[[#This Row],[Bank_Account]] -> AE-IBAN-01738272 | G135: =RawTable[[#This Row],[Month]] -> Jan-2026 | H135: =RawTable[[#This Row],[Currency]] -> JOD | I135: =RawTable[[#This Row],[Net_Amount]] -> 1697.58 | J135: =RawTable[[#This Row],[VAT_Applicable]] -> No | K135: =RawTable[[#This Row],[VAT_Rate]] -> 0 | L135: =RawTable[[#This Row],[VAT_Amount]] -> 0 | M135: =RawTable[[#This Row],[Gross_Amount]] -> 1697.58 | N135: =RawTable[[#This Row],[Exchange_Rate]] -> 1.08643 | O135: =RawTable[[#This Row],[Amount_CHF]] -> 1844.3 | P135: =IF( OR(ValidationTable[[#This Row],[Record_ID]]="",ValidationTable[[#This Row],[Payment_Type]]="",ValidationTable[[#This Row],[Entity_Type]]="", ValidationTable[[#This Row],[Country]]="", ValidationTable[[#This Row],[Name]]="", ValidationTable[[#This Row],[Month]]="", ValidationTable[[#This Row],[Currency]]="" ), "Fail", "Pass" ) -> Pass | Q135: =IF( OR(ValidationTable[[#This Row],[Net_Amount]]<=0, ROUND(ValidationTable[[#This Row],[Net_Amount]]+ValidationTable[[#This Row],[VAT_Amount]],2)<>ROUND(ValidationTable[[#This Row],[Gross_Amount]],2) ), "Fail", "Pass" ) -> Pass | R135: =IF(ValidationTable[[#This Row],[Currency]]="","Fail","Pass") -> Pass | S135: =IF( ValidationTable[[#This Row],[Currency]]="CHF", IF(ValidationTable[[#This Row],[Exchange_Rate]]<>1,"Fail","Pass"), IF(ValidationTable[[#This Row],[Exchange_Rate]]<=0,"Fail","Pass") ) -> Pass | T135: =IF(ValidationTable[[#This Row],[VAT_Applicable]]="Yes", IF( ROUND(ValidationTable[[#This Row],[Net_Amount]]*ValidationTable[[#This Row],[VAT_Rate]],2)<>ROUND(ValidationTable[[#This Row],[VAT_Amount]],2), "Fail", "Pass" ), IF( OR(ValidationTable[[#This Row],[VAT_Rate]]<>0,ValidationTable[[#This Row],[VAT_Amount]]<>0 ), "Fail", "Pass" ) ) -> Pass | U135: =IF(LEN(TRIM(ValidationTable[[#This Row],[Bank_Account]]))=0,"Fail","Pass") -> Pass | V135: =IF( COUNTIF(ValidationTable[Record_ID],ValidationTable[[#This Row],[Record_ID]])>1, "Fail", "Pass" ) -> Pass | W135: =IF( COUNTIF(ValidationTable[[#This Row],[RequiredField_Validation]]:ValidationTable[[#This Row],[Duplicate_Validation]],"Fail")>0, "Fail", "Pass" ) -> Pass | X135: =IF(ValidationTable[[#This Row],[Validation_Result]]="Pass","Yes","No") -> Yes
A136: =RawTable[[#This Row],[Record_ID]] -> 135 | B136: =RawTable[[#This Row],[Payment_Type]] -> Payroll | C136: =RawTable[[#This Row],[Entity_Type]] -> Employee | D136: =RawTable[[#This Row],[Country]] -> USA | E136: =RawTable[[#This Row],[Name]] -> Michael Taylor | F136: =RawTable[[#This Row],[Bank_Account]] -> US-RT-000024680-AC-0000113560 | G136: =RawTable[[#This Row],[Month]] -> Jan-2026 | H136: =RawTable[[#This Row],[Currency]] -> USD | I136: =RawTable[[#This Row],[Net_Amount]] -> 7689.7 | J136: =RawTable[[#This Row],[VAT_Applicable]] -> No | K136: =RawTable[[#This Row],[VAT_Rate]] -> 0 | L136: =RawTable[[#This Row],[VAT_Amount]] -> 0 | M136: =RawTable[[#This Row],[Gross_Amount]] -> 7689.7 | N136: =RawTable[[#This Row],[Exchange_Rate]] -> 0.77018 | O136: =RawTable[[#This Row],[Amount_CHF]] -> 5922.45 | P136: =IF( OR(ValidationTable[[#This Row],[Record_ID]]="",ValidationTable[[#This Row],[Payment_Type]]="",ValidationTable[[#This Row],[Entity_Type]]="", ValidationTable[[#This Row],[Country]]="", ValidationTable[[#This Row],[Name]]="", ValidationTable[[#This Row],[Month]]="", ValidationTable[[#This Row],[Currency]]="" ), "Fail", "Pass" ) -> Pass | Q136: =IF( OR(ValidationTable[[#This Row],[Net_Amount]]<=0, ROUND(ValidationTable[[#This Row],[Net_Amount]]+ValidationTable[[#This Row],[VAT_Amount]],2)<>ROUND(ValidationTable[[#This Row],[Gross_Amount]],2) ), "Fail", "Pass" ) -> Pass | R136: =IF(ValidationTable[[#This Row],[Currency]]="","Fail","Pass") -> Pass | S136: =IF( ValidationTable[[#This Row],[Currency]]="CHF", IF(ValidationTable[[#This Row],[Exchange_Rate]]<>1,"Fail","Pass"), IF(ValidationTable[[#This Row],[Exchange_Rate]]<=0,"Fail","Pass") ) -> Pass | T136: =IF(ValidationTable[[#This Row],[VAT_Applicable]]="Yes", IF( ROUND(ValidationTable[[#This Row],[Net_Amount]]*ValidationTable[[#This Row],[VAT_Rate]],2)<>ROUND(ValidationTable[[#This Row],[VAT_Amount]],2), "Fail", "Pass" ), IF( OR(ValidationTable[[#This Row],[VAT_Rate]]<>0,ValidationTable[[#This Row],[VAT_Amount]]<>0 ), "Fail", "Pass" ) ) -> Pass | U136: =IF(LEN(TRIM(ValidationTable[[#This Row],[Bank_Account]]))=0,"Fail","Pass") -> Pass | V136: =IF( COUNTIF(ValidationTable[Record_ID],ValidationTable[[#This Row],[Record_ID]])>1, "Fail", "Pass" ) -> Pass | W136: =IF( COUNTIF(ValidationTable[[#This Row],[RequiredField_Validation]]:ValidationTable[[#This Row],[Duplicate_Validation]],"Fail")>0, "Fail", "Pass" ) -> Pass | X136: =IF(ValidationTable[[#This Row],[Validation_Result]]="Pass","Yes","No") -> Yes
A137: =RawTable[[#This Row],[Record_ID]] -> 136 | B137: =RawTable[[#This Row],[Payment_Type]] -> Payroll | C137: =RawTable[[#This Row],[Entity_Type]] -> Employee | D137: =RawTable[[#This Row],[Country]] -> Germany | E137: =RawTable[[#This Row],[Name]] -> John Wilson | F137: =RawTable[[#This Row],[Bank_Account]] -> US-RT-000071572-AC-0000329324 | G137: =RawTable[[#This Row],[Month]] -> Jan-2026 | H137: =RawTable[[#This Row],[Currency]] -> EUR | I137: =RawTable[[#This Row],[Net_Amount]] -> 6409.8 | J137: =RawTable[[#This Row],[VAT_Applicable]] -> No | K137: =RawTable[[#This Row],[VAT_Rate]] -> 0 | L137: =RawTable[[#This Row],[VAT_Amount]] -> 0 | M137: =RawTable[[#This Row],[Gross_Amount]] -> 6409.8 | N137: =RawTable[[#This Row],[Exchange_Rate]] -> 0.90888 | O137: =RawTable[[#This Row],[Amount_CHF]] -> 5825.74 | P137: =IF( OR(ValidationTable[[#This Row],[Record_ID]]="",ValidationTable[[#This Row],[Payment_Type]]="",ValidationTable[[#This Row],[Entity_Type]]="", ValidationTable[[#This Row],[Country]]="", ValidationTable[[#This Row],[Name]]="", ValidationTable[[#This Row],[Month]]="", ValidationTable[[#This Row],[Currency]]="" ), "Fail", "Pass" ) -> Pass | Q137: =IF( OR(ValidationTable[[#This Row],[Net_Amount]]<=0, ROUND(ValidationTable[[#This Row],[Net_Amount]]+ValidationTable[[#This Row],[VAT_Amount]],2)<>ROUND(ValidationTable[[#This Row],[Gross_Amount]],2) ), "Fail", "Pass" ) -> Pass | R137: =IF(ValidationTable[[#This Row],[Currency]]="","Fail","Pass") -> Pass | S137: =IF( ValidationTable[[#This Row],[Currency]]="CHF", IF(ValidationTable[[#This Row],[Exchange_Rate]]<>1,"Fail","Pass"), IF(ValidationTable[[#This Row],[Exchange_Rate]]<=0,"Fail","Pass") ) -> Pass | T137: =IF(ValidationTable[[#This Row],[VAT_Applicable]]="Yes", IF( ROUND(ValidationTable[[#This Row],[Net_Amount]]*ValidationTable[[#This Row],[VAT_Rate]],2)<>ROUND(ValidationTable[[#This Row],[VAT_Amount]],2), "Fail", "Pass" ), IF( OR(ValidationTable[[#This Row],[VAT_Rate]]<>0,ValidationTable[[#This Row],[VAT_Amount]]<>0 ), "Fail", "Pass" ) ) -> Pass | U137: =IF(LEN(TRIM(ValidationTable[[#This Row],[Bank_Account]]))=0,"Fail","Pass") -> Pass | V137: =IF( COUNTIF(ValidationTable[Record_ID],ValidationTable[[#This Row],[Record_ID]])>1, "Fail", "Pass" ) -> Pass | W137: =IF( COUNTIF(ValidationTable[[#This Row],[RequiredField_Validation]]:ValidationTable[[#This Row],[Duplicate_Validation]],"Fail")>0, "Fail", "Pass" ) -> Pass | X137: =IF(ValidationTable[[#This Row],[Validation_Result]]="Pass","Yes","No") -> Yes
A138: =RawTable[[#This Row],[Record_ID]] -> 137 | B138: =RawTable[[#This Row],[Payment_Type]] -> Payroll | C138: =RawTable[[#This Row],[Entity_Type]] -> Employee | D138: =RawTable[[#This Row],[Country]] -> Germany | E138: =RawTable[[#This Row],[Name]] -> Laura Khan | F138: =RawTable[[#This Row],[Bank_Account]] -> US-RT-000066636-AC-0000306612 | G138: =RawTable[[#This Row],[Month]] -> Mar-2026 | H138: =RawTable[[#This Row],[Currency]] -> EUR | I138: =RawTable[[#This Row],[Net_Amount]] -> 6326.4 | J138: =RawTable[[#This Row],[VAT_Applicable]] -> No | K138: =RawTable[[#This Row],[VAT_Rate]] -> 0 | L138: =RawTable[[#This Row],[VAT_Amount]] -> 0 | M138: =RawTable[[#This Row],[Gross_Amount]] -> 6326.4 | N138: =RawTable[[#This Row],[Exchange_Rate]] -> 0.90888 | O138: =RawTable[[#This Row],[Amount_CHF]] -> 5749.94 | P138: =IF( OR(ValidationTable[[#This Row],[Record_ID]]="",ValidationTable[[#This Row],[Payment_Type]]="",ValidationTable[[#This Row],[Entity_Type]]="", ValidationTable[[#This Row],[Country]]="", ValidationTable[[#This Row],[Name]]="", ValidationTable[[#This Row],[Month]]="", ValidationTable[[#This Row],[Currency]]="" ), "Fail", "Pass" ) -> Pass | Q138: =IF( OR(ValidationTable[[#This Row],[Net_Amount]]<=0, ROUND(ValidationTable[[#This Row],[Net_Amount]]+ValidationTable[[#This Row],[VAT_Amount]],2)<>ROUND(ValidationTable[[#This Row],[Gross_Amount]],2) ), "Fail", "Pass" ) -> Pass | R138: =IF(ValidationTable[[#This Row],[Currency]]="","Fail","Pass") -> Pass | S138: =IF( ValidationTable[[#This Row],[Currency]]="CHF", IF(ValidationTable[[#This Row],[Exchange_Rate]]<>1,"Fail","Pass"), IF(ValidationTable[[#This Row],[Exchange_Rate]]<=0,"Fail","Pass") ) -> Pass | T138: =IF(ValidationTable[[#This Row],[VAT_Applicable]]="Yes", IF( ROUND(ValidationTable[[#This Row],[Net_Amount]]*ValidationTable[[#This Row],[VAT_Rate]],2)<>ROUND(ValidationTable[[#This Row],[VAT_Amount]],2), "Fail", "Pass" ), IF( OR(ValidationTable[[#This Row],[VAT_Rate]]<>0,ValidationTable[[#This Row],[VAT_Amount]]<>0 ), "Fail", "Pass" ) ) -> Pass | U138: =IF(LEN(TRIM(ValidationTable[[#This Row],[Bank_Account]]))=0,"Fail","Pass") -> Pass | V138: =IF( COUNTIF(ValidationTable[Record_ID],ValidationTable[[#This Row],[Record_ID]])>1, "Fail", "Pass" ) -> Pass | W138: =IF( COUNTIF(ValidationTable[[#This Row],[RequiredField_Validation]]:ValidationTable[[#This Row],[Duplicate_Validation]],"Fail")>0, "Fail", "Pass" ) -> Pass | X138: =IF(ValidationTable[[#This Row],[Validation_Result]]="Pass","Yes","No") -> Yes
A139: =RawTable[[#This Row],[Record_ID]] -> 138 | B139: =RawTable[[#This Row],[Payment_Type]] -> Payroll | C139: =RawTable[[#This Row],[Entity_Type]] -> Employee | D139: =RawTable[[#This Row],[Country]] -> UAE | E139: =RawTable[[#This Row],[Name]] -> Anna Khan | F139: =RawTable[[#This Row],[Bank_Account]] -> DE890000000000081474 | G139: =RawTable[[#This Row],[Month]] -> Mar-2026 | H139: =RawTable[[#This Row],[Currency]] -> AED | I139: =RawTable[[#This Row],[Net_Amount]] -> 20002.4 | J139: =RawTable[[#This Row],[VAT_Applicable]] -> No | K139: =RawTable[[#This Row],[VAT_Rate]] -> 0 | L139: =RawTable[[#This Row],[VAT_Amount]] -> 0 | M139: =RawTable[[#This Row],[Gross_Amount]] -> 20002.4 | N139: =RawTable[[#This Row],[Exchange_Rate]] -> 0.21065 | O139: =RawTable[[#This Row],[Amount_CHF]] -> 4213.51 | P139: =IF( OR(ValidationTable[[#This Row],[Record_ID]]="",ValidationTable[[#This Row],[Payment_Type]]="",ValidationTable[[#This Row],[Entity_Type]]="", ValidationTable[[#This Row],[Country]]="", ValidationTable[[#This Row],[Name]]="", ValidationTable[[#This Row],[Month]]="", ValidationTable[[#This Row],[Currency]]="" ), "Fail", "Pass" ) -> Pass | Q139: =IF( OR(ValidationTable[[#This Row],[Net_Amount]]<=0, ROUND(ValidationTable[[#This Row],[Net_Amount]]+ValidationTable[[#This Row],[VAT_Amount]],2)<>ROUND(ValidationTable[[#This Row],[Gross_Amount]],2) ), "Fail", "Pass" ) -> Pass | R139: =IF(ValidationTable[[#This Row],[Currency]]="","Fail","Pass") -> Pass | S139: =IF( ValidationTable[[#This Row],[Currency]]="CHF", IF(ValidationTable[[#This Row],[Exchange_Rate]]<>1,"Fail","Pass"), IF(ValidationTable[[#This Row],[Exchange_Rate]]<=0,"Fail","Pass") ) -> Pass | T139: =IF(ValidationTable[[#This Row],[VAT_Applicable]]="Yes", IF( ROUND(ValidationTable[[#This Row],[Net_Amount]]*ValidationTable[[#This Row],[VAT_Rate]],2)<>ROUND(ValidationTable[[#This Row],[VAT_Amount]],2), "Fail", "Pass" ), IF( OR(ValidationTable[[#This Row],[VAT_Rate]]<>0,ValidationTable[[#This Row],[VAT_Amount]]<>0 ), "Fail", "Pass" ) ) -> Pass | U139: =IF(LEN(TRIM(ValidationTable[[#This Row],[Bank_Account]]))=0,"Fail","Pass") -> Pass | V139: =IF( COUNTIF(ValidationTable[Record_ID],ValidationTable[[#This Row],[Record_ID]])>1, "Fail", "Pass" ) -> Pass | W139: =IF( COUNTIF(ValidationTable[[#This Row],[RequiredField_Validation]]:ValidationTable[[#This Row],[Duplicate_Validation]],"Fail")>0, "Fail", "Pass" ) -> Pass | X139: =IF(ValidationTable[[#This Row],[Validation_Result]]="Pass","Yes","No") -> Yes
A140: =RawTable[[#This Row],[Record_ID]] -> 139 | B140: =RawTable[[#This Row],[Payment_Type]] -> Payroll | C140: =RawTable[[#This Row],[Entity_Type]] -> Employee | D140: =RawTable[[#This Row],[Country]] -> Germany | E140: =RawTable[[#This Row],[Name]] -> Sara Brown | F140: =RawTable[[#This Row],[Bank_Account]] -> DE890000000000950530 | G140: =RawTable[[#This Row],[Month]] -> Jan-2026 | H140: =RawTable[[#This Row],[Currency]] -> EUR | I140: =RawTable[[#This Row],[Net_Amount]] -> 5796 | J140: =RawTable[[#This Row],[VAT_Applicable]] -> No | K140: =RawTable[[#This Row],[VAT_Rate]] -> 0 | L140: =RawTable[[#This Row],[VAT_Amount]] -> 0 | M140: =RawTable[[#This Row],[Gross_Amount]] -> 5796 | N140: =RawTable[[#This Row],[Exchange_Rate]] -> 0.90888 | O140: =RawTable[[#This Row],[Amount_CHF]] -> 5267.87 | P140: =IF( OR(ValidationTable[[#This Row],[Record_ID]]="",ValidationTable[[#This Row],[Payment_Type]]="",ValidationTable[[#This Row],[Entity_Type]]="", ValidationTable[[#This Row],[Country]]="", ValidationTable[[#This Row],[Name]]="", ValidationTable[[#This Row],[Month]]="", ValidationTable[[#This Row],[Currency]]="" ), "Fail", "Pass" ) -> Pass | Q140: =IF( OR(ValidationTable[[#This Row],[Net_Amount]]<=0, ROUND(ValidationTable[[#This Row],[Net_Amount]]+ValidationTable[[#This Row],[VAT_Amount]],2)<>ROUND(ValidationTable[[#This Row],[Gross_Amount]],2) ), "Fail", "Pass" ) -> Pass | R140: =IF(ValidationTable[[#This Row],[Currency]]="","Fail","Pass") -> Pass | S140: =IF( ValidationTable[[#This Row],[Currency]]="CHF", IF(ValidationTable[[#This Row],[Exchange_Rate]]<>1,"Fail","Pass"), IF(ValidationTable[[#This Row],[Exchange_Rate]]<=0,"Fail","Pass") ) -> Pass | T140: =IF(ValidationTable[[#This Row],[VAT_Applicable]]="Yes", IF( ROUND(ValidationTable[[#This Row],[Net_Amount]]*ValidationTable[[#This Row],[VAT_Rate]],2)<>ROUND(ValidationTable[[#This Row],[VAT_Amount]],2), "Fail", "Pass" ), IF( OR(ValidationTable[[#This Row],[VAT_Rate]]<>0,ValidationTable[[#This Row],[VAT_Amount]]<>0 ), "Fail", "Pass" ) ) -> Pass | U140: =IF(LEN(TRIM(ValidationTable[[#This Row],[Bank_Account]]))=0,"Fail","Pass") -> Pass | V140: =IF( COUNTIF(ValidationTable[Record_ID],ValidationTable[[#This Row],[Record_ID]])>1, "Fail", "Pass" ) -> Pass | W140: =IF( COUNTIF(ValidationTable[[#This Row],[RequiredField_Validation]]:ValidationTable[[#This Row],[Duplicate_Validation]],"Fail")>0, "Fail", "Pass" ) -> Pass | X140: =IF(ValidationTable[[#This Row],[Validation_Result]]="Pass","Yes","No") -> Yes
A141: =RawTable[[#This Row],[Record_ID]] -> 140 | B141: =RawTable[[#This Row],[Payment_Type]] -> Payroll | C141: =RawTable[[#This Row],[Entity_Type]] -> Employee | D141: =RawTable[[#This Row],[Country]] -> Switzerland | E141: =RawTable[[#This Row],[Name]] -> Laura Ali | F141: =RawTable[[#This Row],[Bank_Account]] -> CH930000000001752280 | G141: =RawTable[[#This Row],[Month]] -> Feb-2026 | H141: =RawTable[[#This Row],[Currency]] -> CHF | I141: =RawTable[[#This Row],[Net_Amount]] -> 6481.8 | J141: =RawTable[[#This Row],[VAT_Applicable]] -> No | K141: =RawTable[[#This Row],[VAT_Rate]] -> 0 | L141: =RawTable[[#This Row],[VAT_Amount]] -> 0 | M141: =RawTable[[#This Row],[Gross_Amount]] -> 6481.8 | N141: =RawTable[[#This Row],[Exchange_Rate]] -> 1 | O141: =RawTable[[#This Row],[Amount_CHF]] -> 6481.8 | P141: =IF( OR(ValidationTable[[#This Row],[Record_ID]]="",ValidationTable[[#This Row],[Payment_Type]]="",ValidationTable[[#This Row],[Entity_Type]]="", ValidationTable[[#This Row],[Country]]="", ValidationTable[[#This Row],[Name]]="", ValidationTable[[#This Row],[Month]]="", ValidationTable[[#This Row],[Currency]]="" ), "Fail", "Pass" ) -> Pass | Q141: =IF( OR(ValidationTable[[#This Row],[Net_Amount]]<=0, ROUND(ValidationTable[[#This Row],[Net_Amount]]+ValidationTable[[#This Row],[VAT_Amount]],2)<>ROUND(ValidationTable[[#This Row],[Gross_Amount]],2) ), "Fail", "Pass" ) -> Pass | R141: =IF(ValidationTable[[#This Row],[Currency]]="","Fail","Pass") -> Pass | S141: =IF( ValidationTable[[#This Row],[Currency]]="CHF", IF(ValidationTable[[#This Row],[Exchange_Rate]]<>1,"Fail","Pass"), IF(ValidationTable[[#This Row],[Exchange_Rate]]<=0,"Fail","Pass") ) -> Pass | T141: =IF(ValidationTable[[#This Row],[VAT_Applicable]]="Yes", IF( ROUND(ValidationTable[[#This Row],[Net_Amount]]*ValidationTable[[#This Row],[VAT_Rate]],2)<>ROUND(ValidationTable[[#This Row],[VAT_Amount]],2), "Fail", "Pass" ), IF( OR(ValidationTable[[#This Row],[VAT_Rate]]<>0,ValidationTable[[#This Row],[VAT_Amount]]<>0 ), "Fail", "Pass" ) ) -> Pass | U141: =IF(LEN(TRIM(ValidationTable[[#This Row],[Bank_Account]]))=0,"Fail","Pass") -> Pass | V141: =IF( COUNTIF(ValidationTable[Record_ID],ValidationTable[[#This Row],[Record_ID]])>1, "Fail", "Pass" ) -> Pass | W141: =IF( COUNTIF(ValidationTable[[#This Row],[RequiredField_Validation]]:ValidationTable[[#This Row],[Duplicate_Validation]],"Fail")>0, "Fail", "Pass" ) -> Pass | X141: =IF(ValidationTable[[#This Row],[Validation_Result]]="Pass","Yes","No") -> Yes
A142: =RawTable[[#This Row],[Record_ID]] -> 141 | B142: =RawTable[[#This Row],[Payment_Type]] -> Payroll | C142: =RawTable[[#This Row],[Entity_Type]] -> Employee | D142: =RawTable[[#This Row],[Country]] -> Germany | E142: =RawTable[[#This Row],[Name]] -> Laura Taylor | F142: =RawTable[[#This Row],[Bank_Account]] -> DE890000000000977688 | G142: =RawTable[[#This Row],[Month]] -> Feb-2026 | H142: =RawTable[[#This Row],[Currency]] -> EUR | I142: =RawTable[[#This Row],[Net_Amount]] -> 5851.2 | J142: =RawTable[[#This Row],[VAT_Applicable]] -> No | K142: =RawTable[[#This Row],[VAT_Rate]] -> 0 | L142: =RawTable[[#This Row],[VAT_Amount]] -> 0 | M142: =RawTable[[#This Row],[Gross_Amount]] -> 5851.2 | N142: =RawTable[[#This Row],[Exchange_Rate]] -> 0.90888 | O142: =RawTable[[#This Row],[Amount_CHF]] -> 5318.04 | P142: =IF( OR(ValidationTable[[#This Row],[Record_ID]]="",ValidationTable[[#This Row],[Payment_Type]]="",ValidationTable[[#This Row],[Entity_Type]]="", ValidationTable[[#This Row],[Country]]="", ValidationTable[[#This Row],[Name]]="", ValidationTable[[#This Row],[Month]]="", ValidationTable[[#This Row],[Currency]]="" ), "Fail", "Pass" ) -> Pass | Q142: =IF( OR(ValidationTable[[#This Row],[Net_Amount]]<=0, ROUND(ValidationTable[[#This Row],[Net_Amount]]+ValidationTable[[#This Row],[VAT_Amount]],2)<>ROUND(ValidationTable[[#This Row],[Gross_Amount]],2) ), "Fail", "Pass" ) -> Pass | R142: =IF(ValidationTable[[#This Row],[Currency]]="","Fail","Pass") -> Pass | S142: =IF( ValidationTable[[#This Row],[Currency]]="CHF", IF(ValidationTable[[#This Row],[Exchange_Rate]]<>1,"Fail","Pass"), IF(ValidationTable[[#This Row],[Exchange_Rate]]<=0,"Fail","Pass") ) -> Pass | T142: =IF(ValidationTable[[#This Row],[VAT_Applicable]]="Yes", IF( ROUND(ValidationTable[[#This Row],[Net_Amount]]*ValidationTable[[#This Row],[VAT_Rate]],2)<>ROUND(ValidationTable[[#This Row],[VAT_Amount]],2), "Fail", "Pass" ), IF( OR(ValidationTable[[#This Row],[VAT_Rate]]<>0,ValidationTable[[#This Row],[VAT_Amount]]<>0 ), "Fail", "Pass" ) ) -> Pass | U142: =IF(LEN(TRIM(ValidationTable[[#This Row],[Bank_Account]]))=0,"Fail","Pass") -> Pass | V142: =IF( COUNTIF(ValidationTable[Record_ID],ValidationTable[[#This Row],[Record_ID]])>1, "Fail", "Pass" ) -> Pass | W142: =IF( COUNTIF(ValidationTable[[#This Row],[RequiredField_Validation]]:ValidationTable[[#This Row],[Duplicate_Validation]],"Fail")>0, "Fail", "Pass" ) -> Pass | X142: =IF(ValidationTable[[#This Row],[Validation_Result]]="Pass","Yes","No") -> Yes
A143: =RawTable[[#This Row],[Record_ID]] -> 142 | B143: =RawTable[[#This Row],[Payment_Type]] -> Payroll | C143: =RawTable[[#This Row],[Entity_Type]] -> Employee | D143: =RawTable[[#This Row],[Country]] -> Switzerland | E143: =RawTable[[#This Row],[Name]] -> Laura Khan | F143: =RawTable[[#This Row],[Bank_Account]] -> US-RT-000066636-AC-0000306612 | G143: =RawTable[[#This Row],[Month]] -> Jan-2026 | H143: =RawTable[[#This Row],[Currency]] -> CHF | I143: =RawTable[[#This Row],[Net_Amount]] -> 6956.4 | J143: =RawTable[[#This Row],[VAT_Applicable]] -> No | K143: =RawTable[[#This Row],[VAT_Rate]] -> 0 | L143: =RawTable[[#This Row],[VAT_Amount]] -> 0 | M143: =RawTable[[#This Row],[Gross_Amount]] -> 6956.4 | N143: =RawTable[[#This Row],[Exchange_Rate]] -> 1 | O143: =RawTable[[#This Row],[Amount_CHF]] -> 6956.4 | P143: =IF( OR(ValidationTable[[#This Row],[Record_ID]]="",ValidationTable[[#This Row],[Payment_Type]]="",ValidationTable[[#This Row],[Entity_Type]]="", ValidationTable[[#This Row],[Country]]="", ValidationTable[[#This Row],[Name]]="", ValidationTable[[#This Row],[Month]]="", ValidationTable[[#This Row],[Currency]]="" ), "Fail", "Pass" ) -> Pass | Q143: =IF( OR(ValidationTable[[#This Row],[Net_Amount]]<=0, ROUND(ValidationTable[[#This Row],[Net_Amount]]+ValidationTable[[#This Row],[VAT_Amount]],2)<>ROUND(ValidationTable[[#This Row],[Gross_Amount]],2) ), "Fail", "Pass" ) -> Pass | R143: =IF(ValidationTable[[#This Row],[Currency]]="","Fail","Pass") -> Pass | S143: =IF( ValidationTable[[#This Row],[Currency]]="CHF", IF(ValidationTable[[#This Row],[Exchange_Rate]]<>1,"Fail","Pass"), IF(ValidationTable[[#This Row],[Exchange_Rate]]<=0,"Fail","Pass") ) -> Pass | T143: =IF(ValidationTable[[#This Row],[VAT_Applicable]]="Yes", IF( ROUND(ValidationTable[[#This Row],[Net_Amount]]*ValidationTable[[#This Row],[VAT_Rate]],2)<>ROUND(ValidationTable[[#This Row],[VAT_Amount]],2), "Fail", "Pass" ), IF( OR(ValidationTable[[#This Row],[VAT_Rate]]<>0,ValidationTable[[#This Row],[VAT_Amount]]<>0 ), "Fail", "Pass" ) ) -> Pass | U143: =IF(LEN(TRIM(ValidationTable[[#This Row],[Bank_Account]]))=0,"Fail","Pass") -> Pass | V143: =IF( COUNTIF(ValidationTable[Record_ID],ValidationTable[[#This Row],[Record_ID]])>1, "Fail", "Pass" ) -> Pass | W143: =IF( COUNTIF(ValidationTable[[#This Row],[RequiredField_Validation]]:ValidationTable[[#This Row],[Duplicate_Validation]],"Fail")>0, "Fail", "Pass" ) -> Pass | X143: =IF(ValidationTable[[#This Row],[Validation_Result]]="Pass","Yes","No") -> Yes
A144: =RawTable[[#This Row],[Record_ID]] -> 143 | B144: =RawTable[[#This Row],[Payment_Type]] -> Payroll | C144: =RawTable[[#This Row],[Entity_Type]] -> Employee | D144: =RawTable[[#This Row],[Country]] -> USA | E144: =RawTable[[#This Row],[Name]] -> Julia Schmidt | F144: =RawTable[[#This Row],[Bank_Account]] -> US-RT-000090082-AC-0000414494 | G144: =RawTable[[#This Row],[Month]] -> Jan-2026 | H144: =RawTable[[#This Row],[Currency]] -> USD | I144: =RawTable[[#This Row],[Net_Amount]] -> 6719.3 | J144: =RawTable[[#This Row],[VAT_Applicable]] -> No | K144: =RawTable[[#This Row],[VAT_Rate]] -> 0 | L144: =RawTable[[#This Row],[VAT_Amount]] -> 0 | M144: =RawTable[[#This Row],[Gross_Amount]] -> 6719.3 | N144: =RawTable[[#This Row],[Exchange_Rate]] -> 0.77018 | O144: =RawTable[[#This Row],[Amount_CHF]] -> 5175.07 | P144: =IF( OR(ValidationTable[[#This Row],[Record_ID]]="",ValidationTable[[#This Row],[Payment_Type]]="",ValidationTable[[#This Row],[Entity_Type]]="", ValidationTable[[#This Row],[Country]]="", ValidationTable[[#This Row],[Name]]="", ValidationTable[[#This Row],[Month]]="", ValidationTable[[#This Row],[Currency]]="" ), "Fail", "Pass" ) -> Pass | Q144: =IF( OR(ValidationTable[[#This Row],[Net_Amount]]<=0, ROUND(ValidationTable[[#This Row],[Net_Amount]]+ValidationTable[[#This Row],[VAT_Amount]],2)<>ROUND(ValidationTable[[#This Row],[Gross_Amount]],2) ), "Fail", "Pass" ) -> Pass | R144: =IF(ValidationTable[[#This Row],[Currency]]="","Fail","Pass") -> Pass | S144: =IF( ValidationTable[[#This Row],[Currency]]="CHF", IF(ValidationTable[[#This Row],[Exchange_Rate]]<>1,"Fail","Pass"), IF(ValidationTable[[#This Row],[Exchange_Rate]]<=0,"Fail","Pass") ) -> Pass | T144: =IF(ValidationTable[[#This Row],[VAT_Applicable]]="Yes", IF( ROUND(ValidationTable[[#This Row],[Net_Amount]]*ValidationTable[[#This Row],[VAT_Rate]],2)<>ROUND(ValidationTable[[#This Row],[VAT_Amount]],2), "Fail", "Pass" ), IF( OR(ValidationTable[[#This Row],[VAT_Rate]]<>0,ValidationTable[[#This Row],[VAT_Amount]]<>0 ), "Fail", "Pass" ) ) -> Pass | U144: =IF(LEN(TRIM(ValidationTable[[#This Row],[Bank_Account]]))=0,"Fail","Pass") -> Pass | V144: =IF( COUNTIF(ValidationTable[Record_ID],ValidationTable[[#This Row],[Record_ID]])>1, "Fail", "Pass" ) -> Pass | W144: =IF( COUNTIF(ValidationTable[[#This Row],[RequiredField_Validation]]:ValidationTable[[#This Row],[Duplicate_Validation]],"Fail")>0, "Fail", "Pass" ) -> Pass | X144: =IF(ValidationTable[[#This Row],[Validation_Result]]="Pass","Yes","No") -> Yes
A145: =RawTable[[#This Row],[Record_ID]] -> 144 | B145: =RawTable[[#This Row],[Payment_Type]] -> Payroll | C145: =RawTable[[#This Row],[Entity_Type]] -> Employee | D145: =RawTable[[#This Row],[Country]] -> Jordan | E145: =RawTable[[#This Row],[Name]] -> Julia Haddad | F145: =RawTable[[#This Row],[Bank_Account]] -> CH930000000000863800 | G145: =RawTable[[#This Row],[Month]] -> Feb-2026 | H145: =RawTable[[#This Row],[Currency]] -> JOD | I145: =RawTable[[#This Row],[Net_Amount]] -> 1926.94 | J145: =RawTable[[#This Row],[VAT_Applicable]] -> No | K145: =RawTable[[#This Row],[VAT_Rate]] -> 0 | L145: =RawTable[[#This Row],[VAT_Amount]] -> 0 | M145: =RawTable[[#This Row],[Gross_Amount]] -> 1926.94 | N145: =RawTable[[#This Row],[Exchange_Rate]] -> 1.08643 | O145: =RawTable[[#This Row],[Amount_CHF]] -> 2093.49 | P145: =IF( OR(ValidationTable[[#This Row],[Record_ID]]="",ValidationTable[[#This Row],[Payment_Type]]="",ValidationTable[[#This Row],[Entity_Type]]="", ValidationTable[[#This Row],[Country]]="", ValidationTable[[#This Row],[Name]]="", ValidationTable[[#This Row],[Month]]="", ValidationTable[[#This Row],[Currency]]="" ), "Fail", "Pass" ) -> Pass | Q145: =IF( OR(ValidationTable[[#This Row],[Net_Amount]]<=0, ROUND(ValidationTable[[#This Row],[Net_Amount]]+ValidationTable[[#This Row],[VAT_Amount]],2)<>ROUND(ValidationTable[[#This Row],[Gross_Amount]],2) ), "Fail", "Pass" ) -> Pass | R145: =IF(ValidationTable[[#This Row],[Currency]]="","Fail","Pass") -> Pass | S145: =IF( ValidationTable[[#This Row],[Currency]]="CHF", IF(ValidationTable[[#This Row],[Exchange_Rate]]<>1,"Fail","Pass"), IF(ValidationTable[[#This Row],[Exchange_Rate]]<=0,"Fail","Pass") ) -> Pass | T145: =IF(ValidationTable[[#This Row],[VAT_Applicable]]="Yes", IF( ROUND(ValidationTable[[#This Row],[Net_Amount]]*ValidationTable[[#This Row],[VAT_Rate]],2)<>ROUND(ValidationTable[[#This Row],[VAT_Amount]],2), "Fail", "Pass" ), IF( OR(ValidationTable[[#This Row],[VAT_Rate]]<>0,ValidationTable[[#This Row],[VAT_Amount]]<>0 ), "Fail", "Pass" ) ) -> Pass | U145: =IF(LEN(TRIM(ValidationTable[[#This Row],[Bank_Account]]))=0,"Fail","Pass") -> Pass | V145: =IF( COUNTIF(ValidationTable[Record_ID],ValidationTable[[#This Row],[Record_ID]])>1, "Fail", "Pass" ) -> Pass | W145: =IF( COUNTIF(ValidationTable[[#This Row],[RequiredField_Validation]]:ValidationTable[[#This Row],[Duplicate_Validation]],"Fail")>0, "Fail", "Pass" ) -> Pass | X145: =IF(ValidationTable[[#This Row],[Validation_Result]]="Pass","Yes","No") -> Yes
... A181: =RawTable[[#This Row],[Record_ID]] -> 180 | B181: =RawTable[[#This Row],[Payment_Type]] -> Payroll | C181: =RawTable[[#This Row],[Entity_Type]] -> Employee | D181: =RawTable[[#This Row],[Country]] -> Germany | E181: =RawTable[[#This Row],[Name]] -> Julia Haddad | F181: =RawTable[[#This Row],[Bank_Account]] -> CH930000000000863800 | G181: =RawTable[[#This Row],[Month]] -> Jan-2026 | H181: =RawTable[[#This Row],[Currency]] -> EUR | I181: =RawTable[[#This Row],[Net_Amount]] -> 6328.2 | J181: =RawTable[[#This Row],[VAT_Applicable]] -> No | K181: =RawTable[[#This Row],[VAT_Rate]] -> 0 | L181: =RawTable[[#This Row],[VAT_Amount]] -> 0 | M181: =RawTable[[#This Row],[Gross_Amount]] -> 6328.2 | N181: =RawTable[[#This Row],[Exchange_Rate]] -> 0.90888 | O181: =RawTable[[#This Row],[Amount_CHF]] -> 5751.57 | P181: =IF( OR(ValidationTable[[#This Row],[Record_ID]]="",ValidationTable[[#This Row],[Payment_Type]]="",ValidationTable[[#This Row],[Entity_Type]]="", ValidationTable[[#This Row],[Country]]="", ValidationTable[[#This Row],[Name]]="", ValidationTable[[#This Row],[Month]]="", ValidationTable[[#This Row],[Currency]]="" ), "Fail", "Pass" ) -> Pass | Q181: =IF( OR(ValidationTable[[#This Row],[Net_Amount]]<=0, ROUND(ValidationTable[[#This Row],[Net_Amount]]+ValidationTable[[#This Row],[VAT_Amount]],2)<>ROUND(ValidationTable[[#This Row],[Gross_Amount]],2) ), "Fail", "Pass" ) -> Pass | R181: =IF(ValidationTable[[#This Row],[Currency]]="","Fail","Pass") -> Pass | S181: =IF( ValidationTable[[#This Row],[Currency]]="CHF", IF(ValidationTable[[#This Row],[Exchange_Rate]]<>1,"Fail","Pass"), IF(ValidationTable[[#This Row],[Exchange_Rate]]<=0,"Fail","Pass") ) -> Pass | T181: =IF(ValidationTable[[#This Row],[VAT_Applicable]]="Yes", IF( ROUND(ValidationTable[[#This Row],[Net_Amount]]*ValidationTable[[#This Row],[VAT_Rate]],2)<>ROUND(ValidationTable[[#This Row],[VAT_Amount]],2), "Fail", "Pass" ), IF( OR(ValidationTable[[#This Row],[VAT_Rate]]<>0,ValidationTable[[#This Row],[VAT_Amount]]<>0 ), "Fail", "Pass" ) ) -> Pass | U181: =IF(LEN(TRIM(ValidationTable[[#This Row],[Bank_Account]]))=0,"Fail","Pass") -> Pass | V181: =IF( COUNTIF(ValidationTable[Record_ID],ValidationTable[[#This Row],[Record_ID]])>1, "Fail", "Pass" ) -> Pass | W181: =IF( COUNTIF(ValidationTable[[#This Row],[RequiredField_Validation]]:ValidationTable[[#This Row],[Duplicate_Validation]],"Fail")>0, "Fail", "Pass" ) -> Pass | X181: =IF(ValidationTable[[#This Row],[Validation_Result]]="Pass","Yes","No") -> Yes
A182: =RawTable[[#This Row],[Record_ID]] -> 181 | B182: =RawTable[[#This Row],[Payment_Type]] -> Payroll | C182: =RawTable[[#This Row],[Entity_Type]] -> Employee | E182: =RawTable[[#This Row],[Name]] -> Lina Wilson | F182: =RawTable[[#This Row],[Bank_Account]] -> US-RT-000012340-AC-0000056780 | G182: =RawTable[[#This Row],[Month]] -> Jan-2026 | H182: =RawTable[[#This Row],[Currency]] -> USD | I182: =RawTable[[#This Row],[Net_Amount]] -> 7571.8 | J182: =RawTable[[#This Row],[VAT_Applicable]] -> No | K182: =RawTable[[#This Row],[VAT_Rate]] -> 0 | L182: =RawTable[[#This Row],[VAT_Amount]] -> 0 | M182: =RawTable[[#This Row],[Gross_Amount]] -> 7571.8 | N182: =RawTable[[#This Row],[Exchange_Rate]] -> 0.77018 | O182: =RawTable[[#This Row],[Amount_CHF]] -> 5831.65 | P182: =IF( OR(ValidationTable[[#This Row],[Record_ID]]="",ValidationTable[[#This Row],[Payment_Type]]="",ValidationTable[[#This Row],[Entity_Type]]="", ValidationTable[[#This Row],[Country]]="", ValidationTable[[#This Row],[Name]]="", ValidationTable[[#This Row],[Month]]="", ValidationTable[[#This Row],[Currency]]="" ), "Fail", "Pass" ) -> Fail | Q182: =IF( OR(ValidationTable[[#This Row],[Net_Amount]]<=0, ROUND(ValidationTable[[#This Row],[Net_Amount]]+ValidationTable[[#This Row],[VAT_Amount]],2)<>ROUND(ValidationTable[[#This Row],[Gross_Amount]],2) ), "Fail", "Pass" ) -> Pass | R182: =IF(ValidationTable[[#This Row],[Currency]]="","Fail","Pass") -> Pass | S182: =IF( ValidationTable[[#This Row],[Currency]]="CHF", IF(ValidationTable[[#This Row],[Exchange_Rate]]<>1,"Fail","Pass"), IF(ValidationTable[[#This Row],[Exchange_Rate]]<=0,"Fail","Pass") ) -> Pass | T182: =IF(ValidationTable[[#This Row],[VAT_Applicable]]="Yes", IF( ROUND(ValidationTable[[#This Row],[Net_Amount]]*ValidationTable[[#This Row],[VAT_Rate]],2)<>ROUND(ValidationTable[[#This Row],[VAT_Amount]],2), "Fail", "Pass" ), IF( OR(ValidationTable[[#This Row],[VAT_Rate]]<>0,ValidationTable[[#This Row],[VAT_Amount]]<>0 ), "Fail", "Pass" ) ) -> Pass | U182: =IF(LEN(TRIM(ValidationTable[[#This Row],[Bank_Account]]))=0,"Fail","Pass") -> Pass | V182: =IF( COUNTIF(ValidationTable[Record_ID],ValidationTable[[#This Row],[Record_ID]])>1, "Fail", "Pass" ) -> Pass | W182: =IF( COUNTIF(ValidationTable[[#This Row],[RequiredField_Validation]]:ValidationTable[[#This Row],[Duplicate_Validation]],"Fail")>0, "Fail", "Pass" ) -> Fail | X182: =IF(ValidationTable[[#This Row],[Validation_Result]]="Pass","Yes","No") -> No
A183: =RawTable[[#This Row],[Record_ID]] -> 182 | B183: =RawTable[[#This Row],[Payment_Type]] -> Payroll | C183: =RawTable[[#This Row],[Entity_Type]] -> Employee | E183: =RawTable[[#This Row],[Name]] -> Julia Smith | F183: =RawTable[[#This Row],[Bank_Account]] -> CH930000000000320840 | G183: =RawTable[[#This Row],[Month]] -> Feb-2026 | H183: =RawTable[[#This Row],[Currency]] -> AED | I183: =RawTable[[#This Row],[Net_Amount]] -> 21542.4 | J183: =RawTable[[#This Row],[VAT_Applicable]] -> No | K183: =RawTable[[#This Row],[VAT_Rate]] -> 0 | L183: =RawTable[[#This Row],[VAT_Amount]] -> 0 | M183: =RawTable[[#This Row],[Gross_Amount]] -> 21542.4 | N183: =RawTable[[#This Row],[Exchange_Rate]] -> 0.21065 | O183: =RawTable[[#This Row],[Amount_CHF]] -> 4537.91 | P183: =IF( OR(ValidationTable[[#This Row],[Record_ID]]="",ValidationTable[[#This Row],[Payment_Type]]="",ValidationTable[[#This Row],[Entity_Type]]="", ValidationTable[[#This Row],[Country]]="", ValidationTable[[#This Row],[Name]]="", ValidationTable[[#This Row],[Month]]="", ValidationTable[[#This Row],[Currency]]="" ), "Fail", "Pass" ) -> Fail | Q183: =IF( OR(ValidationTable[[#This Row],[Net_Amount]]<=0, ROUND(ValidationTable[[#This Row],[Net_Amount]]+ValidationTable[[#This Row],[VAT_Amount]],2)<>ROUND(ValidationTable[[#This Row],[Gross_Amount]],2) ), "Fail", "Pass" ) -> Pass | R183: =IF(ValidationTable[[#This Row],[Currency]]="","Fail","Pass") -> Pass | S183: =IF( ValidationTable[[#This Row],[Currency]]="CHF", IF(ValidationTable[[#This Row],[Exchange_Rate]]<>1,"Fail","Pass"), IF(ValidationTable[[#This Row],[Exchange_Rate]]<=0,"Fail","Pass") ) -> Pass | T183: =IF(ValidationTable[[#This Row],[VAT_Applicable]]="Yes", IF( ROUND(ValidationTable[[#This Row],[Net_Amount]]*ValidationTable[[#This Row],[VAT_Rate]],2)<>ROUND(ValidationTable[[#This Row],[VAT_Amount]],2), "Fail", "Pass" ), IF( OR(ValidationTable[[#This Row],[VAT_Rate]]<>0,ValidationTable[[#This Row],[VAT_Amount]]<>0 ), "Fail", "Pass" ) ) -> Pass | U183: =IF(LEN(TRIM(ValidationTable[[#This Row],[Bank_Account]]))=0,"Fail","Pass") -> Pass | V183: =IF( COUNTIF(ValidationTable[Record_ID],ValidationTable[[#This Row],[Record_ID]])>1, "Fail", "Pass" ) -> Pass | W183: =IF( COUNTIF(ValidationTable[[#This Row],[RequiredField_Validation]]:ValidationTable[[#This Row],[Duplicate_Validation]],"Fail")>0, "Fail", "Pass" ) -> Fail | X183: =IF(ValidationTable[[#This Row],[Validation_Result]]="Pass","Yes","No") -> No
A184: =RawTable[[#This Row],[Record_ID]] -> 183 | B184: =RawTable[[#This Row],[Payment_Type]] -> Payroll | C184: =RawTable[[#This Row],[Entity_Type]] -> Employee | D184: =RawTable[[#This Row],[Country]] -> USA | E184: =RawTable[[#This Row],[Name]] -> Ahmed Müller | F184: =RawTable[[#This Row],[Bank_Account]] -> US-RT-000096252-AC-0000442884 | G184: =RawTable[[#This Row],[Month]] -> Jan-2026 | H184: =RawTable[[#This Row],[Currency]] -> USD | I184: =RawTable[[#This Row],[Net_Amount]] -> 6514.9 | J184: =RawTable[[#This Row],[VAT_Applicable]] -> No | K184: =RawTable[[#This Row],[VAT_Rate]] -> 0 | L184: =RawTable[[#This Row],[VAT_Amount]] -> 0 | M184: =RawTable[[#This Row],[Gross_Amount]] -> 6514.9 | N184: =RawTable[[#This Row],[Exchange_Rate]] -> 0.77018 | O184: =RawTable[[#This Row],[Amount_CHF]] -> 5017.65 | P184: =IF( OR(ValidationTable[[#This Row],[Record_ID]]="",ValidationTable[[#This Row],[Payment_Type]]="",ValidationTable[[#This Row],[Entity_Type]]="", ValidationTable[[#This Row],[Country]]="", ValidationTable[[#This Row],[Name]]="", ValidationTable[[#This Row],[Month]]="", ValidationTable[[#This Row],[Currency]]="" ), "Fail", "Pass" ) -> Pass | Q184: =IF( OR(ValidationTable[[#This Row],[Net_Amount]]<=0, ROUND(ValidationTable[[#This Row],[Net_Amount]]+ValidationTable[[#This Row],[VAT_Amount]],2)<>ROUND(ValidationTable[[#This Row],[Gross_Amount]],2) ), "Fail", "Pass" ) -> Pass | R184: =IF(ValidationTable[[#This Row],[Currency]]="","Fail","Pass") -> Pass | S184: =IF( ValidationTable[[#This Row],[Currency]]="CHF", IF(ValidationTable[[#This Row],[Exchange_Rate]]<>1,"Fail","Pass"), IF(ValidationTable[[#This Row],[Exchange_Rate]]<=0,"Fail","Pass") ) -> Pass | T184: =IF(ValidationTable[[#This Row],[VAT_Applicable]]="Yes", IF( ROUND(ValidationTable[[#This Row],[Net_Amount]]*ValidationTable[[#This Row],[VAT_Rate]],2)<>ROUND(ValidationTable[[#This Row],[VAT_Amount]],2), "Fail", "Pass" ), IF( OR(ValidationTable[[#This Row],[VAT_Rate]]<>0,ValidationTable[[#This Row],[VAT_Amount]]<>0 ), "Fail", "Pass" ) ) -> Pass | U184: =IF(LEN(TRIM(ValidationTable[[#This Row],[Bank_Account]]))=0,"Fail","Pass") -> Pass | V184: =IF( COUNTIF(ValidationTable[Record_ID],ValidationTable[[#This Row],[Record_ID]])>1, "Fail", "Pass" ) -> Pass | W184: =IF( COUNTIF(ValidationTable[[#This Row],[RequiredField_Validation]]:ValidationTable[[#This Row],[Duplicate_Validation]],"Fail")>0, "Fail", "Pass" ) -> Pass | X184: =IF(ValidationTable[[#This Row],[Validation_Result]]="Pass","Yes","No") -> Yes
A185: =RawTable[[#This Row],[Record_ID]] -> 184 | B185: =RawTable[[#This Row],[Payment_Type]] -> Payroll | C185: =RawTable[[#This Row],[Entity_Type]] -> Employee | D185: =RawTable[[#This Row],[Country]] -> USA | E185: =RawTable[[#This Row],[Name]] -> Omar Khan | F185: =RawTable[[#This Row],[Bank_Account]] -> AE-IBAN-01738272 | G185: =RawTable[[#This Row],[Month]] -> Jan-2026 | H185: =RawTable[[#This Row],[Currency]] -> USD | I185: =RawTable[[#This Row],[Net_Amount]] -> 6601.7 | J185: =RawTable[[#This Row],[VAT_Applicable]] -> No | K185: =RawTable[[#This Row],[VAT_Rate]] -> 0 | L185: =RawTable[[#This Row],[VAT_Amount]] -> 0 | M185: =RawTable[[#This Row],[Gross_Amount]] -> 6601.7 | N185: =RawTable[[#This Row],[Exchange_Rate]] -> 0.77018 | O185: =RawTable[[#This Row],[Amount_CHF]] -> 5084.5 | P185: =IF( OR(ValidationTable[[#This Row],[Record_ID]]="",ValidationTable[[#This Row],[Payment_Type]]="",ValidationTable[[#This Row],[Entity_Type]]="", ValidationTable[[#This Row],[Country]]="", ValidationTable[[#This Row],[Name]]="", ValidationTable[[#This Row],[Month]]="", ValidationTable[[#This Row],[Currency]]="" ), "Fail", "Pass" ) -> Pass | Q185: =IF( OR(ValidationTable[[#This Row],[Net_Amount]]<=0, ROUND(ValidationTable[[#This Row],[Net_Amount]]+ValidationTable[[#This Row],[VAT_Amount]],2)<>ROUND(ValidationTable[[#This Row],[Gross_Amount]],2) ), "Fail", "Pass" ) -> Pass | R185: =IF(ValidationTable[[#This Row],[Currency]]="","Fail","Pass") -> Pass | S185: =IF( ValidationTable[[#This Row],[Currency]]="CHF", IF(ValidationTable[[#This Row],[Exchange_Rate]]<>1,"Fail","Pass"), IF(ValidationTable[[#This Row],[Exchange_Rate]]<=0,"Fail","Pass") ) -> Pass | T185: =IF(ValidationTable[[#This Row],[VAT_Applicable]]="Yes", IF( ROUND(ValidationTable[[#This Row],[Net_Amount]]*ValidationTable[[#This Row],[VAT_Rate]],2)<>ROUND(ValidationTable[[#This Row],[VAT_Amount]],2), "Fail", "Pass" ), IF( OR(ValidationTable[[#This Row],[VAT_Rate]]<>0,ValidationTable[[#This Row],[VAT_Amount]]<>0 ), "Fail", "Pass" ) ) -> Pass | U185: =IF(LEN(TRIM(ValidationTable[[#This Row],[Bank_Account]]))=0,"Fail","Pass") -> Pass | V185: =IF( COUNTIF(ValidationTable[Record_ID],ValidationTable[[#This Row],[Record_ID]])>1, "Fail", "Pass" ) -> Pass | W185: =IF( COUNTIF(ValidationTable[[#This Row],[RequiredField_Validation]]:ValidationTable[[#This Row],[Duplicate_Validation]],"Fail")>0, "Fail", "Pass" ) -> Pass | X185: =IF(ValidationTable[[#This Row],[Validation_Result]]="Pass","Yes","No") -> Yes
A186: =RawTable[[#This Row],[Record_ID]] -> 185 | B186: =RawTable[[#This Row],[Payment_Type]] -> Payroll | C186: =RawTable[[#This Row],[Entity_Type]] -> Employee | D186: =RawTable[[#This Row],[Country]] -> Switzerland | E186: =RawTable[[#This Row],[Name]] -> David Haddad | F186: =RawTable[[#This Row],[Bank_Account]] -> DE890000000000095053 | G186: =RawTable[[#This Row],[Month]] -> Jan-2026 | H186: =RawTable[[#This Row],[Currency]] -> CHF | I186: =RawTable[[#This Row],[Net_Amount]] -> 6350.09 | J186: =RawTable[[#This Row],[VAT_Applicable]] -> No | K186: =RawTable[[#This Row],[VAT_Rate]] -> 0 | L186: =RawTable[[#This Row],[VAT_Amount]] -> 0 | M186: =RawTable[[#This Row],[Gross_Amount]] -> 6350.09 | N186: =RawTable[[#This Row],[Exchange_Rate]] -> 1 | O186: =RawTable[[#This Row],[Amount_CHF]] -> 6350.09 | P186: =IF( OR(ValidationTable[[#This Row],[Record_ID]]="",ValidationTable[[#This Row],[Payment_Type]]="",ValidationTable[[#This Row],[Entity_Type]]="", ValidationTable[[#This Row],[Country]]="", ValidationTable[[#This Row],[Name]]="", ValidationTable[[#This Row],[Month]]="", ValidationTable[[#This Row],[Currency]]="" ), "Fail", "Pass" ) -> Pass | Q186: =IF( OR(ValidationTable[[#This Row],[Net_Amount]]<=0, ROUND(ValidationTable[[#This Row],[Net_Amount]]+ValidationTable[[#This Row],[VAT_Amount]],2)<>ROUND(ValidationTable[[#This Row],[Gross_Amount]],2) ), "Fail", "Pass" ) -> Pass | R186: =IF(ValidationTable[[#This Row],[Currency]]="","Fail","Pass") -> Pass | S186: =IF( ValidationTable[[#This Row],[Currency]]="CHF", IF(ValidationTable[[#This Row],[Exchange_Rate]]<>1,"Fail","Pass"), IF(ValidationTable[[#This Row],[Exchange_Rate]]<=0,"Fail","Pass") ) -> Pass | T186: =IF(ValidationTable[[#This Row],[VAT_Applicable]]="Yes", IF( ROUND(ValidationTable[[#This Row],[Net_Amount]]*ValidationTable[[#This Row],[VAT_Rate]],2)<>ROUND(ValidationTable[[#This Row],[VAT_Amount]],2), "Fail", "Pass" ), IF( OR(ValidationTable[[#This Row],[VAT_Rate]]<>0,ValidationTable[[#This Row],[VAT_Amount]]<>0 ), "Fail", "Pass" ) ) -> Pass | U186: =IF(LEN(TRIM(ValidationTable[[#This Row],[Bank_Account]]))=0,"Fail","Pass") -> Pass | V186: =IF( COUNTIF(ValidationTable[Record_ID],ValidationTable[[#This Row],[Record_ID]])>1, "Fail", "Pass" ) -> Pass | W186: =IF( COUNTIF(ValidationTable[[#This Row],[RequiredField_Validation]]:ValidationTable[[#This Row],[Duplicate_Validation]],"Fail")>0, "Fail", "Pass" ) -> Pass | X186: =IF(ValidationTable[[#This Row],[Validation_Result]]="Pass","Yes","No") -> Yes
A187: =RawTable[[#This Row],[Record_ID]] -> 186 | B187: =RawTable[[#This Row],[Payment_Type]] -> Payroll | C187: =RawTable[[#This Row],[Entity_Type]] -> Employee | D187: =RawTable[[#This Row],[Country]] -> UAE | E187: =RawTable[[#This Row],[Name]] -> Lina Johnson | F187: =RawTable[[#This Row],[Bank_Account]] -> CH930000000000740400 | G187: =RawTable[[#This Row],[Month]] -> Feb-2026 | H187: =RawTable[[#This Row],[Currency]] -> AED | I187: =RawTable[[#This Row],[Net_Amount]] -> 22653.4 | J187: =RawTable[[#This Row],[VAT_Applicable]] -> No | K187: =RawTable[[#This Row],[VAT_Rate]] -> 0 | L187: =RawTable[[#This Row],[VAT_Amount]] -> 0 | M187: =RawTable[[#This Row],[Gross_Amount]] -> 22653.4 | N187: =RawTable[[#This Row],[Exchange_Rate]] -> 0.21065 | O187: =RawTable[[#This Row],[Amount_CHF]] -> 4771.94 | P187: =IF( OR(ValidationTable[[#This Row],[Record_ID]]="",ValidationTable[[#This Row],[Payment_Type]]="",ValidationTable[[#This Row],[Entity_Type]]="", ValidationTable[[#This Row],[Country]]="", ValidationTable[[#This Row],[Name]]="", ValidationTable[[#This Row],[Month]]="", ValidationTable[[#This Row],[Currency]]="" ), "Fail", "Pass" ) -> Pass | Q187: =IF( OR(ValidationTable[[#This Row],[Net_Amount]]<=0, ROUND(ValidationTable[[#This Row],[Net_Amount]]+ValidationTable[[#This Row],[VAT_Amount]],2)<>ROUND(ValidationTable[[#This Row],[Gross_Amount]],2) ), "Fail", "Pass" ) -> Pass | R187: =IF(ValidationTable[[#This Row],[Currency]]="","Fail","Pass") -> Pass | S187: =IF( ValidationTable[[#This Row],[Currency]]="CHF", IF(ValidationTable[[#This Row],[Exchange_Rate]]<>1,"Fail","Pass"), IF(ValidationTable[[#This Row],[Exchange_Rate]]<=0,"Fail","Pass") ) -> Pass | T187: =IF(ValidationTable[[#This Row],[VAT_Applicable]]="Yes", IF( ROUND(ValidationTable[[#This Row],[Net_Amount]]*ValidationTable[[#This Row],[VAT_Rate]],2)<>ROUND(ValidationTable[[#This Row],[VAT_Amount]],2), "Fail", "Pass" ), IF( OR(ValidationTable[[#This Row],[VAT_Rate]]<>0,ValidationTable[[#This Row],[VAT_Amount]]<>0 ), "Fail", "Pass" ) ) -> Pass | U187: =IF(LEN(TRIM(ValidationTable[[#This Row],[Bank_Account]]))=0,"Fail","Pass") -> Pass | V187: =IF( COUNTIF(ValidationTable[Record_ID],ValidationTable[[#This Row],[Record_ID]])>1, "Fail", "Pass" ) -> Pass | W187: =IF( COUNTIF(ValidationTable[[#This Row],[RequiredField_Validation]]:ValidationTable[[#This Row],[Duplicate_Validation]],"Fail")>0, "Fail", "Pass" ) -> Pass | X187: =IF(ValidationTable[[#This Row],[Validation_Result]]="Pass","Yes","No") -> Yes
A188: =RawTable[[#This Row],[Record_ID]] -> 187 | B188: =RawTable[[#This Row],[Payment_Type]] -> Payroll | C188: =RawTable[[#This Row],[Entity_Type]] -> Employee | D188: =RawTable[[#This Row],[Country]] -> UAE | E188: =RawTable[[#This Row],[Name]] -> Laura Taylor | F188: =RawTable[[#This Row],[Bank_Account]] -> DE890000000000977688 | G188: =RawTable[[#This Row],[Month]] -> Jan-2026 | H188: =RawTable[[#This Row],[Currency]] -> AED | I188: =RawTable[[#This Row],[Net_Amount]] -> 21454.4 | J188: =RawTable[[#This Row],[VAT_Applicable]] -> No | K188: =RawTable[[#This Row],[VAT_Rate]] -> 0 | L188: =RawTable[[#This Row],[VAT_Amount]] -> 0 | M188: =RawTable[[#This Row],[Gross_Amount]] -> 21454.4 | N188: =RawTable[[#This Row],[Exchange_Rate]] -> 0.21065 | O188: =RawTable[[#This Row],[Amount_CHF]] -> 4519.37 | P188: =IF( OR(ValidationTable[[#This Row],[Record_ID]]="",ValidationTable[[#This Row],[Payment_Type]]="",ValidationTable[[#This Row],[Entity_Type]]="", ValidationTable[[#This Row],[Country]]="", ValidationTable[[#This Row],[Name]]="", ValidationTable[[#This Row],[Month]]="", ValidationTable[[#This Row],[Currency]]="" ), "Fail", "Pass" ) -> Pass | Q188: =IF( OR(ValidationTable[[#This Row],[Net_Amount]]<=0, ROUND(ValidationTable[[#This Row],[Net_Amount]]+ValidationTable[[#This Row],[VAT_Amount]],2)<>ROUND(ValidationTable[[#This Row],[Gross_Amount]],2) ), "Fail", "Pass" ) -> Pass | R188: =IF(ValidationTable[[#This Row],[Currency]]="","Fail","Pass") -> Pass | S188: =IF( ValidationTable[[#This Row],[Currency]]="CHF", IF(ValidationTable[[#This Row],[Exchange_Rate]]<>1,"Fail","Pass"), IF(ValidationTable[[#This Row],[Exchange_Rate]]<=0,"Fail","Pass") ) -> Pass | T188: =IF(ValidationTable[[#This Row],[VAT_Applicable]]="Yes", IF( ROUND(ValidationTable[[#This Row],[Net_Amount]]*ValidationTable[[#This Row],[VAT_Rate]],2)<>ROUND(ValidationTable[[#This Row],[VAT_Amount]],2), "Fail", "Pass" ), IF( OR(ValidationTable[[#This Row],[VAT_Rate]]<>0,ValidationTable[[#This Row],[VAT_Amount]]<>0 ), "Fail", "Pass" ) ) -> Pass | U188: =IF(LEN(TRIM(ValidationTable[[#This Row],[Bank_Account]]))=0,"Fail","Pass") -> Pass | V188: =IF( COUNTIF(ValidationTable[Record_ID],ValidationTable[[#This Row],[Record_ID]])>1, "Fail", "Pass" ) -> Pass | W188: =IF( COUNTIF(ValidationTable[[#This Row],[RequiredField_Validation]]:ValidationTable[[#This Row],[Duplicate_Validation]],"Fail")>0, "Fail", "Pass" ) -> Pass | X188: =IF(ValidationTable[[#This Row],[Validation_Result]]="Pass","Yes","No") -> Yes
A189: =RawTable[[#This Row],[Record_ID]] -> 188 | B189: =RawTable[[#This Row],[Payment_Type]] -> Payroll | C189: =RawTable[[#This Row],[Entity_Type]] -> Employee | D189: =RawTable[[#This Row],[Country]] -> Jordan | E189: =RawTable[[#This Row],[Name]] -> Sara Brown | F189: =RawTable[[#This Row],[Bank_Account]] -> DE890000000000950530 | G189: =RawTable[[#This Row],[Month]] -> Feb-2026 | H189: =RawTable[[#This Row],[Currency]] -> JOD | I189: =RawTable[[#This Row],[Net_Amount]] -> 1738.8 | J189: =RawTable[[#This Row],[VAT_Applicable]] -> No | K189: =RawTable[[#This Row],[VAT_Rate]] -> 0 | L189: =RawTable[[#This Row],[VAT_Amount]] -> 0 | M189: =RawTable[[#This Row],[Gross_Amount]] -> 1738.8 | N189: =RawTable[[#This Row],[Exchange_Rate]] -> 1.08643 | O189: =RawTable[[#This Row],[Amount_CHF]] -> 1889.08 | P189: =IF( OR(ValidationTable[[#This Row],[Record_ID]]="",ValidationTable[[#This Row],[Payment_Type]]="",ValidationTable[[#This Row],[Entity_Type]]="", ValidationTable[[#This Row],[Country]]="", ValidationTable[[#This Row],[Name]]="", ValidationTable[[#This Row],[Month]]="", ValidationTable[[#This Row],[Currency]]="" ), "Fail", "Pass" ) -> Pass | Q189: =IF( OR(ValidationTable[[#This Row],[Net_Amount]]<=0, ROUND(ValidationTable[[#This Row],[Net_Amount]]+ValidationTable[[#This Row],[VAT_Amount]],2)<>ROUND(ValidationTable[[#This Row],[Gross_Amount]],2) ), "Fail", "Pass" ) -> Pass | R189: =IF(ValidationTable[[#This Row],[Currency]]="","Fail","Pass") -> Pass | S189: =IF( ValidationTable[[#This Row],[Currency]]="CHF", IF(ValidationTable[[#This Row],[Exchange_Rate]]<>1,"Fail","Pass"), IF(ValidationTable[[#This Row],[Exchange_Rate]]<=0,"Fail","Pass") ) -> Pass | T189: =IF(ValidationTable[[#This Row],[VAT_Applicable]]="Yes", IF( ROUND(ValidationTable[[#This Row],[Net_Amount]]*ValidationTable[[#This Row],[VAT_Rate]],2)<>ROUND(ValidationTable[[#This Row],[VAT_Amount]],2), "Fail", "Pass" ), IF( OR(ValidationTable[[#This Row],[VAT_Rate]]<>0,ValidationTable[[#This Row],[VAT_Amount]]<>0 ), "Fail", "Pass" ) ) -> Pass | U189: =IF(LEN(TRIM(ValidationTable[[#This Row],[Bank_Account]]))=0,"Fail","Pass") -> Pass | V189: =IF( COUNTIF(ValidationTable[Record_ID],ValidationTable[[#This Row],[Record_ID]])>1, "Fail", "Pass" ) -> Pass | W189: =IF( COUNTIF(ValidationTable[[#This Row],[RequiredField_Validation]]:ValidationTable[[#This Row],[Duplicate_Validation]],"Fail")>0, "Fail", "Pass" ) -> Pass | X189: =IF(ValidationTable[[#This Row],[Validation_Result]]="Pass","Yes","No") -> Yes
A190: =RawTable[[#This Row],[Record_ID]] -> 189 | B190: =RawTable[[#This Row],[Payment_Type]] -> Payroll | C190: =RawTable[[#This Row],[Entity_Type]] -> Employee | D190: =RawTable[[#This Row],[Country]] -> Switzerland | E190: =RawTable[[#This Row],[Name]] -> Omar Khan | F190: =RawTable[[#This Row],[Bank_Account]] -> AE-IBAN-01738272 | G190: =RawTable[[#This Row],[Month]] -> Feb-2026 | H190: =RawTable[[#This Row],[Currency]] -> CHF | I190: =RawTable[[#This Row],[Net_Amount]] -> 6222.1 | J190: =RawTable[[#This Row],[VAT_Applicable]] -> No | K190: =RawTable[[#This Row],[VAT_Rate]] -> 0 | L190: =RawTable[[#This Row],[VAT_Amount]] -> 0 | M190: =RawTable[[#This Row],[Gross_Amount]] -> 6222.1 | N190: =RawTable[[#This Row],[Exchange_Rate]] -> 1 | O190: =RawTable[[#This Row],[Amount_CHF]] -> 6222.1 | P190: =IF( OR(ValidationTable[[#This Row],[Record_ID]]="",ValidationTable[[#This Row],[Payment_Type]]="",ValidationTable[[#This Row],[Entity_Type]]="", ValidationTable[[#This Row],[Country]]="", ValidationTable[[#This Row],[Name]]="", ValidationTable[[#This Row],[Month]]="", ValidationTable[[#This Row],[Currency]]="" ), "Fail", "Pass" ) -> Pass | Q190: =IF( OR(ValidationTable[[#This Row],[Net_Amount]]<=0, ROUND(ValidationTable[[#This Row],[Net_Amount]]+ValidationTable[[#This Row],[VAT_Amount]],2)<>ROUND(ValidationTable[[#This Row],[Gross_Amount]],2) ), "Fail", "Pass" ) -> Pass | R190: =IF(ValidationTable[[#This Row],[Currency]]="","Fail","Pass") -> Pass | S190: =IF( ValidationTable[[#This Row],[Currency]]="CHF", IF(ValidationTable[[#This Row],[Exchange_Rate]]<>1,"Fail","Pass"), IF(ValidationTable[[#This Row],[Exchange_Rate]]<=0,"Fail","Pass") ) -> Pass | T190: =IF(ValidationTable[[#This Row],[VAT_Applicable]]="Yes", IF( ROUND(ValidationTable[[#This Row],[Net_Amount]]*ValidationTable[[#This Row],[VAT_Rate]],2)<>ROUND(ValidationTable[[#This Row],[VAT_Amount]],2), "Fail", "Pass" ), IF( OR(ValidationTable[[#This Row],[VAT_Rate]]<>0,ValidationTable[[#This Row],[VAT_Amount]]<>0 ), "Fail", "Pass" ) ) -> Pass | U190: =IF(LEN(TRIM(ValidationTable[[#This Row],[Bank_Account]]))=0,"Fail","Pass") -> Pass | V190: =IF( COUNTIF(ValidationTable[Record_ID],ValidationTable[[#This Row],[Record_ID]])>1, "Fail", "Pass" ) -> Pass | W190: =IF( COUNTIF(ValidationTable[[#This Row],[RequiredField_Validation]]:ValidationTable[[#This Row],[Duplicate_Validation]],"Fail")>0, "Fail", "Pass" ) -> Pass | X190: =IF(ValidationTable[[#This Row],[Validation_Result]]="Pass","Yes","No") -> Yes
A191: =RawTable[[#This Row],[Record_ID]] -> 190 | B191: =RawTable[[#This Row],[Payment_Type]] -> Payroll | C191: =RawTable[[#This Row],[Entity_Type]] -> Employee | D191: =RawTable[[#This Row],[Country]] -> UAE | E191: =RawTable[[#This Row],[Name]] -> John Müller | F191: =RawTable[[#This Row],[Bank_Account]] -> CH930000000001382080 | G191: =RawTable[[#This Row],[Month]] -> Jan-2026 | H191: =RawTable[[#This Row],[Currency]] -> AED | I191: =RawTable[[#This Row],[Net_Amount]] -> 21276.2 | J191: =RawTable[[#This Row],[VAT_Applicable]] -> No | K191: =RawTable[[#This Row],[VAT_Rate]] -> 0 | L191: =RawTable[[#This Row],[VAT_Amount]] -> 0 | M191: =RawTable[[#This Row],[Gross_Amount]] -> 21276.2 | N191: =RawTable[[#This Row],[Exchange_Rate]] -> 0.21065 | O191: =RawTable[[#This Row],[Amount_CHF]] -> 4481.83 | P191: =IF( OR(ValidationTable[[#This Row],[Record_ID]]="",ValidationTable[[#This Row],[Payment_Type]]="",ValidationTable[[#This Row],[Entity_Type]]="", ValidationTable[[#This Row],[Country]]="", ValidationTable[[#This Row],[Name]]="", ValidationTable[[#This Row],[Month]]="", ValidationTable[[#This Row],[Currency]]="" ), "Fail", "Pass" ) -> Pass | Q191: =IF( OR(ValidationTable[[#This Row],[Net_Amount]]<=0, ROUND(ValidationTable[[#This Row],[Net_Amount]]+ValidationTable[[#This Row],[VAT_Amount]],2)<>ROUND(ValidationTable[[#This Row],[Gross_Amount]],2) ), "Fail", "Pass" ) -> Pass | R191: =IF(ValidationTable[[#This Row],[Currency]]="","Fail","Pass") -> Pass | S191: =IF( ValidationTable[[#This Row],[Currency]]="CHF", IF(ValidationTable[[#This Row],[Exchange_Rate]]<>1,"Fail","Pass"), IF(ValidationTable[[#This Row],[Exchange_Rate]]<=0,"Fail","Pass") ) -> Pass | T191: =IF(ValidationTable[[#This Row],[VAT_Applicable]]="Yes", IF( ROUND(ValidationTable[[#This Row],[Net_Amount]]*ValidationTable[[#This Row],[VAT_Rate]],2)<>ROUND(ValidationTable[[#This Row],[VAT_Amount]],2), "Fail", "Pass" ), IF( OR(ValidationTable[[#This Row],[VAT_Rate]]<>0,ValidationTable[[#This Row],[VAT_Amount]]<>0 ), "Fail", "Pass" ) ) -> Pass | U191: =IF(LEN(TRIM(ValidationTable[[#This Row],[Bank_Account]]))=0,"Fail","Pass") -> Pass | V191: =IF( COUNTIF(ValidationTable[Record_ID],ValidationTable[[#This Row],[Record_ID]])>1, "Fail", "Pass" ) -> Pass | W191: =IF( COUNTIF(ValidationTable[[#This Row],[RequiredField_Validation]]:ValidationTable[[#This Row],[Duplicate_Validation]],"Fail")>0, "Fail", "Pass" ) -> Pass | X191: =IF(ValidationTable[[#This Row],[Validation_Result]]="Pass","Yes","No") -> Yes
A192: =RawTable[[#This Row],[Record_ID]] -> 191 | B192: =RawTable[[#This Row],[Payment_Type]] -> Payroll | C192: =RawTable[[#This Row],[Entity_Type]] -> Employee | D192: =RawTable[[#This Row],[Country]] -> UAE | E192: =RawTable[[#This Row],[Name]] -> Laura Brown | F192: =RawTable[[#This Row],[Bank_Account]] -> DE890000000000339475 | G192: =RawTable[[#This Row],[Month]] -> Feb-2026 | H192: =RawTable[[#This Row],[Currency]] -> AED | I192: =RawTable[[#This Row],[Net_Amount]] -> 22399.22 | J192: =RawTable[[#This Row],[VAT_Applicable]] -> No | K192: =RawTable[[#This Row],[VAT_Rate]] -> 0 | L192: =RawTable[[#This Row],[VAT_Amount]] -> 0 | M192: =RawTable[[#This Row],[Gross_Amount]] -> 22399.22 | N192: =RawTable[[#This Row],[Exchange_Rate]] -> 0.21065 | O192: =RawTable[[#This Row],[Amount_CHF]] -> 4718.4 | P192: =IF( OR(ValidationTable[[#This Row],[Record_ID]]="",ValidationTable[[#This Row],[Payment_Type]]="",ValidationTable[[#This Row],[Entity_Type]]="", ValidationTable[[#This Row],[Country]]="", ValidationTable[[#This Row],[Name]]="", ValidationTable[[#This Row],[Month]]="", ValidationTable[[#This Row],[Currency]]="" ), "Fail", "Pass" ) -> Pass | Q192: =IF( OR(ValidationTable[[#This Row],[Net_Amount]]<=0, ROUND(ValidationTable[[#This Row],[Net_Amount]]+ValidationTable[[#This Row],[VAT_Amount]],2)<>ROUND(ValidationTable[[#This Row],[Gross_Amount]],2) ), "Fail", "Pass" ) -> Pass | R192: =IF(ValidationTable[[#This Row],[Currency]]="","Fail","Pass") -> Pass | S192: =IF( ValidationTable[[#This Row],[Currency]]="CHF", IF(ValidationTable[[#This Row],[Exchange_Rate]]<>1,"Fail","Pass"), IF(ValidationTable[[#This Row],[Exchange_Rate]]<=0,"Fail","Pass") ) -> Pass | T192: =IF(ValidationTable[[#This Row],[VAT_Applicable]]="Yes", IF( ROUND(ValidationTable[[#This Row],[Net_Amount]]*ValidationTable[[#This Row],[VAT_Rate]],2)<>ROUND(ValidationTable[[#This Row],[VAT_Amount]],2), "Fail", "Pass" ), IF( OR(ValidationTable[[#This Row],[VAT_Rate]]<>0,ValidationTable[[#This Row],[VAT_Amount]]<>0 ), "Fail", "Pass" ) ) -> Pass | U192: =IF(LEN(TRIM(ValidationTable[[#This Row],[Bank_Account]]))=0,"Fail","Pass") -> Pass | V192: =IF( COUNTIF(ValidationTable[Record_ID],ValidationTable[[#This Row],[Record_ID]])>1, "Fail", "Pass" ) -> Pass | W192: =IF( COUNTIF(ValidationTable[[#This Row],[RequiredField_Validation]]:ValidationTable[[#This Row],[Duplicate_Validation]],"Fail")>0, "Fail", "Pass" ) -> Pass | X192: =IF(ValidationTable[[#This Row],[Validation_Result]]="Pass","Yes","No") -> Yes
A193: =RawTable[[#This Row],[Record_ID]] -> 192 | B193: =RawTable[[#This Row],[Payment_Type]] -> Payroll | C193: =RawTable[[#This Row],[Entity_Type]] -> Employee | D193: =RawTable[[#This Row],[Country]] -> Germany | E193: =RawTable[[#This Row],[Name]] -> Julia Taylor | F193: =RawTable[[#This Row],[Bank_Account]] -> DE890000000001072741 | G193: =RawTable[[#This Row],[Month]] -> Jan-2026 | H193: =RawTable[[#This Row],[Currency]] -> EUR | I193: =RawTable[[#This Row],[Net_Amount]] -> 5848.8 | J193: =RawTable[[#This Row],[VAT_Applicable]] -> No | K193: =RawTable[[#This Row],[VAT_Rate]] -> 0 | L193: =RawTable[[#This Row],[VAT_Amount]] -> 0 | M193: =RawTable[[#This Row],[Gross_Amount]] -> 5848.8 | N193: =RawTable[[#This Row],[Exchange_Rate]] -> 0.90888 | O193: =RawTable[[#This Row],[Amount_CHF]] -> 5315.86 | P193: =IF( OR(ValidationTable[[#This Row],[Record_ID]]="",ValidationTable[[#This Row],[Payment_Type]]="",ValidationTable[[#This Row],[Entity_Type]]="", ValidationTable[[#This Row],[Country]]="", ValidationTable[[#This Row],[Name]]="", ValidationTable[[#This Row],[Month]]="", ValidationTable[[#This Row],[Currency]]="" ), "Fail", "Pass" ) -> Pass | Q193: =IF( OR(ValidationTable[[#This Row],[Net_Amount]]<=0, ROUND(ValidationTable[[#This Row],[Net_Amount]]+ValidationTable[[#This Row],[VAT_Amount]],2)<>ROUND(ValidationTable[[#This Row],[Gross_Amount]],2) ), "Fail", "Pass" ) -> Pass | R193: =IF(ValidationTable[[#This Row],[Currency]]="","Fail","Pass") -> Pass | S193: =IF( ValidationTable[[#This Row],[Currency]]="CHF", IF(ValidationTable[[#This Row],[Exchange_Rate]]<>1,"Fail","Pass"), IF(ValidationTable[[#This Row],[Exchange_Rate]]<=0,"Fail","Pass") ) -> Pass | T193: =IF(ValidationTable[[#This Row],[VAT_Applicable]]="Yes", IF( ROUND(ValidationTable[[#This Row],[Net_Amount]]*ValidationTable[[#This Row],[VAT_Rate]],2)<>ROUND(ValidationTable[[#This Row],[VAT_Amount]],2), "Fail", "Pass" ), IF( OR(ValidationTable[[#This Row],[VAT_Rate]]<>0,ValidationTable[[#This Row],[VAT_Amount]]<>0 ), "Fail", "Pass" ) ) -> Pass | U193: =IF(LEN(TRIM(ValidationTable[[#This Row],[Bank_Account]]))=0,"Fail","Pass") -> Pass | V193: =IF( COUNTIF(ValidationTable[Record_ID],ValidationTable[[#This Row],[Record_ID]])>1, "Fail", "Pass" ) -> Pass | W193: =IF( COUNTIF(ValidationTable[[#This Row],[RequiredField_Validation]]:ValidationTable[[#This Row],[Duplicate_Validation]],"Fail")>0, "Fail", "Pass" ) -> Pass | X193: =IF(ValidationTable[[#This Row],[Validation_Result]]="Pass","Yes","No") -> Yes
A194: =RawTable[[#This Row],[Record_ID]] -> 193 | B194: =RawTable[[#This Row],[Payment_Type]] -> Payroll | C194: =RawTable[[#This Row],[Entity_Type]] -> Employee | D194: =RawTable[[#This Row],[Country]] -> Germany | E194: =RawTable[[#This Row],[Name]] -> Julia Johnson | F194: =RawTable[[#This Row],[Bank_Account]] -> CH930000000000715720 | G194: =RawTable[[#This Row],[Month]] -> Jan-2026 | H194: =RawTable[[#This Row],[Currency]] -> EUR | I194: =RawTable[[#This Row],[Net_Amount]] -> 6558 | J194: =RawTable[[#This Row],[VAT_Applicable]] -> No | K194: =RawTable[[#This Row],[VAT_Rate]] -> 0 | L194: =RawTable[[#This Row],[VAT_Amount]] -> 0 | M194: =RawTable[[#This Row],[Gross_Amount]] -> 6558 | N194: =RawTable[[#This Row],[Exchange_Rate]] -> 0.90888 | O194: =RawTable[[#This Row],[Amount_CHF]] -> 5960.44 | P194: =IF( OR(ValidationTable[[#This Row],[Record_ID]]="",ValidationTable[[#This Row],[Payment_Type]]="",ValidationTable[[#This Row],[Entity_Type]]="", ValidationTable[[#This Row],[Country]]="", ValidationTable[[#This Row],[Name]]="", ValidationTable[[#This Row],[Month]]="", ValidationTable[[#This Row],[Currency]]="" ), "Fail", "Pass" ) -> Pass | Q194: =IF( OR(ValidationTable[[#This Row],[Net_Amount]]<=0, ROUND(ValidationTable[[#This Row],[Net_Amount]]+ValidationTable[[#This Row],[VAT_Amount]],2)<>ROUND(ValidationTable[[#This Row],[Gross_Amount]],2) ), "Fail", "Pass" ) -> Pass | R194: =IF(ValidationTable[[#This Row],[Currency]]="","Fail","Pass") -> Pass | S194: =IF( ValidationTable[[#This Row],[Currency]]="CHF", IF(ValidationTable[[#This Row],[Exchange_Rate]]<>1,"Fail","Pass"), IF(ValidationTable[[#This Row],[Exchange_Rate]]<=0,"Fail","Pass") ) -> Pass | T194: =IF(ValidationTable[[#This Row],[VAT_Applicable]]="Yes", IF( ROUND(ValidationTable[[#This Row],[Net_Amount]]*ValidationTable[[#This Row],[VAT_Rate]],2)<>ROUND(ValidationTable[[#This Row],[VAT_Amount]],2), "Fail", "Pass" ), IF( OR(ValidationTable[[#This Row],[VAT_Rate]]<>0,ValidationTable[[#This Row],[VAT_Amount]]<>0 ), "Fail", "Pass" ) ) -> Pass | U194: =IF(LEN(TRIM(ValidationTable[[#This Row],[Bank_Account]]))=0,"Fail","Pass") -> Pass | V194: =IF( COUNTIF(ValidationTable[Record_ID],ValidationTable[[#This Row],[Record_ID]])>1, "Fail", "Pass" ) -> Pass | W194: =IF( COUNTIF(ValidationTable[[#This Row],[RequiredField_Validation]]:ValidationTable[[#This Row],[Duplicate_Validation]],"Fail")>0, "Fail", "Pass" ) -> Pass | X194: =IF(ValidationTable[[#This Row],[Validation_Result]]="Pass","Yes","No") -> Yes
A195: =RawTable[[#This Row],[Record_ID]] -> 194 | B195: =RawTable[[#This Row],[Payment_Type]] -> Payroll | C195: =RawTable[[#This Row],[Entity_Type]] -> Employee | D195: =RawTable[[#This Row],[Country]] -> USA | E195: =RawTable[[#This Row],[Name]] -> Anna Ali | F195: =RawTable[[#This Row],[Bank_Account]] -> JO-IBAN-00827115 | G195: =RawTable[[#This Row],[Month]] -> Feb-2026 | H195: =RawTable[[#This Row],[Currency]] -> USD | I195: =RawTable[[#This Row],[Net_Amount]] -> 6846.7 | J195: =RawTable[[#This Row],[VAT_Applicable]] -> No | K195: =RawTable[[#This Row],[VAT_Rate]] -> 0 | L195: =RawTable[[#This Row],[VAT_Amount]] -> 0 | M195: =RawTable[[#This Row],[Gross_Amount]] -> 6846.7 | N195: =RawTable[[#This Row],[Exchange_Rate]] -> 0.77018 | O195: =RawTable[[#This Row],[Amount_CHF]] -> 5273.19 | P195: =IF( OR(ValidationTable[[#This Row],[Record_ID]]="",ValidationTable[[#This Row],[Payment_Type]]="",ValidationTable[[#This Row],[Entity_Type]]="", ValidationTable[[#This Row],[Country]]="", ValidationTable[[#This Row],[Name]]="", ValidationTable[[#This Row],[Month]]="", ValidationTable[[#This Row],[Currency]]="" ), "Fail", "Pass" ) -> Pass | Q195: =IF( OR(ValidationTable[[#This Row],[Net_Amount]]<=0, ROUND(ValidationTable[[#This Row],[Net_Amount]]+ValidationTable[[#This Row],[VAT_Amount]],2)<>ROUND(ValidationTable[[#This Row],[Gross_Amount]],2) ), "Fail", "Pass" ) -> Pass | R195: =IF(ValidationTable[[#This Row],[Currency]]="","Fail","Pass") -> Pass | S195: =IF( ValidationTable[[#This Row],[Currency]]="CHF", IF(ValidationTable[[#This Row],[Exchange_Rate]]<>1,"Fail","Pass"), IF(ValidationTable[[#This Row],[Exchange_Rate]]<=0,"Fail","Pass") ) -> Pass | T195: =IF(ValidationTable[[#This Row],[VAT_Applicable]]="Yes", IF( ROUND(ValidationTable[[#This Row],[Net_Amount]]*ValidationTable[[#This Row],[VAT_Rate]],2)<>ROUND(ValidationTable[[#This Row],[VAT_Amount]],2), "Fail", "Pass" ), IF( OR(ValidationTable[[#This Row],[VAT_Rate]]<>0,ValidationTable[[#This Row],[VAT_Amount]]<>0 ), "Fail", "Pass" ) ) -> Pass | U195: =IF(LEN(TRIM(ValidationTable[[#This Row],[Bank_Account]]))=0,"Fail","Pass") -> Pass | V195: =IF( COUNTIF(ValidationTable[Record_ID],ValidationTable[[#This Row],[Record_ID]])>1, "Fail", "Pass" ) -> Pass | W195: =IF( COUNTIF(ValidationTable[[#This Row],[RequiredField_Validation]]:ValidationTable[[#This Row],[Duplicate_Validation]],"Fail")>0, "Fail", "Pass" ) -> Pass | X195: =IF(ValidationTable[[#This Row],[Validation_Result]]="Pass","Yes","No") -> Yes
... A198: =RawTable[[#This Row],[Record_ID]] -> 197 | B198: =RawTable[[#This Row],[Payment_Type]] -> Payroll | C198: =RawTable[[#This Row],[Entity_Type]] -> Employee | D198: =RawTable[[#This Row],[Country]] -> UAE | E198: =RawTable[[#This Row],[Name]] -> Anna Haddad | F198: =RawTable[[#This Row],[Bank_Account]] -> AE-IBAN-04400001 | G198: =RawTable[[#This Row],[Month]] -> Jan-2026 | H198: =RawTable[[#This Row],[Currency]] -> AED | I198: =RawTable[[#This Row],[Net_Amount]] -> 22763.4 | J198: =RawTable[[#This Row],[VAT_Applicable]] -> No | K198: =RawTable[[#This Row],[VAT_Rate]] -> 0 | L198: =RawTable[[#This Row],[VAT_Amount]] -> 0 | M198: =RawTable[[#This Row],[Gross_Amount]] -> 22763.4 | N198: =RawTable[[#This Row],[Exchange_Rate]] -> 0.21065 | O198: =RawTable[[#This Row],[Amount_CHF]] -> 4795.11 | P198: =IF( OR(ValidationTable[[#This Row],[Record_ID]]="",ValidationTable[[#This Row],[Payment_Type]]="",ValidationTable[[#This Row],[Entity_Type]]="", ValidationTable[[#This Row],[Country]]="", ValidationTable[[#This Row],[Name]]="", ValidationTable[[#This Row],[Month]]="", ValidationTable[[#This Row],[Currency]]="" ), "Fail", "Pass" ) -> Pass | Q198: =IF( OR(ValidationTable[[#This Row],[Net_Amount]]<=0, ROUND(ValidationTable[[#This Row],[Net_Amount]]+ValidationTable[[#This Row],[VAT_Amount]],2)<>ROUND(ValidationTable[[#This Row],[Gross_Amount]],2) ), "Fail", "Pass" ) -> Pass | R198: =IF(ValidationTable[[#This Row],[Currency]]="","Fail","Pass") -> Pass | S198: =IF( ValidationTable[[#This Row],[Currency]]="CHF", IF(ValidationTable[[#This Row],[Exchange_Rate]]<>1,"Fail","Pass"), IF(ValidationTable[[#This Row],[Exchange_Rate]]<=0,"Fail","Pass") ) -> Pass | T198: =IF(ValidationTable[[#This Row],[VAT_Applicable]]="Yes", IF( ROUND(ValidationTable[[#This Row],[Net_Amount]]*ValidationTable[[#This Row],[VAT_Rate]],2)<>ROUND(ValidationTable[[#This Row],[VAT_Amount]],2), "Fail", "Pass" ), IF( OR(ValidationTable[[#This Row],[VAT_Rate]]<>0,ValidationTable[[#This Row],[VAT_Amount]]<>0 ), "Fail", "Pass" ) ) -> Pass | U198: =IF(LEN(TRIM(ValidationTable[[#This Row],[Bank_Account]]))=0,"Fail","Pass") -> Pass | V198: =IF( COUNTIF(ValidationTable[Record_ID],ValidationTable[[#This Row],[Record_ID]])>1, "Fail", "Pass" ) -> Pass | W198: =IF( COUNTIF(ValidationTable[[#This Row],[RequiredField_Validation]]:ValidationTable[[#This Row],[Duplicate_Validation]],"Fail")>0, "Fail", "Pass" ) -> Pass | X198: =IF(ValidationTable[[#This Row],[Validation_Result]]="Pass","Yes","No") -> Yes
A199: =RawTable[[#This Row],[Record_ID]] -> 198 | B199: =RawTable[[#This Row],[Payment_Type]] -> Payroll | C199: =RawTable[[#This Row],[Entity_Type]] -> Employee | D199: =RawTable[[#This Row],[Country]] -> Germany | E199: =RawTable[[#This Row],[Name]] -> Laura Brown | G199: =RawTable[[#This Row],[Month]] -> Mar-2026 | H199: =RawTable[[#This Row],[Currency]] -> EUR | I199: =RawTable[[#This Row],[Net_Amount]] -> 6108.88 | J199: =RawTable[[#This Row],[VAT_Applicable]] -> No | K199: =RawTable[[#This Row],[VAT_Rate]] -> 0 | L199: =RawTable[[#This Row],[VAT_Amount]] -> 0 | M199: =RawTable[[#This Row],[Gross_Amount]] -> 6108.88 | N199: =RawTable[[#This Row],[Exchange_Rate]] -> 0.90888 | O199: =RawTable[[#This Row],[Amount_CHF]] -> 5552.24 | P199: =IF( OR(ValidationTable[[#This Row],[Record_ID]]="",ValidationTable[[#This Row],[Payment_Type]]="",ValidationTable[[#This Row],[Entity_Type]]="", ValidationTable[[#This Row],[Country]]="", ValidationTable[[#This Row],[Name]]="", ValidationTable[[#This Row],[Month]]="", ValidationTable[[#This Row],[Currency]]="" ), "Fail", "Pass" ) -> Pass | Q199: =IF( OR(ValidationTable[[#This Row],[Net_Amount]]<=0, ROUND(ValidationTable[[#This Row],[Net_Amount]]+ValidationTable[[#This Row],[VAT_Amount]],2)<>ROUND(ValidationTable[[#This Row],[Gross_Amount]],2) ), "Fail", "Pass" ) -> Pass | R199: =IF(ValidationTable[[#This Row],[Currency]]="","Fail","Pass") -> Pass | S199: =IF( ValidationTable[[#This Row],[Currency]]="CHF", IF(ValidationTable[[#This Row],[Exchange_Rate]]<>1,"Fail","Pass"), IF(ValidationTable[[#This Row],[Exchange_Rate]]<=0,"Fail","Pass") ) -> Pass | T199: =IF(ValidationTable[[#This Row],[VAT_Applicable]]="Yes", IF( ROUND(ValidationTable[[#This Row],[Net_Amount]]*ValidationTable[[#This Row],[VAT_Rate]],2)<>ROUND(ValidationTable[[#This Row],[VAT_Amount]],2), "Fail", "Pass" ), IF( OR(ValidationTable[[#This Row],[VAT_Rate]]<>0,ValidationTable[[#This Row],[VAT_Amount]]<>0 ), "Fail", "Pass" ) ) -> Pass | U199: =IF(LEN(TRIM(ValidationTable[[#This Row],[Bank_Account]]))=0,"Fail","Pass") -> Fail | V199: =IF( COUNTIF(ValidationTable[Record_ID],ValidationTable[[#This Row],[Record_ID]])>1, "Fail", "Pass" ) -> Pass | W199: =IF( COUNTIF(ValidationTable[[#This Row],[RequiredField_Validation]]:ValidationTable[[#This Row],[Duplicate_Validation]],"Fail")>0, "Fail", "Pass" ) -> Fail | X199: =IF(ValidationTable[[#This Row],[Validation_Result]]="Pass","Yes","No") -> No
A200: =RawTable[[#This Row],[Record_ID]] -> 199 | B200: =RawTable[[#This Row],[Payment_Type]] -> Payroll | C200: =RawTable[[#This Row],[Entity_Type]] -> Employee | D200: =RawTable[[#This Row],[Country]] -> Switzerland | E200: =RawTable[[#This Row],[Name]] -> Ahmed Haddad | F200: =RawTable[[#This Row],[Bank_Account]] -> JO-IBAN-00209865 | G200: =RawTable[[#This Row],[Month]] -> Mar-2026 | H200: =RawTable[[#This Row],[Currency]] -> CHF | I200: =RawTable[[#This Row],[Net_Amount]] -> 6766.5 | J200: =RawTable[[#This Row],[VAT_Applicable]] -> No | K200: =RawTable[[#This Row],[VAT_Rate]] -> 0 | L200: =RawTable[[#This Row],[VAT_Amount]] -> 0 | M200: =RawTable[[#This Row],[Gross_Amount]] -> 6766.5 | N200: =RawTable[[#This Row],[Exchange_Rate]] -> 1 | O200: =RawTable[[#This Row],[Amount_CHF]] -> 6766.5 | P200: =IF( OR(ValidationTable[[#This Row],[Record_ID]]="",ValidationTable[[#This Row],[Payment_Type]]="",ValidationTable[[#This Row],[Entity_Type]]="", ValidationTable[[#This Row],[Country]]="", ValidationTable[[#This Row],[Name]]="", ValidationTable[[#This Row],[Month]]="", ValidationTable[[#This Row],[Currency]]="" ), "Fail", "Pass" ) -> Pass | Q200: =IF( OR(ValidationTable[[#This Row],[Net_Amount]]<=0, ROUND(ValidationTable[[#This Row],[Net_Amount]]+ValidationTable[[#This Row],[VAT_Amount]],2)<>ROUND(ValidationTable[[#This Row],[Gross_Amount]],2) ), "Fail", "Pass" ) -> Pass | R200: =IF(ValidationTable[[#This Row],[Currency]]="","Fail","Pass") -> Pass | S200: =IF( ValidationTable[[#This Row],[Currency]]="CHF", IF(ValidationTable[[#This Row],[Exchange_Rate]]<>1,"Fail","Pass"), IF(ValidationTable[[#This Row],[Exchange_Rate]]<=0,"Fail","Pass") ) -> Pass | T200: =IF(ValidationTable[[#This Row],[VAT_Applicable]]="Yes", IF( ROUND(ValidationTable[[#This Row],[Net_Amount]]*ValidationTable[[#This Row],[VAT_Rate]],2)<>ROUND(ValidationTable[[#This Row],[VAT_Amount]],2), "Fail", "Pass" ), IF( OR(ValidationTable[[#This Row],[VAT_Rate]]<>0,ValidationTable[[#This Row],[VAT_Amount]]<>0 ), "Fail", "Pass" ) ) -> Pass | U200: =IF(LEN(TRIM(ValidationTable[[#This Row],[Bank_Account]]))=0,"Fail","Pass") -> Pass | V200: =IF( COUNTIF(ValidationTable[Record_ID],ValidationTable[[#This Row],[Record_ID]])>1, "Fail", "Pass" ) -> Pass | W200: =IF( COUNTIF(ValidationTable[[#This Row],[RequiredField_Validation]]:ValidationTable[[#This Row],[Duplicate_Validation]],"Fail")>0, "Fail", "Pass" ) -> Pass | X200: =IF(ValidationTable[[#This Row],[Validation_Result]]="Pass","Yes","No") -> Yes
A201: =RawTable[[#This Row],[Record_ID]] -> 200 | B201: =RawTable[[#This Row],[Payment_Type]] -> Payroll | C201: =RawTable[[#This Row],[Entity_Type]] -> Employee | D201: =RawTable[[#This Row],[Country]] -> Jordan | E201: =RawTable[[#This Row],[Name]] -> Omar Khan | G201: =RawTable[[#This Row],[Month]] -> Jan-2026 | H201: =RawTable[[#This Row],[Currency]] -> JOD | I201: =RawTable[[#This Row],[Net_Amount]] -> 1748.89 | J201: =RawTable[[#This Row],[VAT_Applicable]] -> No | K201: =RawTable[[#This Row],[VAT_Rate]] -> 0 | L201: =RawTable[[#This Row],[VAT_Amount]] -> 0 | M201: =RawTable[[#This Row],[Gross_Amount]] -> 1748.89 | N201: =RawTable[[#This Row],[Exchange_Rate]] -> 1.08643 | O201: =RawTable[[#This Row],[Amount_CHF]] -> 1900.05 | P201: =IF( OR(ValidationTable[[#This Row],[Record_ID]]="",ValidationTable[[#This Row],[Payment_Type]]="",ValidationTable[[#This Row],[Entity_Type]]="", ValidationTable[[#This Row],[Country]]="", ValidationTable[[#This Row],[Name]]="", ValidationTable[[#This Row],[Month]]="", ValidationTable[[#This Row],[Currency]]="" ), "Fail", "Pass" ) -> Pass | Q201: =IF( OR(ValidationTable[[#This Row],[Net_Amount]]<=0, ROUND(ValidationTable[[#This Row],[Net_Amount]]+ValidationTable[[#This Row],[VAT_Amount]],2)<>ROUND(ValidationTable[[#This Row],[Gross_Amount]],2) ), "Fail", "Pass" ) -> Pass | R201: =IF(ValidationTable[[#This Row],[Currency]]="","Fail","Pass") -> Pass | S201: =IF( ValidationTable[[#This Row],[Currency]]="CHF", IF(ValidationTable[[#This Row],[Exchange_Rate]]<>1,"Fail","Pass"), IF(ValidationTable[[#This Row],[Exchange_Rate]]<=0,"Fail","Pass") ) -> Pass | T201: =IF(ValidationTable[[#This Row],[VAT_Applicable]]="Yes", IF( ROUND(ValidationTable[[#This Row],[Net_Amount]]*ValidationTable[[#This Row],[VAT_Rate]],2)<>ROUND(ValidationTable[[#This Row],[VAT_Amount]],2), "Fail", "Pass" ), IF( OR(ValidationTable[[#This Row],[VAT_Rate]]<>0,ValidationTable[[#This Row],[VAT_Amount]]<>0 ), "Fail", "Pass" ) ) -> Pass | U201: =IF(LEN(TRIM(ValidationTable[[#This Row],[Bank_Account]]))=0,"Fail","Pass") -> Fail | V201: =IF( COUNTIF(ValidationTable[Record_ID],ValidationTable[[#This Row],[Record_ID]])>1, "Fail", "Pass" ) -> Pass | W201: =IF( COUNTIF(ValidationTable[[#This Row],[RequiredField_Validation]]:ValidationTable[[#This Row],[Duplicate_Validation]],"Fail")>0, "Fail", "Pass" ) -> Fail | X201: =IF(ValidationTable[[#This Row],[Validation_Result]]="Pass","Yes","No") -> No
A202: =RawTable[[#This Row],[Record_ID]] -> 201 | B202: =RawTable[[#This Row],[Payment_Type]] -> Contractor_Fee | C202: =RawTable[[#This Row],[Entity_Type]] -> Contractor | D202: =RawTable[[#This Row],[Country]] -> USA | E202: =RawTable[[#This Row],[Name]] -> Sara Schmidt | F202: =RawTable[[#This Row],[Bank_Account]] -> US-RT-000065402-AC-0000300934 | G202: =RawTable[[#This Row],[Month]] -> Feb-2026 | H202: =RawTable[[#This Row],[Currency]] -> USD | I202: =RawTable[[#This Row],[Net_Amount]] -> 5830.16 | J202: =RawTable[[#This Row],[VAT_Applicable]] -> No | K202: =RawTable[[#This Row],[VAT_Rate]] -> 0 | L202: =RawTable[[#This Row],[VAT_Amount]] -> 0 | M202: =RawTable[[#This Row],[Gross_Amount]] -> 5830.16 | N202: =RawTable[[#This Row],[Exchange_Rate]] -> 0.77018 | O202: =RawTable[[#This Row],[Amount_CHF]] -> 4490.27 | P202: =IF( OR(ValidationTable[[#This Row],[Record_ID]]="",ValidationTable[[#This Row],[Payment_Type]]="",ValidationTable[[#This Row],[Entity_Type]]="", ValidationTable[[#This Row],[Country]]="", ValidationTable[[#This Row],[Name]]="", ValidationTable[[#This Row],[Month]]="", ValidationTable[[#This Row],[Currency]]="" ), "Fail", "Pass" ) -> Pass | Q202: =IF( OR(ValidationTable[[#This Row],[Net_Amount]]<=0, ROUND(ValidationTable[[#This Row],[Net_Amount]]+ValidationTable[[#This Row],[VAT_Amount]],2)<>ROUND(ValidationTable[[#This Row],[Gross_Amount]],2) ), "Fail", "Pass" ) -> Pass | R202: =IF(ValidationTable[[#This Row],[Currency]]="","Fail","Pass") -> Pass | S202: =IF( ValidationTable[[#This Row],[Currency]]="CHF", IF(ValidationTable[[#This Row],[Exchange_Rate]]<>1,"Fail","Pass"), IF(ValidationTable[[#This Row],[Exchange_Rate]]<=0,"Fail","Pass") ) -> Pass | T202: =IF(ValidationTable[[#This Row],[VAT_Applicable]]="Yes", IF( ROUND(ValidationTable[[#This Row],[Net_Amount]]*ValidationTable[[#This Row],[VAT_Rate]],2)<>ROUND(ValidationTable[[#This Row],[VAT_Amount]],2), "Fail", "Pass" ), IF( OR(ValidationTable[[#This Row],[VAT_Rate]]<>0,ValidationTable[[#This Row],[VAT_Amount]]<>0 ), "Fail", "Pass" ) ) -> Pass | U202: =IF(LEN(TRIM(ValidationTable[[#This Row],[Bank_Account]]))=0,"Fail","Pass") -> Pass | V202: =IF( COUNTIF(ValidationTable[Record_ID],ValidationTable[[#This Row],[Record_ID]])>1, "Fail", "Pass" ) -> Pass | W202: =IF( COUNTIF(ValidationTable[[#This Row],[RequiredField_Validation]]:ValidationTable[[#This Row],[Duplicate_Validation]],"Fail")>0, "Fail", "Pass" ) -> Pass | X202: =IF(ValidationTable[[#This Row],[Validation_Result]]="Pass","Yes","No") -> Yes
A203: =RawTable[[#This Row],[Record_ID]] -> 202 | B203: =RawTable[[#This Row],[Payment_Type]] -> Contractor_Fee | C203: =RawTable[[#This Row],[Entity_Type]] -> Contractor | D203: =RawTable[[#This Row],[Country]] -> Switzerland | E203: =RawTable[[#This Row],[Name]] -> Anna Smith | F203: =RawTable[[#This Row],[Bank_Account]] -> CH930000000002023760 | G203: =RawTable[[#This Row],[Month]] -> Jan-2026 | H203: =RawTable[[#This Row],[Currency]] -> CHF | I203: =RawTable[[#This Row],[Net_Amount]] -> 5281.12 | J203: =RawTable[[#This Row],[VAT_Applicable]] -> No | K203: =RawTable[[#This Row],[VAT_Rate]] -> 0 | L203: =RawTable[[#This Row],[VAT_Amount]] -> 0 | M203: =RawTable[[#This Row],[Gross_Amount]] -> 5281.12 | N203: =RawTable[[#This Row],[Exchange_Rate]] -> 1 | O203: =RawTable[[#This Row],[Amount_CHF]] -> 5281.12 | P203: =IF( OR(ValidationTable[[#This Row],[Record_ID]]="",ValidationTable[[#This Row],[Payment_Type]]="",ValidationTable[[#This Row],[Entity_Type]]="", ValidationTable[[#This Row],[Country]]="", ValidationTable[[#This Row],[Name]]="", ValidationTable[[#This Row],[Month]]="", ValidationTable[[#This Row],[Currency]]="" ), "Fail", "Pass" ) -> Pass | Q203: =IF( OR(ValidationTable[[#This Row],[Net_Amount]]<=0, ROUND(ValidationTable[[#This Row],[Net_Amount]]+ValidationTable[[#This Row],[VAT_Amount]],2)<>ROUND(ValidationTable[[#This Row],[Gross_Amount]],2) ), "Fail", "Pass" ) -> Pass | R203: =IF(ValidationTable[[#This Row],[Currency]]="","Fail","Pass") -> Pass | S203: =IF( ValidationTable[[#This Row],[Currency]]="CHF", IF(ValidationTable[[#This Row],[Exchange_Rate]]<>1,"Fail","Pass"), IF(ValidationTable[[#This Row],[Exchange_Rate]]<=0,"Fail","Pass") ) -> Pass | T203: =IF(ValidationTable[[#This Row],[VAT_Applicable]]="Yes", IF( ROUND(ValidationTable[[#This Row],[Net_Amount]]*ValidationTable[[#This Row],[VAT_Rate]],2)<>ROUND(ValidationTable[[#This Row],[VAT_Amount]],2), "Fail", "Pass" ), IF( OR(ValidationTable[[#This Row],[VAT_Rate]]<>0,ValidationTable[[#This Row],[VAT_Amount]]<>0 ), "Fail", "Pass" ) ) -> Pass | U203: =IF(LEN(TRIM(ValidationTable[[#This Row],[Bank_Account]]))=0,"Fail","Pass") -> Pass | V203: =IF( COUNTIF(ValidationTable[Record_ID],ValidationTable[[#This Row],[Record_ID]])>1, "Fail", "Pass" ) -> Pass | W203: =IF( COUNTIF(ValidationTable[[#This Row],[RequiredField_Validation]]:ValidationTable[[#This Row],[Duplicate_Validation]],"Fail")>0, "Fail", "Pass" ) -> Pass | X203: =IF(ValidationTable[[#This Row],[Validation_Result]]="Pass","Yes","No") -> Yes
A204: =RawTable[[#This Row],[Record_ID]] -> 203 | B204: =RawTable[[#This Row],[Payment_Type]] -> Contractor_Fee | C204: =RawTable[[#This Row],[Entity_Type]] -> Contractor | D204: =RawTable[[#This Row],[Country]] -> USA | E204: =RawTable[[#This Row],[Name]] -> Sara Taylor | F204: =RawTable[[#This Row],[Bank_Account]] -> JO-IBAN-00777735 | G204: =RawTable[[#This Row],[Month]] -> Mar-2026 | H204: =RawTable[[#This Row],[Currency]] -> USD | I204: =RawTable[[#This Row],[Net_Amount]] -> 5892.32 | J204: =RawTable[[#This Row],[VAT_Applicable]] -> No | K204: =RawTable[[#This Row],[VAT_Rate]] -> 0 | L204: =RawTable[[#This Row],[VAT_Amount]] -> 0 | M204: =RawTable[[#This Row],[Gross_Amount]] -> 5892.32 | N204: =RawTable[[#This Row],[Exchange_Rate]] -> 0.77018 | O204: =RawTable[[#This Row],[Amount_CHF]] -> 4538.15 | P204: =IF( OR(ValidationTable[[#This Row],[Record_ID]]="",ValidationTable[[#This Row],[Payment_Type]]="",ValidationTable[[#This Row],[Entity_Type]]="", ValidationTable[[#This Row],[Country]]="", ValidationTable[[#This Row],[Name]]="", ValidationTable[[#This Row],[Month]]="", ValidationTable[[#This Row],[Currency]]="" ), "Fail", "Pass" ) -> Pass | Q204: =IF( OR(ValidationTable[[#This Row],[Net_Amount]]<=0, ROUND(ValidationTable[[#This Row],[Net_Amount]]+ValidationTable[[#This Row],[VAT_Amount]],2)<>ROUND(ValidationTable[[#This Row],[Gross_Amount]],2) ), "Fail", "Pass" ) -> Pass | R204: =IF(ValidationTable[[#This Row],[Currency]]="","Fail","Pass") -> Pass | S204: =IF( ValidationTable[[#This Row],[Currency]]="CHF", IF(ValidationTable[[#This Row],[Exchange_Rate]]<>1,"Fail","Pass"), IF(ValidationTable[[#This Row],[Exchange_Rate]]<=0,"Fail","Pass") ) -> Pass | T204: =IF(ValidationTable[[#This Row],[VAT_Applicable]]="Yes", IF( ROUND(ValidationTable[[#This Row],[Net_Amount]]*ValidationTable[[#This Row],[VAT_Rate]],2)<>ROUND(ValidationTable[[#This Row],[VAT_Amount]],2), "Fail", "Pass" ), IF( OR(ValidationTable[[#This Row],[VAT_Rate]]<>0,ValidationTable[[#This Row],[VAT_Amount]]<>0 ), "Fail", "Pass" ) ) -> Pass | U204: =IF(LEN(TRIM(ValidationTable[[#This Row],[Bank_Account]]))=0,"Fail","Pass") -> Pass | V204: =IF( COUNTIF(ValidationTable[Record_ID],ValidationTable[[#This Row],[Record_ID]])>1, "Fail", "Pass" ) -> Pass | W204: =IF( COUNTIF(ValidationTable[[#This Row],[RequiredField_Validation]]:ValidationTable[[#This Row],[Duplicate_Validation]],"Fail")>0, "Fail", "Pass" ) -> Pass | X204: =IF(ValidationTable[[#This Row],[Validation_Result]]="Pass","Yes","No") -> Yes
A205: =RawTable[[#This Row],[Record_ID]] -> 204 | B205: =RawTable[[#This Row],[Payment_Type]] -> Contractor_Fee | C205: =RawTable[[#This Row],[Entity_Type]] -> Contractor | D205: =RawTable[[#This Row],[Country]] -> Switzerland | E205: =RawTable[[#This Row],[Name]] -> David Haddad | F205: =RawTable[[#This Row],[Bank_Account]] -> DE890000000000095053 | G205: =RawTable[[#This Row],[Month]] -> Mar-2026 | H205: =RawTable[[#This Row],[Currency]] -> CHF | I205: =RawTable[[#This Row],[Net_Amount]] -> 5005 | J205: =RawTable[[#This Row],[VAT_Applicable]] -> No | K205: =RawTable[[#This Row],[VAT_Rate]] -> 0 | L205: =RawTable[[#This Row],[VAT_Amount]] -> 0 | M205: =RawTable[[#This Row],[Gross_Amount]] -> 5005 | N205: =RawTable[[#This Row],[Exchange_Rate]] -> 1 | O205: =RawTable[[#This Row],[Amount_CHF]] -> 5005 | P205: =IF( OR(ValidationTable[[#This Row],[Record_ID]]="",ValidationTable[[#This Row],[Payment_Type]]="",ValidationTable[[#This Row],[Entity_Type]]="", ValidationTable[[#This Row],[Country]]="", ValidationTable[[#This Row],[Name]]="", ValidationTable[[#This Row],[Month]]="", ValidationTable[[#This Row],[Currency]]="" ), "Fail", "Pass" ) -> Pass | Q205: =IF( OR(ValidationTable[[#This Row],[Net_Amount]]<=0, ROUND(ValidationTable[[#This Row],[Net_Amount]]+ValidationTable[[#This Row],[VAT_Amount]],2)<>ROUND(ValidationTable[[#This Row],[Gross_Amount]],2) ), "Fail", "Pass" ) -> Pass | R205: =IF(ValidationTable[[#This Row],[Currency]]="","Fail","Pass") -> Pass | S205: =IF( ValidationTable[[#This Row],[Currency]]="CHF", IF(ValidationTable[[#This Row],[Exchange_Rate]]<>1,"Fail","Pass"), IF(ValidationTable[[#This Row],[Exchange_Rate]]<=0,"Fail","Pass") ) -> Pass | T205: =IF(ValidationTable[[#This Row],[VAT_Applicable]]="Yes", IF( ROUND(ValidationTable[[#This Row],[Net_Amount]]*ValidationTable[[#This Row],[VAT_Rate]],2)<>ROUND(ValidationTable[[#This Row],[VAT_Amount]],2), "Fail", "Pass" ), IF( OR(ValidationTable[[#This Row],[VAT_Rate]]<>0,ValidationTable[[#This Row],[VAT_Amount]]<>0 ), "Fail", "Pass" ) ) -> Pass | U205: =IF(LEN(TRIM(ValidationTable[[#This Row],[Bank_Account]]))=0,"Fail","Pass") -> Pass | V205: =IF( COUNTIF(ValidationTable[Record_ID],ValidationTable[[#This Row],[Record_ID]])>1, "Fail", "Pass" ) -> Pass | W205: =IF( COUNTIF(ValidationTable[[#This Row],[RequiredField_Validation]]:ValidationTable[[#This Row],[Duplicate_Validation]],"Fail")>0, "Fail", "Pass" ) -> Pass | X205: =IF(ValidationTable[[#This Row],[Validation_Result]]="Pass","Yes","No") -> Yes
A206: =RawTable[[#This Row],[Record_ID]] -> 205 | B206: =RawTable[[#This Row],[Payment_Type]] -> Contractor_Fee | C206: =RawTable[[#This Row],[Entity_Type]] -> Contractor | D206: =RawTable[[#This Row],[Country]] -> Jordan | E206: =RawTable[[#This Row],[Name]] -> John Ali | F206: =RawTable[[#This Row],[Bank_Account]] -> DE890000000000312317 | G206: =RawTable[[#This Row],[Month]] -> Feb-2026 | H206: =RawTable[[#This Row],[Currency]] -> JOD | I206: =RawTable[[#This Row],[Net_Amount]] -> 1382.26 | J206: =RawTable[[#This Row],[VAT_Applicable]] -> No | K206: =RawTable[[#This Row],[VAT_Rate]] -> 0 | L206: =RawTable[[#This Row],[VAT_Amount]] -> 0 | M206: =RawTable[[#This Row],[Gross_Amount]] -> 1382.26 | N206: =RawTable[[#This Row],[Exchange_Rate]] -> 1.08643 | O206: =RawTable[[#This Row],[Amount_CHF]] -> 1501.73 | P206: =IF( OR(ValidationTable[[#This Row],[Record_ID]]="",ValidationTable[[#This Row],[Payment_Type]]="",ValidationTable[[#This Row],[Entity_Type]]="", ValidationTable[[#This Row],[Country]]="", ValidationTable[[#This Row],[Name]]="", ValidationTable[[#This Row],[Month]]="", ValidationTable[[#This Row],[Currency]]="" ), "Fail", "Pass" ) -> Pass | Q206: =IF( OR(ValidationTable[[#This Row],[Net_Amount]]<=0, ROUND(ValidationTable[[#This Row],[Net_Amount]]+ValidationTable[[#This Row],[VAT_Amount]],2)<>ROUND(ValidationTable[[#This Row],[Gross_Amount]],2) ), "Fail", "Pass" ) -> Pass | R206: =IF(ValidationTable[[#This Row],[Currency]]="","Fail","Pass") -> Pass | S206: =IF( ValidationTable[[#This Row],[Currency]]="CHF", IF(ValidationTable[[#This Row],[Exchange_Rate]]<>1,"Fail","Pass"), IF(ValidationTable[[#This Row],[Exchange_Rate]]<=0,"Fail","Pass") ) -> Pass | T206: =IF(ValidationTable[[#This Row],[VAT_Applicable]]="Yes", IF( ROUND(ValidationTable[[#This Row],[Net_Amount]]*ValidationTable[[#This Row],[VAT_Rate]],2)<>ROUND(ValidationTable[[#This Row],[VAT_Amount]],2), "Fail", "Pass" ), IF( OR(ValidationTable[[#This Row],[VAT_Rate]]<>0,ValidationTable[[#This Row],[VAT_Amount]]<>0 ), "Fail", "Pass" ) ) -> Pass | U206: =IF(LEN(TRIM(ValidationTable[[#This Row],[Bank_Account]]))=0,"Fail","Pass") -> Pass | V206: =IF( COUNTIF(ValidationTable[Record_ID],ValidationTable[[#This Row],[Record_ID]])>1, "Fail", "Pass" ) -> Pass | W206: =IF( COUNTIF(ValidationTable[[#This Row],[RequiredField_Validation]]:ValidationTable[[#This Row],[Duplicate_Validation]],"Fail")>0, "Fail", "Pass" ) -> Pass | X206: =IF(ValidationTable[[#This Row],[Validation_Result]]="Pass","Yes","No") -> Yes
A207: =RawTable[[#This Row],[Record_ID]] -> 206 | B207: =RawTable[[#This Row],[Payment_Type]] -> Contractor_Fee | C207: =RawTable[[#This Row],[Entity_Type]] -> Contractor | D207: =RawTable[[#This Row],[Country]] -> USA | E207: =RawTable[[#This Row],[Name]] -> Ahmed Brown | F207: =RawTable[[#This Row],[Bank_Account]] -> US-RT-000102422-AC-0000471274 | G207: =RawTable[[#This Row],[Month]] -> Mar-2026 | H207: =RawTable[[#This Row],[Currency]] -> USD | I207: =RawTable[[#This Row],[Net_Amount]] -> 5708.64 | J207: =RawTable[[#This Row],[VAT_Applicable]] -> No | K207: =RawTable[[#This Row],[VAT_Rate]] -> 0 | L207: =RawTable[[#This Row],[VAT_Amount]] -> 0 | M207: =RawTable[[#This Row],[Gross_Amount]] -> 5708.64 | N207: =RawTable[[#This Row],[Exchange_Rate]] -> 0.77018 | O207: =RawTable[[#This Row],[Amount_CHF]] -> 4396.68 | P207: =IF( OR(ValidationTable[[#This Row],[Record_ID]]="",ValidationTable[[#This Row],[Payment_Type]]="",ValidationTable[[#This Row],[Entity_Type]]="", ValidationTable[[#This Row],[Country]]="", ValidationTable[[#This Row],[Name]]="", ValidationTable[[#This Row],[Month]]="", ValidationTable[[#This Row],[Currency]]="" ), "Fail", "Pass" ) -> Pass | Q207: =IF( OR(ValidationTable[[#This Row],[Net_Amount]]<=0, ROUND(ValidationTable[[#This Row],[Net_Amount]]+ValidationTable[[#This Row],[VAT_Amount]],2)<>ROUND(ValidationTable[[#This Row],[Gross_Amount]],2) ), "Fail", "Pass" ) -> Pass | R207: =IF(ValidationTable[[#This Row],[Currency]]="","Fail","Pass") -> Pass | S207: =IF( ValidationTable[[#This Row],[Currency]]="CHF", IF(ValidationTable[[#This Row],[Exchange_Rate]]<>1,"Fail","Pass"), IF(ValidationTable[[#This Row],[Exchange_Rate]]<=0,"Fail","Pass") ) -> Pass | T207: =IF(ValidationTable[[#This Row],[VAT_Applicable]]="Yes", IF( ROUND(ValidationTable[[#This Row],[Net_Amount]]*ValidationTable[[#This Row],[VAT_Rate]],2)<>ROUND(ValidationTable[[#This Row],[VAT_Amount]],2), "Fail", "Pass" ), IF( OR(ValidationTable[[#This Row],[VAT_Rate]]<>0,ValidationTable[[#This Row],[VAT_Amount]]<>0 ), "Fail", "Pass" ) ) -> Pass | U207: =IF(LEN(TRIM(ValidationTable[[#This Row],[Bank_Account]]))=0,"Fail","Pass") -> Pass | V207: =IF( COUNTIF(ValidationTable[Record_ID],ValidationTable[[#This Row],[Record_ID]])>1, "Fail", "Pass" ) -> Pass | W207: =IF( COUNTIF(ValidationTable[[#This Row],[RequiredField_Validation]]:ValidationTable[[#This Row],[Duplicate_Validation]],"Fail")>0, "Fail", "Pass" ) -> Pass | X207: =IF(ValidationTable[[#This Row],[Validation_Result]]="Pass","Yes","No") -> Yes
A208: =RawTable[[#This Row],[Record_ID]] -> 207 | B208: =RawTable[[#This Row],[Payment_Type]] -> Contractor_Fee | C208: =RawTable[[#This Row],[Entity_Type]] -> Contractor | D208: =RawTable[[#This Row],[Country]] -> UAE | E208: =RawTable[[#This Row],[Name]] -> Laura Müller | F208: =RawTable[[#This Row],[Bank_Account]] -> US-RT-000095018-AC-0000437206 | G208: =RawTable[[#This Row],[Month]] -> Mar-2026 | H208: =RawTable[[#This Row],[Currency]] -> AED | I208: =RawTable[[#This Row],[Net_Amount]] -> 17932.64 | J208: =RawTable[[#This Row],[VAT_Applicable]] -> No | K208: =RawTable[[#This Row],[VAT_Rate]] -> 0 | L208: =RawTable[[#This Row],[VAT_Amount]] -> 0 | M208: =RawTable[[#This Row],[Gross_Amount]] -> 17932.64 | N208: =RawTable[[#This Row],[Exchange_Rate]] -> 0.21065 | O208: =RawTable[[#This Row],[Amount_CHF]] -> 3777.51 | P208: =IF( OR(ValidationTable[[#This Row],[Record_ID]]="",ValidationTable[[#This Row],[Payment_Type]]="",ValidationTable[[#This Row],[Entity_Type]]="", ValidationTable[[#This Row],[Country]]="", ValidationTable[[#This Row],[Name]]="", ValidationTable[[#This Row],[Month]]="", ValidationTable[[#This Row],[Currency]]="" ), "Fail", "Pass" ) -> Pass | Q208: =IF( OR(ValidationTable[[#This Row],[Net_Amount]]<=0, ROUND(ValidationTable[[#This Row],[Net_Amount]]+ValidationTable[[#This Row],[VAT_Amount]],2)<>ROUND(ValidationTable[[#This Row],[Gross_Amount]],2) ), "Fail", "Pass" ) -> Pass | R208: =IF(ValidationTable[[#This Row],[Currency]]="","Fail","Pass") -> Pass | S208: =IF( ValidationTable[[#This Row],[Currency]]="CHF", IF(ValidationTable[[#This Row],[Exchange_Rate]]<>1,"Fail","Pass"), IF(ValidationTable[[#This Row],[Exchange_Rate]]<=0,"Fail","Pass") ) -> Pass | T208: =IF(ValidationTable[[#This Row],[VAT_Applicable]]="Yes", IF( ROUND(ValidationTable[[#This Row],[Net_Amount]]*ValidationTable[[#This Row],[VAT_Rate]],2)<>ROUND(ValidationTable[[#This Row],[VAT_Amount]],2), "Fail", "Pass" ), IF( OR(ValidationTable[[#This Row],[VAT_Rate]]<>0,ValidationTable[[#This Row],[VAT_Amount]]<>0 ), "Fail", "Pass" ) ) -> Pass | U208: =IF(LEN(TRIM(ValidationTable[[#This Row],[Bank_Account]]))=0,"Fail","Pass") -> Pass | V208: =IF( COUNTIF(ValidationTable[Record_ID],ValidationTable[[#This Row],[Record_ID]])>1, "Fail", "Pass" ) -> Pass | W208: =IF( COUNTIF(ValidationTable[[#This Row],[RequiredField_Validation]]:ValidationTable[[#This Row],[Duplicate_Validation]],"Fail")>0, "Fail", "Pass" ) -> Pass | X208: =IF(ValidationTable[[#This Row],[Validation_Result]]="Pass","Yes","No") -> Yes
A209: =RawTable[[#This Row],[Record_ID]] -> 208 | B209: =RawTable[[#This Row],[Payment_Type]] -> Contractor_Fee | C209: =RawTable[[#This Row],[Entity_Type]] -> Contractor | D209: =RawTable[[#This Row],[Country]] -> Germany | E209: =RawTable[[#This Row],[Name]] -> Laura Johnson | F209: =RawTable[[#This Row],[Bank_Account]] -> DE890000000001140636 | G209: =RawTable[[#This Row],[Month]] -> Mar-2026 | H209: =RawTable[[#This Row],[Currency]] -> EUR | I209: =RawTable[[#This Row],[Net_Amount]] -> 4619.04 | J209: =RawTable[[#This Row],[VAT_Applicable]] -> No | K209: =RawTable[[#This Row],[VAT_Rate]] -> 0 | L209: =RawTable[[#This Row],[VAT_Amount]] -> 0 | M209: =RawTable[[#This Row],[Gross_Amount]] -> 4619.04 | N209: =RawTable[[#This Row],[Exchange_Rate]] -> 0.90888 | O209: =RawTable[[#This Row],[Amount_CHF]] -> 4198.15 | P209: =IF( OR(ValidationTable[[#This Row],[Record_ID]]="",ValidationTable[[#This Row],[Payment_Type]]="",ValidationTable[[#This Row],[Entity_Type]]="", ValidationTable[[#This Row],[Country]]="", ValidationTable[[#This Row],[Name]]="", ValidationTable[[#This Row],[Month]]="", ValidationTable[[#This Row],[Currency]]="" ), "Fail", "Pass" ) -> Pass | Q209: =IF( OR(ValidationTable[[#This Row],[Net_Amount]]<=0, ROUND(ValidationTable[[#This Row],[Net_Amount]]+ValidationTable[[#This Row],[VAT_Amount]],2)<>ROUND(ValidationTable[[#This Row],[Gross_Amount]],2) ), "Fail", "Pass" ) -> Pass | R209: =IF(ValidationTable[[#This Row],[Currency]]="","Fail","Pass") -> Pass | S209: =IF( ValidationTable[[#This Row],[Currency]]="CHF", IF(ValidationTable[[#This Row],[Exchange_Rate]]<>1,"Fail","Pass"), IF(ValidationTable[[#This Row],[Exchange_Rate]]<=0,"Fail","Pass") ) -> Pass | T209: =IF(ValidationTable[[#This Row],[VAT_Applicable]]="Yes", IF( ROUND(ValidationTable[[#This Row],[Net_Amount]]*ValidationTable[[#This Row],[VAT_Rate]],2)<>ROUND(ValidationTable[[#This Row],[VAT_Amount]],2), "Fail", "Pass" ), IF( OR(ValidationTable[[#This Row],[VAT_Rate]]<>0,ValidationTable[[#This Row],[VAT_Amount]]<>0 ), "Fail", "Pass" ) ) -> Pass | U209: =IF(LEN(TRIM(ValidationTable[[#This Row],[Bank_Account]]))=0,"Fail","Pass") -> Pass | V209: =IF( COUNTIF(ValidationTable[Record_ID],ValidationTable[[#This Row],[Record_ID]])>1, "Fail", "Pass" ) -> Pass | W209: =IF( COUNTIF(ValidationTable[[#This Row],[RequiredField_Validation]]:ValidationTable[[#This Row],[Duplicate_Validation]],"Fail")>0, "Fail", "Pass" ) -> Pass | X209: =IF(ValidationTable[[#This Row],[Validation_Result]]="Pass","Yes","No") -> Yes
A210: =RawTable[[#This Row],[Record_ID]] -> 209 | B210: =RawTable[[#This Row],[Payment_Type]] -> Contractor_Fee | C210: =RawTable[[#This Row],[Entity_Type]] -> Contractor | D210: =RawTable[[#This Row],[Country]] -> USA | E210: =RawTable[[#This Row],[Name]] -> Laura Schmidt | F210: =RawTable[[#This Row],[Bank_Account]] -> US-RT-000104890-AC-0000482630 | G210: =RawTable[[#This Row],[Month]] -> Feb-2026 | H210: =RawTable[[#This Row],[Currency]] -> USD | I210: =RawTable[[#This Row],[Net_Amount]] -> 5880.56 | J210: =RawTable[[#This Row],[VAT_Applicable]] -> No | K210: =RawTable[[#This Row],[VAT_Rate]] -> 0 | L210: =RawTable[[#This Row],[VAT_Amount]] -> 0 | M210: =RawTable[[#This Row],[Gross_Amount]] -> 5880.56 | N210: =RawTable[[#This Row],[Exchange_Rate]] -> 0.77018 | O210: =RawTable[[#This Row],[Amount_CHF]] -> 4529.09 | P210: =IF( OR(ValidationTable[[#This Row],[Record_ID]]="",ValidationTable[[#This Row],[Payment_Type]]="",ValidationTable[[#This Row],[Entity_Type]]="", ValidationTable[[#This Row],[Country]]="", ValidationTable[[#This Row],[Name]]="", ValidationTable[[#This Row],[Month]]="", ValidationTable[[#This Row],[Currency]]="" ), "Fail", "Pass" ) -> Pass | Q210: =IF( OR(ValidationTable[[#This Row],[Net_Amount]]<=0, ROUND(ValidationTable[[#This Row],[Net_Amount]]+ValidationTable[[#This Row],[VAT_Amount]],2)<>ROUND(ValidationTable[[#This Row],[Gross_Amount]],2) ), "Fail", "Pass" ) -> Pass | R210: =IF(ValidationTable[[#This Row],[Currency]]="","Fail","Pass") -> Pass | S210: =IF( ValidationTable[[#This Row],[Currency]]="CHF", IF(ValidationTable[[#This Row],[Exchange_Rate]]<>1,"Fail","Pass"), IF(ValidationTable[[#This Row],[Exchange_Rate]]<=0,"Fail","Pass") ) -> Pass | T210: =IF(ValidationTable[[#This Row],[VAT_Applicable]]="Yes", IF( ROUND(ValidationTable[[#This Row],[Net_Amount]]*ValidationTable[[#This Row],[VAT_Rate]],2)<>ROUND(ValidationTable[[#This Row],[VAT_Amount]],2), "Fail", "Pass" ), IF( OR(ValidationTable[[#This Row],[VAT_Rate]]<>0,ValidationTable[[#This Row],[VAT_Amount]]<>0 ), "Fail", "Pass" ) ) -> Pass | U210: =IF(LEN(TRIM(ValidationTable[[#This Row],[Bank_Account]]))=0,"Fail","Pass") -> Pass | V210: =IF( COUNTIF(ValidationTable[Record_ID],ValidationTable[[#This Row],[Record_ID]])>1, "Fail", "Pass" ) -> Pass | W210: =IF( COUNTIF(ValidationTable[[#This Row],[RequiredField_Validation]]:ValidationTable[[#This Row],[Duplicate_Validation]],"Fail")>0, "Fail", "Pass" ) -> Pass | X210: =IF(ValidationTable[[#This Row],[Validation_Result]]="Pass","Yes","No") -> Yes
A211: =RawTable[[#This Row],[Record_ID]] -> 210 | B211: =RawTable[[#This Row],[Payment_Type]] -> Contractor_Fee | C211: =RawTable[[#This Row],[Entity_Type]] -> Contractor | D211: =RawTable[[#This Row],[Country]] -> USA | E211: =RawTable[[#This Row],[Name]] -> Sara Khan | F211: =RawTable[[#This Row],[Bank_Account]] -> US-RT-000050594-AC-0000232798 | G211: =RawTable[[#This Row],[Month]] -> Mar-2026 | H211: =RawTable[[#This Row],[Currency]] -> USD | I211: =RawTable[[#This Row],[Net_Amount]] -> 5367.04 | J211: =RawTable[[#This Row],[VAT_Applicable]] -> No | K211: =RawTable[[#This Row],[VAT_Rate]] -> 0 | L211: =RawTable[[#This Row],[VAT_Amount]] -> 0 | M211: =RawTable[[#This Row],[Gross_Amount]] -> 5367.04 | N211: =RawTable[[#This Row],[Exchange_Rate]] -> 0.77018 | O211: =RawTable[[#This Row],[Amount_CHF]] -> 4133.59 | P211: =IF( OR(ValidationTable[[#This Row],[Record_ID]]="",ValidationTable[[#This Row],[Payment_Type]]="",ValidationTable[[#This Row],[Entity_Type]]="", ValidationTable[[#This Row],[Country]]="", ValidationTable[[#This Row],[Name]]="", ValidationTable[[#This Row],[Month]]="", ValidationTable[[#This Row],[Currency]]="" ), "Fail", "Pass" ) -> Pass | Q211: =IF( OR(ValidationTable[[#This Row],[Net_Amount]]<=0, ROUND(ValidationTable[[#This Row],[Net_Amount]]+ValidationTable[[#This Row],[VAT_Amount]],2)<>ROUND(ValidationTable[[#This Row],[Gross_Amount]],2) ), "Fail", "Pass" ) -> Pass | R211: =IF(ValidationTable[[#This Row],[Currency]]="","Fail","Pass") -> Pass | S211: =IF( ValidationTable[[#This Row],[Currency]]="CHF", IF(ValidationTable[[#This Row],[Exchange_Rate]]<>1,"Fail","Pass"), IF(ValidationTable[[#This Row],[Exchange_Rate]]<=0,"Fail","Pass") ) -> Pass | T211: =IF(ValidationTable[[#This Row],[VAT_Applicable]]="Yes", IF( ROUND(ValidationTable[[#This Row],[Net_Amount]]*ValidationTable[[#This Row],[VAT_Rate]],2)<>ROUND(ValidationTable[[#This Row],[VAT_Amount]],2), "Fail", "Pass" ), IF( OR(ValidationTable[[#This Row],[VAT_Rate]]<>0,ValidationTable[[#This Row],[VAT_Amount]]<>0 ), "Fail", "Pass" ) ) -> Pass | U211: =IF(LEN(TRIM(ValidationTable[[#This Row],[Bank_Account]]))=0,"Fail","Pass") -> Pass | V211: =IF( COUNTIF(ValidationTable[Record_ID],ValidationTable[[#This Row],[Record_ID]])>1, "Fail", "Pass" ) -> Pass | W211: =IF( COUNTIF(ValidationTable[[#This Row],[RequiredField_Validation]]:ValidationTable[[#This Row],[Duplicate_Validation]],"Fail")>0, "Fail", "Pass" ) -> Pass | X211: =IF(ValidationTable[[#This Row],[Validation_Result]]="Pass","Yes","No") -> Yes
A212: =RawTable[[#This Row],[Record_ID]] -> 211 | B212: =RawTable[[#This Row],[Payment_Type]] -> Contractor_Fee | C212: =RawTable[[#This Row],[Entity_Type]] -> Contractor | D212: =RawTable[[#This Row],[Country]] -> Germany | E212: =RawTable[[#This Row],[Name]] -> Omar Taylor | F212: =RawTable[[#This Row],[Bank_Account]] -> DE890000000001167794 | G212: =RawTable[[#This Row],[Month]] -> Jan-2026 | H212: =RawTable[[#This Row],[Currency]] -> EUR | I212: =RawTable[[#This Row],[Net_Amount]] -> 4791.36 | J212: =RawTable[[#This Row],[VAT_Applicable]] -> No | K212: =RawTable[[#This Row],[VAT_Rate]] -> 0 | L212: =RawTable[[#This Row],[VAT_Amount]] -> 0 | M212: =RawTable[[#This Row],[Gross_Amount]] -> 4791.36 | N212: =RawTable[[#This Row],[Exchange_Rate]] -> 0.90888 | O212: =RawTable[[#This Row],[Amount_CHF]] -> 4354.77 | P212: =IF( OR(ValidationTable[[#This Row],[Record_ID]]="",ValidationTable[[#This Row],[Payment_Type]]="",ValidationTable[[#This Row],[Entity_Type]]="", ValidationTable[[#This Row],[Country]]="", ValidationTable[[#This Row],[Name]]="", ValidationTable[[#This Row],[Month]]="", ValidationTable[[#This Row],[Currency]]="" ), "Fail", "Pass" ) -> Pass | Q212: =IF( OR(ValidationTable[[#This Row],[Net_Amount]]<=0, ROUND(ValidationTable[[#This Row],[Net_Amount]]+ValidationTable[[#This Row],[VAT_Amount]],2)<>ROUND(ValidationTable[[#This Row],[Gross_Amount]],2) ), "Fail", "Pass" ) -> Pass | R212: =IF(ValidationTable[[#This Row],[Currency]]="","Fail","Pass") -> Pass | S212: =IF( ValidationTable[[#This Row],[Currency]]="CHF", IF(ValidationTable[[#This Row],[Exchange_Rate]]<>1,"Fail","Pass"), IF(ValidationTable[[#This Row],[Exchange_Rate]]<=0,"Fail","Pass") ) -> Pass | T212: =IF(ValidationTable[[#This Row],[VAT_Applicable]]="Yes", IF( ROUND(ValidationTable[[#This Row],[Net_Amount]]*ValidationTable[[#This Row],[VAT_Rate]],2)<>ROUND(ValidationTable[[#This Row],[VAT_Amount]],2), "Fail", "Pass" ), IF( OR(ValidationTable[[#This Row],[VAT_Rate]]<>0,ValidationTable[[#This Row],[VAT_Amount]]<>0 ), "Fail", "Pass" ) ) -> Pass | U212: =IF(LEN(TRIM(ValidationTable[[#This Row],[Bank_Account]]))=0,"Fail","Pass") -> Pass | V212: =IF( COUNTIF(ValidationTable[Record_ID],ValidationTable[[#This Row],[Record_ID]])>1, "Fail", "Pass" ) -> Pass | W212: =IF( COUNTIF(ValidationTable[[#This Row],[RequiredField_Validation]]:ValidationTable[[#This Row],[Duplicate_Validation]],"Fail")>0, "Fail", "Pass" ) -> Pass | X212: =IF(ValidationTable[[#This Row],[Validation_Result]]="Pass","Yes","No") -> Yes
A213: =RawTable[[#This Row],[Record_ID]] -> 212 | B213: =RawTable[[#This Row],[Payment_Type]] -> Contractor_Fee | C213: =RawTable[[#This Row],[Entity_Type]] -> Contractor | D213: =RawTable[[#This Row],[Country]] -> Switzerland | E213: =RawTable[[#This Row],[Name]] -> John Ali | F213: =RawTable[[#This Row],[Bank_Account]] -> DE890000000000312317 | G213: =RawTable[[#This Row],[Month]] -> Feb-2026 | H213: =RawTable[[#This Row],[Currency]] -> CHF | I213: =RawTable[[#This Row],[Net_Amount]] -> 4991.48 | J213: =RawTable[[#This Row],[VAT_Applicable]] -> No | K213: =RawTable[[#This Row],[VAT_Rate]] -> 0 | L213: =RawTable[[#This Row],[VAT_Amount]] -> 0 | M213: =RawTable[[#This Row],[Gross_Amount]] -> 4991.48 | N213: =RawTable[[#This Row],[Exchange_Rate]] -> 1 | O213: =RawTable[[#This Row],[Amount_CHF]] -> 4991.48 | P213: =IF( OR(ValidationTable[[#This Row],[Record_ID]]="",ValidationTable[[#This Row],[Payment_Type]]="",ValidationTable[[#This Row],[Entity_Type]]="", ValidationTable[[#This Row],[Country]]="", ValidationTable[[#This Row],[Name]]="", ValidationTable[[#This Row],[Month]]="", ValidationTable[[#This Row],[Currency]]="" ), "Fail", "Pass" ) -> Pass | Q213: =IF( OR(ValidationTable[[#This Row],[Net_Amount]]<=0, ROUND(ValidationTable[[#This Row],[Net_Amount]]+ValidationTable[[#This Row],[VAT_Amount]],2)<>ROUND(ValidationTable[[#This Row],[Gross_Amount]],2) ), "Fail", "Pass" ) -> Pass | R213: =IF(ValidationTable[[#This Row],[Currency]]="","Fail","Pass") -> Pass | S213: =IF( ValidationTable[[#This Row],[Currency]]="CHF", IF(ValidationTable[[#This Row],[Exchange_Rate]]<>1,"Fail","Pass"), IF(ValidationTable[[#This Row],[Exchange_Rate]]<=0,"Fail","Pass") ) -> Pass | T213: =IF(ValidationTable[[#This Row],[VAT_Applicable]]="Yes", IF( ROUND(ValidationTable[[#This Row],[Net_Amount]]*ValidationTable[[#This Row],[VAT_Rate]],2)<>ROUND(ValidationTable[[#This Row],[VAT_Amount]],2), "Fail", "Pass" ), IF( OR(ValidationTable[[#This Row],[VAT_Rate]]<>0,ValidationTable[[#This Row],[VAT_Amount]]<>0 ), "Fail", "Pass" ) ) -> Pass | U213: =IF(LEN(TRIM(ValidationTable[[#This Row],[Bank_Account]]))=0,"Fail","Pass") -> Pass | V213: =IF( COUNTIF(ValidationTable[Record_ID],ValidationTable[[#This Row],[Record_ID]])>1, "Fail", "Pass" ) -> Pass | W213: =IF( COUNTIF(ValidationTable[[#This Row],[RequiredField_Validation]]:ValidationTable[[#This Row],[Duplicate_Validation]],"Fail")>0, "Fail", "Pass" ) -> Pass | X213: =IF(ValidationTable[[#This Row],[Validation_Result]]="Pass","Yes","No") -> Yes
... A314: =RawTable[[#This Row],[Record_ID]] -> 313 | B314: =RawTable[[#This Row],[Payment_Type]] -> Vendor_Invoice | C314: =RawTable[[#This Row],[Entity_Type]] -> Vendor | D314: =RawTable[[#This Row],[Country]] -> UAE | E314: =RawTable[[#This Row],[Name]] -> NorthStar Logistics | F314: =RawTable[[#This Row],[Bank_Account]] -> AE-IBAN-05432100 | G314: =RawTable[[#This Row],[Month]] -> Feb-2026 | H314: =RawTable[[#This Row],[Currency]] -> AED | I314: =RawTable[[#This Row],[Net_Amount]] -> 20153.98 | J314: =RawTable[[#This Row],[VAT_Applicable]] -> Yes | K314: =RawTable[[#This Row],[VAT_Rate]] -> 0 | L314: =RawTable[[#This Row],[VAT_Amount]] -> 0 | M314: =RawTable[[#This Row],[Gross_Amount]] -> 20153.98 | N314: =RawTable[[#This Row],[Exchange_Rate]] -> 0.21065 | O314: =RawTable[[#This Row],[Amount_CHF]] -> 4245.44 | P314: =IF( OR(ValidationTable[[#This Row],[Record_ID]]="",ValidationTable[[#This Row],[Payment_Type]]="",ValidationTable[[#This Row],[Entity_Type]]="", ValidationTable[[#This Row],[Country]]="", ValidationTable[[#This Row],[Name]]="", ValidationTable[[#This Row],[Month]]="", ValidationTable[[#This Row],[Currency]]="" ), "Fail", "Pass" ) -> Pass | Q314: =IF( OR(ValidationTable[[#This Row],[Net_Amount]]<=0, ROUND(ValidationTable[[#This Row],[Net_Amount]]+ValidationTable[[#This Row],[VAT_Amount]],2)<>ROUND(ValidationTable[[#This Row],[Gross_Amount]],2) ), "Fail", "Pass" ) -> Pass | R314: =IF(ValidationTable[[#This Row],[Currency]]="","Fail","Pass") -> Pass | S314: =IF( ValidationTable[[#This Row],[Currency]]="CHF", IF(ValidationTable[[#This Row],[Exchange_Rate]]<>1,"Fail","Pass"), IF(ValidationTable[[#This Row],[Exchange_Rate]]<=0,"Fail","Pass") ) -> Pass | T314: =IF(ValidationTable[[#This Row],[VAT_Applicable]]="Yes", IF( ROUND(ValidationTable[[#This Row],[Net_Amount]]*ValidationTable[[#This Row],[VAT_Rate]],2)<>ROUND(ValidationTable[[#This Row],[VAT_Amount]],2), "Fail", "Pass" ), IF( OR(ValidationTable[[#This Row],[VAT_Rate]]<>0,ValidationTable[[#This Row],[VAT_Amount]]<>0 ), "Fail", "Pass" ) ) -> Pass | U314: =IF(LEN(TRIM(ValidationTable[[#This Row],[Bank_Account]]))=0,"Fail","Pass") -> Pass | V314: =IF( COUNTIF(ValidationTable[Record_ID],ValidationTable[[#This Row],[Record_ID]])>1, "Fail", "Pass" ) -> Pass | W314: =IF( COUNTIF(ValidationTable[[#This Row],[RequiredField_Validation]]:ValidationTable[[#This Row],[Duplicate_Validation]],"Fail")>0, "Fail", "Pass" ) -> Pass | X314: =IF(ValidationTable[[#This Row],[Validation_Result]]="Pass","Yes","No") -> Yes
A315: =RawTable[[#This Row],[Record_ID]] -> 314 | C315: =RawTable[[#This Row],[Entity_Type]] -> Vendor | D315: =RawTable[[#This Row],[Country]] -> UAE | E315: =RawTable[[#This Row],[Name]] -> Sunrise Media Agency | F315: =RawTable[[#This Row],[Bank_Account]] -> US-RT-000120932-AC-0000556444 | G315: =RawTable[[#This Row],[Month]] -> Mar-2026 | H315: =RawTable[[#This Row],[Currency]] -> AED | I315: =RawTable[[#This Row],[Net_Amount]] -> 18010.2 | J315: =RawTable[[#This Row],[VAT_Applicable]] -> No | K315: =RawTable[[#This Row],[VAT_Rate]] -> 0 | L315: =RawTable[[#This Row],[VAT_Amount]] -> 0 | M315: =RawTable[[#This Row],[Gross_Amount]] -> 18010.2 | N315: =RawTable[[#This Row],[Exchange_Rate]] -> 0.21065 | O315: =RawTable[[#This Row],[Amount_CHF]] -> 3793.85 | P315: =IF( OR(ValidationTable[[#This Row],[Record_ID]]="",ValidationTable[[#This Row],[Payment_Type]]="",ValidationTable[[#This Row],[Entity_Type]]="", ValidationTable[[#This Row],[Country]]="", ValidationTable[[#This Row],[Name]]="", ValidationTable[[#This Row],[Month]]="", ValidationTable[[#This Row],[Currency]]="" ), "Fail", "Pass" ) -> Fail | Q315: =IF( OR(ValidationTable[[#This Row],[Net_Amount]]<=0, ROUND(ValidationTable[[#This Row],[Net_Amount]]+ValidationTable[[#This Row],[VAT_Amount]],2)<>ROUND(ValidationTable[[#This Row],[Gross_Amount]],2) ), "Fail", "Pass" ) -> Pass | R315: =IF(ValidationTable[[#This Row],[Currency]]="","Fail","Pass") -> Pass | S315: =IF( ValidationTable[[#This Row],[Currency]]="CHF", IF(ValidationTable[[#This Row],[Exchange_Rate]]<>1,"Fail","Pass"), IF(ValidationTable[[#This Row],[Exchange_Rate]]<=0,"Fail","Pass") ) -> Pass | T315: =IF(ValidationTable[[#This Row],[VAT_Applicable]]="Yes", IF( ROUND(ValidationTable[[#This Row],[Net_Amount]]*ValidationTable[[#This Row],[VAT_Rate]],2)<>ROUND(ValidationTable[[#This Row],[VAT_Amount]],2), "Fail", "Pass" ), IF( OR(ValidationTable[[#This Row],[VAT_Rate]]<>0,ValidationTable[[#This Row],[VAT_Amount]]<>0 ), "Fail", "Pass" ) ) -> Pass | U315: =IF(LEN(TRIM(ValidationTable[[#This Row],[Bank_Account]]))=0,"Fail","Pass") -> Pass | V315: =IF( COUNTIF(ValidationTable[Record_ID],ValidationTable[[#This Row],[Record_ID]])>1, "Fail", "Pass" ) -> Pass | W315: =IF( COUNTIF(ValidationTable[[#This Row],[RequiredField_Validation]]:ValidationTable[[#This Row],[Duplicate_Validation]],"Fail")>0, "Fail", "Pass" ) -> Fail | X315: =IF(ValidationTable[[#This Row],[Validation_Result]]="Pass","Yes","No") -> No
A316: =RawTable[[#This Row],[Record_ID]] -> 315 | B316: =RawTable[[#This Row],[Payment_Type]] -> Vendor_Invoice | C316: =RawTable[[#This Row],[Entity_Type]] -> Vendor | D316: =RawTable[[#This Row],[Country]] -> Jordan | E316: =RawTable[[#This Row],[Name]] -> Global Services Ltd | F316: =RawTable[[#This Row],[Bank_Account]] -> JO-IBAN-01160430 | G316: =RawTable[[#This Row],[Month]] -> Jan-2026 | H316: =RawTable[[#This Row],[Currency]] -> JOD | I316: =RawTable[[#This Row],[Net_Amount]] -> 1639.02 | J316: =RawTable[[#This Row],[VAT_Applicable]] -> Yes | K316: =RawTable[[#This Row],[VAT_Rate]] -> 0.16 | L316: =RawTable[[#This Row],[VAT_Amount]] -> 262.2432 | M316: =RawTable[[#This Row],[Gross_Amount]] -> 1901.2632 | N316: =RawTable[[#This Row],[Exchange_Rate]] -> 1.08643 | O316: =RawTable[[#This Row],[Amount_CHF]] -> 2065.59 | P316: =IF( OR(ValidationTable[[#This Row],[Record_ID]]="",ValidationTable[[#This Row],[Payment_Type]]="",ValidationTable[[#This Row],[Entity_Type]]="", ValidationTable[[#This Row],[Country]]="", ValidationTable[[#This Row],[Name]]="", ValidationTable[[#This Row],[Month]]="", ValidationTable[[#This Row],[Currency]]="" ), "Fail", "Pass" ) -> Pass | Q316: =IF( OR(ValidationTable[[#This Row],[Net_Amount]]<=0, ROUND(ValidationTable[[#This Row],[Net_Amount]]+ValidationTable[[#This Row],[VAT_Amount]],2)<>ROUND(ValidationTable[[#This Row],[Gross_Amount]],2) ), "Fail", "Pass" ) -> Pass | R316: =IF(ValidationTable[[#This Row],[Currency]]="","Fail","Pass") -> Pass | S316: =IF( ValidationTable[[#This Row],[Currency]]="CHF", IF(ValidationTable[[#This Row],[Exchange_Rate]]<>1,"Fail","Pass"), IF(ValidationTable[[#This Row],[Exchange_Rate]]<=0,"Fail","Pass") ) -> Pass | T316: =IF(ValidationTable[[#This Row],[VAT_Applicable]]="Yes", IF( ROUND(ValidationTable[[#This Row],[Net_Amount]]*ValidationTable[[#This Row],[VAT_Rate]],2)<>ROUND(ValidationTable[[#This Row],[VAT_Amount]],2), "Fail", "Pass" ), IF( OR(ValidationTable[[#This Row],[VAT_Rate]]<>0,ValidationTable[[#This Row],[VAT_Amount]]<>0 ), "Fail", "Pass" ) ) -> Pass | U316: =IF(LEN(TRIM(ValidationTable[[#This Row],[Bank_Account]]))=0,"Fail","Pass") -> Pass | V316: =IF( COUNTIF(ValidationTable[Record_ID],ValidationTable[[#This Row],[Record_ID]])>1, "Fail", "Pass" ) -> Pass | W316: =IF( COUNTIF(ValidationTable[[#This Row],[RequiredField_Validation]]:ValidationTable[[#This Row],[Duplicate_Validation]],"Fail")>0, "Fail", "Pass" ) -> Pass | X316: =IF(ValidationTable[[#This Row],[Validation_Result]]="Pass","Yes","No") -> Yes
A317: =RawTable[[#This Row],[Record_ID]] -> 316 | B317: =RawTable[[#This Row],[Payment_Type]] -> Vendor_Invoice | C317: =RawTable[[#This Row],[Entity_Type]] -> Vendor | D317: =RawTable[[#This Row],[Country]] -> USA | E317: =RawTable[[#This Row],[Name]] -> Bright Consulting LLC | F317: =RawTable[[#This Row],[Bank_Account]] -> US-RT-000118464-AC-0000545088 | G317: =RawTable[[#This Row],[Month]] -> Jan-2026 | H317: =RawTable[[#This Row],[Currency]] -> USD | I317: =RawTable[[#This Row],[Net_Amount]] -> 6681.79 | J317: =RawTable[[#This Row],[VAT_Applicable]] -> Yes | K317: =RawTable[[#This Row],[VAT_Rate]] -> 0.05 | L317: =RawTable[[#This Row],[VAT_Amount]] -> 334.0895 | M317: =RawTable[[#This Row],[Gross_Amount]] -> 7015.8795 | N317: =RawTable[[#This Row],[Exchange_Rate]] -> 0.77018 | O317: =RawTable[[#This Row],[Amount_CHF]] -> 5403.49 | P317: =IF( OR(ValidationTable[[#This Row],[Record_ID]]="",ValidationTable[[#This Row],[Payment_Type]]="",ValidationTable[[#This Row],[Entity_Type]]="", ValidationTable[[#This Row],[Country]]="", ValidationTable[[#This Row],[Name]]="", ValidationTable[[#This Row],[Month]]="", ValidationTable[[#This Row],[Currency]]="" ), "Fail", "Pass" ) -> Pass | Q317: =IF( OR(ValidationTable[[#This Row],[Net_Amount]]<=0, ROUND(ValidationTable[[#This Row],[Net_Amount]]+ValidationTable[[#This Row],[VAT_Amount]],2)<>ROUND(ValidationTable[[#This Row],[Gross_Amount]],2) ), "Fail", "Pass" ) -> Pass | R317: =IF(ValidationTable[[#This Row],[Currency]]="","Fail","Pass") -> Pass | S317: =IF( ValidationTable[[#This Row],[Currency]]="CHF", IF(ValidationTable[[#This Row],[Exchange_Rate]]<>1,"Fail","Pass"), IF(ValidationTable[[#This Row],[Exchange_Rate]]<=0,"Fail","Pass") ) -> Pass | T317: =IF(ValidationTable[[#This Row],[VAT_Applicable]]="Yes", IF( ROUND(ValidationTable[[#This Row],[Net_Amount]]*ValidationTable[[#This Row],[VAT_Rate]],2)<>ROUND(ValidationTable[[#This Row],[VAT_Amount]],2), "Fail", "Pass" ), IF( OR(ValidationTable[[#This Row],[VAT_Rate]]<>0,ValidationTable[[#This Row],[VAT_Amount]]<>0 ), "Fail", "Pass" ) ) -> Pass | U317: =IF(LEN(TRIM(ValidationTable[[#This Row],[Bank_Account]]))=0,"Fail","Pass") -> Pass | V317: =IF( COUNTIF(ValidationTable[Record_ID],ValidationTable[[#This Row],[Record_ID]])>1, "Fail", "Pass" ) -> Pass | W317: =IF( COUNTIF(ValidationTable[[#This Row],[RequiredField_Validation]]:ValidationTable[[#This Row],[Duplicate_Validation]],"Fail")>0, "Fail", "Pass" ) -> Pass | X317: =IF(ValidationTable[[#This Row],[Validation_Result]]="Pass","Yes","No") -> Yes
A318: =RawTable[[#This Row],[Record_ID]] -> 317 | B318: =RawTable[[#This Row],[Payment_Type]] -> Vendor_Invoice | C318: =RawTable[[#This Row],[Entity_Type]] -> Vendor | D318: =RawTable[[#This Row],[Country]] -> USA | E318: =RawTable[[#This Row],[Name]] -> Impact Partners | F318: =RawTable[[#This Row],[Bank_Account]] -> JO-IBAN-01222155 | G318: =RawTable[[#This Row],[Month]] -> Jan-2026 | H318: =RawTable[[#This Row],[Currency]] -> USD | I318: =RawTable[[#This Row],[Net_Amount]] -> 6746.67 | J318: =RawTable[[#This Row],[VAT_Applicable]] -> Yes | K318: =RawTable[[#This Row],[VAT_Rate]] -> 0.05 | L318: =RawTable[[#This Row],[VAT_Amount]] -> 337.3335 | M318: =RawTable[[#This Row],[Gross_Amount]] -> 7084.0035 | N318: =RawTable[[#This Row],[Exchange_Rate]] -> 0.77018 | O318: =RawTable[[#This Row],[Amount_CHF]] -> 5455.96 | P318: =IF( OR(ValidationTable[[#This Row],[Record_ID]]="",ValidationTable[[#This Row],[Payment_Type]]="",ValidationTable[[#This Row],[Entity_Type]]="", ValidationTable[[#This Row],[Country]]="", ValidationTable[[#This Row],[Name]]="", ValidationTable[[#This Row],[Month]]="", ValidationTable[[#This Row],[Currency]]="" ), "Fail", "Pass" ) -> Pass | Q318: =IF( OR(ValidationTable[[#This Row],[Net_Amount]]<=0, ROUND(ValidationTable[[#This Row],[Net_Amount]]+ValidationTable[[#This Row],[VAT_Amount]],2)<>ROUND(ValidationTable[[#This Row],[Gross_Amount]],2) ), "Fail", "Pass" ) -> Pass | R318: =IF(ValidationTable[[#This Row],[Currency]]="","Fail","Pass") -> Pass | S318: =IF( ValidationTable[[#This Row],[Currency]]="CHF", IF(ValidationTable[[#This Row],[Exchange_Rate]]<>1,"Fail","Pass"), IF(ValidationTable[[#This Row],[Exchange_Rate]]<=0,"Fail","Pass") ) -> Pass | T318: =IF(ValidationTable[[#This Row],[VAT_Applicable]]="Yes", IF( ROUND(ValidationTable[[#This Row],[Net_Amount]]*ValidationTable[[#This Row],[VAT_Rate]],2)<>ROUND(ValidationTable[[#This Row],[VAT_Amount]],2), "Fail", "Pass" ), IF( OR(ValidationTable[[#This Row],[VAT_Rate]]<>0,ValidationTable[[#This Row],[VAT_Amount]]<>0 ), "Fail", "Pass" ) ) -> Pass | U318: =IF(LEN(TRIM(ValidationTable[[#This Row],[Bank_Account]]))=0,"Fail","Pass") -> Pass | V318: =IF( COUNTIF(ValidationTable[Record_ID],ValidationTable[[#This Row],[Record_ID]])>1, "Fail", "Pass" ) -> Pass | W318: =IF( COUNTIF(ValidationTable[[#This Row],[RequiredField_Validation]]:ValidationTable[[#This Row],[Duplicate_Validation]],"Fail")>0, "Fail", "Pass" ) -> Pass | X318: =IF(ValidationTable[[#This Row],[Validation_Result]]="Pass","Yes","No") -> Yes
A319: =RawTable[[#This Row],[Record_ID]] -> 318 | B319: =RawTable[[#This Row],[Payment_Type]] -> Vendor_Invoice | C319: =RawTable[[#This Row],[Entity_Type]] -> Vendor | D319: =RawTable[[#This Row],[Country]] -> Switzerland | E319: =RawTable[[#This Row],[Name]] -> Impact Partners | F319: =RawTable[[#This Row],[Bank_Account]] -> JO-IBAN-01222155 | G319: =RawTable[[#This Row],[Month]] -> Feb-2026 | H319: =RawTable[[#This Row],[Currency]] -> CHF | I319: =RawTable[[#This Row],[Net_Amount]] -> 6264.76 | J319: =RawTable[[#This Row],[VAT_Applicable]] -> Yes | K319: =RawTable[[#This Row],[VAT_Rate]] -> 0.081 | L319: =RawTable[[#This Row],[VAT_Amount]] -> 507.44556 | M319: =RawTable[[#This Row],[Gross_Amount]] -> 6772.2056 | N319: =RawTable[[#This Row],[Exchange_Rate]] -> 1 | O319: =RawTable[[#This Row],[Amount_CHF]] -> 6772.21 | P319: =IF( OR(ValidationTable[[#This Row],[Record_ID]]="",ValidationTable[[#This Row],[Payment_Type]]="",ValidationTable[[#This Row],[Entity_Type]]="", ValidationTable[[#This Row],[Country]]="", ValidationTable[[#This Row],[Name]]="", ValidationTable[[#This Row],[Month]]="", ValidationTable[[#This Row],[Currency]]="" ), "Fail", "Pass" ) -> Pass | Q319: =IF( OR(ValidationTable[[#This Row],[Net_Amount]]<=0, ROUND(ValidationTable[[#This Row],[Net_Amount]]+ValidationTable[[#This Row],[VAT_Amount]],2)<>ROUND(ValidationTable[[#This Row],[Gross_Amount]],2) ), "Fail", "Pass" ) -> Pass | R319: =IF(ValidationTable[[#This Row],[Currency]]="","Fail","Pass") -> Pass | S319: =IF( ValidationTable[[#This Row],[Currency]]="CHF", IF(ValidationTable[[#This Row],[Exchange_Rate]]<>1,"Fail","Pass"), IF(ValidationTable[[#This Row],[Exchange_Rate]]<=0,"Fail","Pass") ) -> Pass | T319: =IF(ValidationTable[[#This Row],[VAT_Applicable]]="Yes", IF( ROUND(ValidationTable[[#This Row],[Net_Amount]]*ValidationTable[[#This Row],[VAT_Rate]],2)<>ROUND(ValidationTable[[#This Row],[VAT_Amount]],2), "Fail", "Pass" ), IF( OR(ValidationTable[[#This Row],[VAT_Rate]]<>0,ValidationTable[[#This Row],[VAT_Amount]]<>0 ), "Fail", "Pass" ) ) -> Pass | U319: =IF(LEN(TRIM(ValidationTable[[#This Row],[Bank_Account]]))=0,"Fail","Pass") -> Pass | V319: =IF( COUNTIF(ValidationTable[Record_ID],ValidationTable[[#This Row],[Record_ID]])>1, "Fail", "Pass" ) -> Pass | W319: =IF( COUNTIF(ValidationTable[[#This Row],[RequiredField_Validation]]:ValidationTable[[#This Row],[Duplicate_Validation]],"Fail")>0, "Fail", "Pass" ) -> Pass | X319: =IF(ValidationTable[[#This Row],[Validation_Result]]="Pass","Yes","No") -> Yes
A320: =RawTable[[#This Row],[Record_ID]] -> 319 | B320: =RawTable[[#This Row],[Payment_Type]] -> Vendor_Invoice | C320: =RawTable[[#This Row],[Entity_Type]] -> Vendor | D320: =RawTable[[#This Row],[Country]] -> Germany | E320: =RawTable[[#This Row],[Name]] -> Global Services Ltd | F320: =RawTable[[#This Row],[Bank_Account]] -> JO-IBAN-01160430 | G320: =RawTable[[#This Row],[Month]] -> Feb-2026 | H320: =RawTable[[#This Row],[Currency]] -> EUR | I320: =RawTable[[#This Row],[Net_Amount]] -> 5409.28 | J320: =RawTable[[#This Row],[VAT_Applicable]] -> Yes | K320: =RawTable[[#This Row],[VAT_Rate]] -> 0.19 | L320: =RawTable[[#This Row],[VAT_Amount]] -> 1027.7632 | M320: =RawTable[[#This Row],[Gross_Amount]] -> 6437.0432 | N320: =RawTable[[#This Row],[Exchange_Rate]] -> 0.90888 | O320: =RawTable[[#This Row],[Amount_CHF]] -> 5850.5 | P320: =IF( OR(ValidationTable[[#This Row],[Record_ID]]="",ValidationTable[[#This Row],[Payment_Type]]="",ValidationTable[[#This Row],[Entity_Type]]="", ValidationTable[[#This Row],[Country]]="", ValidationTable[[#This Row],[Name]]="", ValidationTable[[#This Row],[Month]]="", ValidationTable[[#This Row],[Currency]]="" ), "Fail", "Pass" ) -> Pass | Q320: =IF( OR(ValidationTable[[#This Row],[Net_Amount]]<=0, ROUND(ValidationTable[[#This Row],[Net_Amount]]+ValidationTable[[#This Row],[VAT_Amount]],2)<>ROUND(ValidationTable[[#This Row],[Gross_Amount]],2) ), "Fail", "Pass" ) -> Pass | R320: =IF(ValidationTable[[#This Row],[Currency]]="","Fail","Pass") -> Pass | S320: =IF( ValidationTable[[#This Row],[Currency]]="CHF", IF(ValidationTable[[#This Row],[Exchange_Rate]]<>1,"Fail","Pass"), IF(ValidationTable[[#This Row],[Exchange_Rate]]<=0,"Fail","Pass") ) -> Pass | T320: =IF(ValidationTable[[#This Row],[VAT_Applicable]]="Yes", IF( ROUND(ValidationTable[[#This Row],[Net_Amount]]*ValidationTable[[#This Row],[VAT_Rate]],2)<>ROUND(ValidationTable[[#This Row],[VAT_Amount]],2), "Fail", "Pass" ), IF( OR(ValidationTable[[#This Row],[VAT_Rate]]<>0,ValidationTable[[#This Row],[VAT_Amount]]<>0 ), "Fail", "Pass" ) ) -> Pass | U320: =IF(LEN(TRIM(ValidationTable[[#This Row],[Bank_Account]]))=0,"Fail","Pass") -> Pass | V320: =IF( COUNTIF(ValidationTable[Record_ID],ValidationTable[[#This Row],[Record_ID]])>1, "Fail", "Pass" ) -> Pass | W320: =IF( COUNTIF(ValidationTable[[#This Row],[RequiredField_Validation]]:ValidationTable[[#This Row],[Duplicate_Validation]],"Fail")>0, "Fail", "Pass" ) -> Pass | X320: =IF(ValidationTable[[#This Row],[Validation_Result]]="Pass","Yes","No") -> Yes
A321: =RawTable[[#This Row],[Record_ID]] -> 320 | B321: =RawTable[[#This Row],[Payment_Type]] -> Vendor_Invoice | C321: =RawTable[[#This Row],[Entity_Type]] -> Vendor | D321: =RawTable[[#This Row],[Country]] -> Jordan | E321: =RawTable[[#This Row],[Name]] -> Tech Solutions GmbH | F321: =RawTable[[#This Row],[Bank_Account]] -> JO-IBAN-01197465 | G321: =RawTable[[#This Row],[Month]] -> Feb-2026 | H321: =RawTable[[#This Row],[Currency]] -> JOD | I321: =RawTable[[#This Row],[Net_Amount]] -> 1824.82 | J321: =RawTable[[#This Row],[VAT_Applicable]] -> Yes | K321: =RawTable[[#This Row],[VAT_Rate]] -> 0.16 | L321: =RawTable[[#This Row],[VAT_Amount]] -> 291.9712 | M321: =RawTable[[#This Row],[Gross_Amount]] -> 2116.7912 | N321: =RawTable[[#This Row],[Exchange_Rate]] -> 1.08643 | O321: =RawTable[[#This Row],[Amount_CHF]] -> 2299.75 | P321: =IF( OR(ValidationTable[[#This Row],[Record_ID]]="",ValidationTable[[#This Row],[Payment_Type]]="",ValidationTable[[#This Row],[Entity_Type]]="", ValidationTable[[#This Row],[Country]]="", ValidationTable[[#This Row],[Name]]="", ValidationTable[[#This Row],[Month]]="", ValidationTable[[#This Row],[Currency]]="" ), "Fail", "Pass" ) -> Pass | Q321: =IF( OR(ValidationTable[[#This Row],[Net_Amount]]<=0, ROUND(ValidationTable[[#This Row],[Net_Amount]]+ValidationTable[[#This Row],[VAT_Amount]],2)<>ROUND(ValidationTable[[#This Row],[Gross_Amount]],2) ), "Fail", "Pass" ) -> Pass | R321: =IF(ValidationTable[[#This Row],[Currency]]="","Fail","Pass") -> Pass | S321: =IF( ValidationTable[[#This Row],[Currency]]="CHF", IF(ValidationTable[[#This Row],[Exchange_Rate]]<>1,"Fail","Pass"), IF(ValidationTable[[#This Row],[Exchange_Rate]]<=0,"Fail","Pass") ) -> Pass | T321: =IF(ValidationTable[[#This Row],[VAT_Applicable]]="Yes", IF( ROUND(ValidationTable[[#This Row],[Net_Amount]]*ValidationTable[[#This Row],[VAT_Rate]],2)<>ROUND(ValidationTable[[#This Row],[VAT_Amount]],2), "Fail", "Pass" ), IF( OR(ValidationTable[[#This Row],[VAT_Rate]]<>0,ValidationTable[[#This Row],[VAT_Amount]]<>0 ), "Fail", "Pass" ) ) -> Pass | U321: =IF(LEN(TRIM(ValidationTable[[#This Row],[Bank_Account]]))=0,"Fail","Pass") -> Pass | V321: =IF( COUNTIF(ValidationTable[Record_ID],ValidationTable[[#This Row],[Record_ID]])>1, "Fail", "Pass" ) -> Pass | W321: =IF( COUNTIF(ValidationTable[[#This Row],[RequiredField_Validation]]:ValidationTable[[#This Row],[Duplicate_Validation]],"Fail")>0, "Fail", "Pass" ) -> Pass | X321: =IF(ValidationTable[[#This Row],[Validation_Result]]="Pass","Yes","No") -> Yes
A322: =RawTable[[#This Row],[Record_ID]] -> 321 | B322: =RawTable[[#This Row],[Payment_Type]] -> Grant_Disbursement | C322: =RawTable[[#This Row],[Entity_Type]] -> Sub-Grantee | D322: =RawTable[[#This Row],[Country]] -> Switzerland | E322: =RawTable[[#This Row],[Name]] -> Safe Spaces NGO | F322: =RawTable[[#This Row],[Bank_Account]] -> CH930000000002492680 | G322: =RawTable[[#This Row],[Month]] -> Jan-2026 | H322: =RawTable[[#This Row],[Currency]] -> CHF | I322: =RawTable[[#This Row],[Net_Amount]] -> 54496 | J322: =RawTable[[#This Row],[VAT_Applicable]] -> No | K322: =RawTable[[#This Row],[VAT_Rate]] -> 0 | L322: =RawTable[[#This Row],[VAT_Amount]] -> 0 | M322: =RawTable[[#This Row],[Gross_Amount]] -> 54496 | N322: =RawTable[[#This Row],[Exchange_Rate]] -> 1 | O322: =RawTable[[#This Row],[Amount_CHF]] -> 54496 | P322: =IF( OR(ValidationTable[[#This Row],[Record_ID]]="",ValidationTable[[#This Row],[Payment_Type]]="",ValidationTable[[#This Row],[Entity_Type]]="", ValidationTable[[#This Row],[Country]]="", ValidationTable[[#This Row],[Name]]="", ValidationTable[[#This Row],[Month]]="", ValidationTable[[#This Row],[Currency]]="" ), "Fail", "Pass" ) -> Pass | Q322: =IF( OR(ValidationTable[[#This Row],[Net_Amount]]<=0, ROUND(ValidationTable[[#This Row],[Net_Amount]]+ValidationTable[[#This Row],[VAT_Amount]],2)<>ROUND(ValidationTable[[#This Row],[Gross_Amount]],2) ), "Fail", "Pass" ) -> Pass | R322: =IF(ValidationTable[[#This Row],[Currency]]="","Fail","Pass") -> Pass | S322: =IF( ValidationTable[[#This Row],[Currency]]="CHF", IF(ValidationTable[[#This Row],[Exchange_Rate]]<>1,"Fail","Pass"), IF(ValidationTable[[#This Row],[Exchange_Rate]]<=0,"Fail","Pass") ) -> Pass | T322: =IF(ValidationTable[[#This Row],[VAT_Applicable]]="Yes", IF( ROUND(ValidationTable[[#This Row],[Net_Amount]]*ValidationTable[[#This Row],[VAT_Rate]],2)<>ROUND(ValidationTable[[#This Row],[VAT_Amount]],2), "Fail", "Pass" ), IF( OR(ValidationTable[[#This Row],[VAT_Rate]]<>0,ValidationTable[[#This Row],[VAT_Amount]]<>0 ), "Fail", "Pass" ) ) -> Pass | U322: =IF(LEN(TRIM(ValidationTable[[#This Row],[Bank_Account]]))=0,"Fail","Pass") -> Pass | V322: =IF( COUNTIF(ValidationTable[Record_ID],ValidationTable[[#This Row],[Record_ID]])>1, "Fail", "Pass" ) -> Pass | W322: =IF( COUNTIF(ValidationTable[[#This Row],[RequiredField_Validation]]:ValidationTable[[#This Row],[Duplicate_Validation]],"Fail")>0, "Fail", "Pass" ) -> Pass | X322: =IF(ValidationTable[[#This Row],[Validation_Result]]="Pass","Yes","No") -> Yes
A323: =RawTable[[#This Row],[Record_ID]] -> 322 | B323: =RawTable[[#This Row],[Payment_Type]] -> Grant_Disbursement | C323: =RawTable[[#This Row],[Entity_Type]] -> Sub-Grantee | D323: =RawTable[[#This Row],[Country]] -> USA | E323: =RawTable[[#This Row],[Name]] -> Health Access Initiative | F323: =RawTable[[#This Row],[Bank_Account]] -> US-RT-000125868-AC-0000579156 | G323: =RawTable[[#This Row],[Month]] -> Jan-2026 | H323: =RawTable[[#This Row],[Currency]] -> USD | I323: =RawTable[[#This Row],[Net_Amount]] -> 61275.2 | J323: =RawTable[[#This Row],[VAT_Applicable]] -> No | K323: =RawTable[[#This Row],[VAT_Rate]] -> 0 | L323: =RawTable[[#This Row],[VAT_Amount]] -> 0 | M323: =RawTable[[#This Row],[Gross_Amount]] -> 61275.2 | N323: =RawTable[[#This Row],[Exchange_Rate]] -> 0.77018 | O323: =RawTable[[#This Row],[Amount_CHF]] -> 47192.93 | P323: =IF( OR(ValidationTable[[#This Row],[Record_ID]]="",ValidationTable[[#This Row],[Payment_Type]]="",ValidationTable[[#This Row],[Entity_Type]]="", ValidationTable[[#This Row],[Country]]="", ValidationTable[[#This Row],[Name]]="", ValidationTable[[#This Row],[Month]]="", ValidationTable[[#This Row],[Currency]]="" ), "Fail", "Pass" ) -> Pass | Q323: =IF( OR(ValidationTable[[#This Row],[Net_Amount]]<=0, ROUND(ValidationTable[[#This Row],[Net_Amount]]+ValidationTable[[#This Row],[VAT_Amount]],2)<>ROUND(ValidationTable[[#This Row],[Gross_Amount]],2) ), "Fail", "Pass" ) -> Pass | R323: =IF(ValidationTable[[#This Row],[Currency]]="","Fail","Pass") -> Pass | S323: =IF( ValidationTable[[#This Row],[Currency]]="CHF", IF(ValidationTable[[#This Row],[Exchange_Rate]]<>1,"Fail","Pass"), IF(ValidationTable[[#This Row],[Exchange_Rate]]<=0,"Fail","Pass") ) -> Pass | T323: =IF(ValidationTable[[#This Row],[VAT_Applicable]]="Yes", IF( ROUND(ValidationTable[[#This Row],[Net_Amount]]*ValidationTable[[#This Row],[VAT_Rate]],2)<>ROUND(ValidationTable[[#This Row],[VAT_Amount]],2), "Fail", "Pass" ), IF( OR(ValidationTable[[#This Row],[VAT_Rate]]<>0,ValidationTable[[#This Row],[VAT_Amount]]<>0 ), "Fail", "Pass" ) ) -> Pass | U323: =IF(LEN(TRIM(ValidationTable[[#This Row],[Bank_Account]]))=0,"Fail","Pass") -> Pass | V323: =IF( COUNTIF(ValidationTable[Record_ID],ValidationTable[[#This Row],[Record_ID]])>1, "Fail", "Pass" ) -> Pass | W323: =IF( COUNTIF(ValidationTable[[#This Row],[RequiredField_Validation]]:ValidationTable[[#This Row],[Duplicate_Validation]],"Fail")>0, "Fail", "Pass" ) -> Pass | X323: =IF(ValidationTable[[#This Row],[Validation_Result]]="Pass","Yes","No") -> Yes
A324: =RawTable[[#This Row],[Record_ID]] -> 323 | B324: =RawTable[[#This Row],[Payment_Type]] -> Grant_Disbursement | C324: =RawTable[[#This Row],[Entity_Type]] -> Sub-Grantee | D324: =RawTable[[#This Row],[Country]] -> Germany | E324: =RawTable[[#This Row],[Name]] -> Inclusive Futures Org | F324: =RawTable[[#This Row],[Bank_Account]] -> DE890000000001398637 | G324: =RawTable[[#This Row],[Month]] -> Jan-2026 | H324: =RawTable[[#This Row],[Currency]] -> EUR | I324: =RawTable[[#This Row],[Net_Amount]] -> 51427.2 | J324: =RawTable[[#This Row],[VAT_Applicable]] -> No | K324: =RawTable[[#This Row],[VAT_Rate]] -> 0 | L324: =RawTable[[#This Row],[VAT_Amount]] -> 0 | M324: =RawTable[[#This Row],[Gross_Amount]] -> 51427.2 | N324: =RawTable[[#This Row],[Exchange_Rate]] -> 0.90888 | O324: =RawTable[[#This Row],[Amount_CHF]] -> 46741.15 | P324: =IF( OR(ValidationTable[[#This Row],[Record_ID]]="",ValidationTable[[#This Row],[Payment_Type]]="",ValidationTable[[#This Row],[Entity_Type]]="", ValidationTable[[#This Row],[Country]]="", ValidationTable[[#This Row],[Name]]="", ValidationTable[[#This Row],[Month]]="", ValidationTable[[#This Row],[Currency]]="" ), "Fail", "Pass" ) -> Pass | Q324: =IF( OR(ValidationTable[[#This Row],[Net_Amount]]<=0, ROUND(ValidationTable[[#This Row],[Net_Amount]]+ValidationTable[[#This Row],[VAT_Amount]],2)<>ROUND(ValidationTable[[#This Row],[Gross_Amount]],2) ), "Fail", "Pass" ) -> Pass | R324: =IF(ValidationTable[[#This Row],[Currency]]="","Fail","Pass") -> Pass | S324: =IF( ValidationTable[[#This Row],[Currency]]="CHF", IF(ValidationTable[[#This Row],[Exchange_Rate]]<>1,"Fail","Pass"), IF(ValidationTable[[#This Row],[Exchange_Rate]]<=0,"Fail","Pass") ) -> Pass | T324: =IF(ValidationTable[[#This Row],[VAT_Applicable]]="Yes", IF( ROUND(ValidationTable[[#This Row],[Net_Amount]]*ValidationTable[[#This Row],[VAT_Rate]],2)<>ROUND(ValidationTable[[#This Row],[VAT_Amount]],2), "Fail", "Pass" ), IF( OR(ValidationTable[[#This Row],[VAT_Rate]]<>0,ValidationTable[[#This Row],[VAT_Amount]]<>0 ), "Fail", "Pass" ) ) -> Pass | U324: =IF(LEN(TRIM(ValidationTable[[#This Row],[Bank_Account]]))=0,"Fail","Pass") -> Pass | V324: =IF( COUNTIF(ValidationTable[Record_ID],ValidationTable[[#This Row],[Record_ID]])>1, "Fail", "Pass" ) -> Pass | W324: =IF( COUNTIF(ValidationTable[[#This Row],[RequiredField_Validation]]:ValidationTable[[#This Row],[Duplicate_Validation]],"Fail")>0, "Fail", "Pass" ) -> Pass | X324: =IF(ValidationTable[[#This Row],[Validation_Result]]="Pass","Yes","No") -> Yes
A325: =RawTable[[#This Row],[Record_ID]] -> 324 | B325: =RawTable[[#This Row],[Payment_Type]] -> Grant_Disbursement | C325: =RawTable[[#This Row],[Entity_Type]] -> Sub-Grantee | D325: =RawTable[[#This Row],[Country]] -> Switzerland | E325: =RawTable[[#This Row],[Name]] -> Community Support Association | F325: =RawTable[[#This Row],[Bank_Account]] -> CH930000000002566720 | G325: =RawTable[[#This Row],[Month]] -> Mar-2026 | H325: =RawTable[[#This Row],[Currency]] -> CHF | I325: =RawTable[[#This Row],[Net_Amount]] -> 51651.6 | J325: =RawTable[[#This Row],[VAT_Applicable]] -> No | K325: =RawTable[[#This Row],[VAT_Rate]] -> 0 | L325: =RawTable[[#This Row],[VAT_Amount]] -> 0 | M325: =RawTable[[#This Row],[Gross_Amount]] -> 51651.6 | N325: =RawTable[[#This Row],[Exchange_Rate]] -> 1 | O325: =RawTable[[#This Row],[Amount_CHF]] -> 51651.6 | P325: =IF( OR(ValidationTable[[#This Row],[Record_ID]]="",ValidationTable[[#This Row],[Payment_Type]]="",ValidationTable[[#This Row],[Entity_Type]]="", ValidationTable[[#This Row],[Country]]="", ValidationTable[[#This Row],[Name]]="", ValidationTable[[#This Row],[Month]]="", ValidationTable[[#This Row],[Currency]]="" ), "Fail", "Pass" ) -> Pass | Q325: =IF( OR(ValidationTable[[#This Row],[Net_Amount]]<=0, ROUND(ValidationTable[[#This Row],[Net_Amount]]+ValidationTable[[#This Row],[VAT_Amount]],2)<>ROUND(ValidationTable[[#This Row],[Gross_Amount]],2) ), "Fail", "Pass" ) -> Pass | R325: =IF(ValidationTable[[#This Row],[Currency]]="","Fail","Pass") -> Pass | S325: =IF( ValidationTable[[#This Row],[Currency]]="CHF", IF(ValidationTable[[#This Row],[Exchange_Rate]]<>1,"Fail","Pass"), IF(ValidationTable[[#This Row],[Exchange_Rate]]<=0,"Fail","Pass") ) -> Pass | T325: =IF(ValidationTable[[#This Row],[VAT_Applicable]]="Yes", IF( ROUND(ValidationTable[[#This Row],[Net_Amount]]*ValidationTable[[#This Row],[VAT_Rate]],2)<>ROUND(ValidationTable[[#This Row],[VAT_Amount]],2), "Fail", "Pass" ), IF( OR(ValidationTable[[#This Row],[VAT_Rate]]<>0,ValidationTable[[#This Row],[VAT_Amount]]<>0 ), "Fail", "Pass" ) ) -> Pass | U325: =IF(LEN(TRIM(ValidationTable[[#This Row],[Bank_Account]]))=0,"Fail","Pass") -> Pass | V325: =IF( COUNTIF(ValidationTable[Record_ID],ValidationTable[[#This Row],[Record_ID]])>1, "Fail", "Pass" ) -> Pass | W325: =IF( COUNTIF(ValidationTable[[#This Row],[RequiredField_Validation]]:ValidationTable[[#This Row],[Duplicate_Validation]],"Fail")>0, "Fail", "Pass" ) -> Pass | X325: =IF(ValidationTable[[#This Row],[Validation_Result]]="Pass","Yes","No") -> Yes
A326: =RawTable[[#This Row],[Record_ID]] -> 325 | B326: =RawTable[[#This Row],[Payment_Type]] -> Grant_Disbursement | C326: =RawTable[[#This Row],[Entity_Type]] -> Sub-Grantee | D326: =RawTable[[#This Row],[Country]] -> Jordan | E326: =RawTable[[#This Row],[Name]] -> Inclusive Futures Org | F326: =RawTable[[#This Row],[Bank_Account]] -> DE890000000001398637 | G326: =RawTable[[#This Row],[Month]] -> Mar-2026 | H326: =RawTable[[#This Row],[Currency]] -> JOD | I326: =RawTable[[#This Row],[Net_Amount]] -> 15428.16 | J326: =RawTable[[#This Row],[VAT_Applicable]] -> No | K326: =RawTable[[#This Row],[VAT_Rate]] -> 0 | L326: =RawTable[[#This Row],[VAT_Amount]] -> 0 | M326: =RawTable[[#This Row],[Gross_Amount]] -> 15428.16 | N326: =RawTable[[#This Row],[Exchange_Rate]] -> 1.08643 | O326: =RawTable[[#This Row],[Amount_CHF]] -> 16761.62 | P326: =IF( OR(ValidationTable[[#This Row],[Record_ID]]="",ValidationTable[[#This Row],[Payment_Type]]="",ValidationTable[[#This Row],[Entity_Type]]="", ValidationTable[[#This Row],[Country]]="", ValidationTable[[#This Row],[Name]]="", ValidationTable[[#This Row],[Month]]="", ValidationTable[[#This Row],[Currency]]="" ), "Fail", "Pass" ) -> Pass | Q326: =IF( OR(ValidationTable[[#This Row],[Net_Amount]]<=0, ROUND(ValidationTable[[#This Row],[Net_Amount]]+ValidationTable[[#This Row],[VAT_Amount]],2)<>ROUND(ValidationTable[[#This Row],[Gross_Amount]],2) ), "Fail", "Pass" ) -> Pass | R326: =IF(ValidationTable[[#This Row],[Currency]]="","Fail","Pass") -> Pass | S326: =IF( ValidationTable[[#This Row],[Currency]]="CHF", IF(ValidationTable[[#This Row],[Exchange_Rate]]<>1,"Fail","Pass"), IF(ValidationTable[[#This Row],[Exchange_Rate]]<=0,"Fail","Pass") ) -> Pass | T326: =IF(ValidationTable[[#This Row],[VAT_Applicable]]="Yes", IF( ROUND(ValidationTable[[#This Row],[Net_Amount]]*ValidationTable[[#This Row],[VAT_Rate]],2)<>ROUND(ValidationTable[[#This Row],[VAT_Amount]],2), "Fail", "Pass" ), IF( OR(ValidationTable[[#This Row],[VAT_Rate]]<>0,ValidationTable[[#This Row],[VAT_Amount]]<>0 ), "Fail", "Pass" ) ) -> Pass | U326: =IF(LEN(TRIM(ValidationTable[[#This Row],[Bank_Account]]))=0,"Fail","Pass") -> Pass | V326: =IF( COUNTIF(ValidationTable[Record_ID],ValidationTable[[#This Row],[Record_ID]])>1, "Fail", "Pass" ) -> Pass | W326: =IF( COUNTIF(ValidationTable[[#This Row],[RequiredField_Validation]]:ValidationTable[[#This Row],[Duplicate_Validation]],"Fail")>0, "Fail", "Pass" ) -> Pass | X326: =IF(ValidationTable[[#This Row],[Validation_Result]]="Pass","Yes","No") -> Yes
A327: =RawTable[[#This Row],[Record_ID]] -> 326 | B327: =RawTable[[#This Row],[Payment_Type]] -> Grant_Disbursement | C327: =RawTable[[#This Row],[Entity_Type]] -> Sub-Grantee | D327: =RawTable[[#This Row],[Country]] -> Jordan | E327: =RawTable[[#This Row],[Name]] -> Regional Advocacy Network | F327: =RawTable[[#This Row],[Bank_Account]] -> JO-IBAN-01296225 | G327: =RawTable[[#This Row],[Month]] -> Jan-2026 | H327: =RawTable[[#This Row],[Currency]] -> JOD | I327: =RawTable[[#This Row],[Net_Amount]] -> 14368.32 | J327: =RawTable[[#This Row],[VAT_Applicable]] -> No | K327: =RawTable[[#This Row],[VAT_Rate]] -> 0 | L327: =RawTable[[#This Row],[VAT_Amount]] -> 0 | M327: =RawTable[[#This Row],[Gross_Amount]] -> 14368.32 | N327: =RawTable[[#This Row],[Exchange_Rate]] -> 1.08643 | O327: =RawTable[[#This Row],[Amount_CHF]] -> 15610.17 | P327: =IF( OR(ValidationTable[[#This Row],[Record_ID]]="",ValidationTable[[#This Row],[Payment_Type]]="",ValidationTable[[#This Row],[Entity_Type]]="", ValidationTable[[#This Row],[Country]]="", ValidationTable[[#This Row],[Name]]="", ValidationTable[[#This Row],[Month]]="", ValidationTable[[#This Row],[Currency]]="" ), "Fail", "Pass" ) -> Pass | Q327: =IF( OR(ValidationTable[[#This Row],[Net_Amount]]<=0, ROUND(ValidationTable[[#This Row],[Net_Amount]]+ValidationTable[[#This Row],[VAT_Amount]],2)<>ROUND(ValidationTable[[#This Row],[Gross_Amount]],2) ), "Fail", "Pass" ) -> Pass | R327: =IF(ValidationTable[[#This Row],[Currency]]="","Fail","Pass") -> Pass | S327: =IF( ValidationTable[[#This Row],[Currency]]="CHF", IF(ValidationTable[[#This Row],[Exchange_Rate]]<>1,"Fail","Pass"), IF(ValidationTable[[#This Row],[Exchange_Rate]]<=0,"Fail","Pass") ) -> Pass | T327: =IF(ValidationTable[[#This Row],[VAT_Applicable]]="Yes", IF( ROUND(ValidationTable[[#This Row],[Net_Amount]]*ValidationTable[[#This Row],[VAT_Rate]],2)<>ROUND(ValidationTable[[#This Row],[VAT_Amount]],2), "Fail", "Pass" ), IF( OR(ValidationTable[[#This Row],[VAT_Rate]]<>0,ValidationTable[[#This Row],[VAT_Amount]]<>0 ), "Fail", "Pass" ) ) -> Pass | U327: =IF(LEN(TRIM(ValidationTable[[#This Row],[Bank_Account]]))=0,"Fail","Pass") -> Pass | V327: =IF( COUNTIF(ValidationTable[Record_ID],ValidationTable[[#This Row],[Record_ID]])>1, "Fail", "Pass" ) -> Pass | W327: =IF( COUNTIF(ValidationTable[[#This Row],[RequiredField_Validation]]:ValidationTable[[#This Row],[Duplicate_Validation]],"Fail")>0, "Fail", "Pass" ) -> Pass | X327: =IF(ValidationTable[[#This Row],[Validation_Result]]="Pass","Yes","No") -> Yes
... A350: =RawTable[[#This Row],[Record_ID]] -> 349 | B350: =RawTable[[#This Row],[Payment_Type]] -> Grant_Disbursement | C350: =RawTable[[#This Row],[Entity_Type]] -> Sub-Grantee | D350: =RawTable[[#This Row],[Country]] -> Switzerland | E350: =RawTable[[#This Row],[Name]] -> Regional Advocacy Network | F350: =RawTable[[#This Row],[Bank_Account]] -> JO-IBAN-01296225 | G350: =RawTable[[#This Row],[Month]] -> Mar-2026 | H350: =RawTable[[#This Row],[Currency]] -> CHF | I350: =RawTable[[#This Row],[Net_Amount]] -> 51885.6 | J350: =RawTable[[#This Row],[VAT_Applicable]] -> No | K350: =RawTable[[#This Row],[VAT_Rate]] -> 0 | L350: =RawTable[[#This Row],[VAT_Amount]] -> 0 | M350: =RawTable[[#This Row],[Gross_Amount]] -> 51885.6 | N350: =RawTable[[#This Row],[Exchange_Rate]] -> 1 | O350: =RawTable[[#This Row],[Amount_CHF]] -> 51885.6 | P350: =IF( OR(ValidationTable[[#This Row],[Record_ID]]="",ValidationTable[[#This Row],[Payment_Type]]="",ValidationTable[[#This Row],[Entity_Type]]="", ValidationTable[[#This Row],[Country]]="", ValidationTable[[#This Row],[Name]]="", ValidationTable[[#This Row],[Month]]="", ValidationTable[[#This Row],[Currency]]="" ), "Fail", "Pass" ) -> Pass | Q350: =IF( OR(ValidationTable[[#This Row],[Net_Amount]]<=0, ROUND(ValidationTable[[#This Row],[Net_Amount]]+ValidationTable[[#This Row],[VAT_Amount]],2)<>ROUND(ValidationTable[[#This Row],[Gross_Amount]],2) ), "Fail", "Pass" ) -> Pass | R350: =IF(ValidationTable[[#This Row],[Currency]]="","Fail","Pass") -> Pass | S350: =IF( ValidationTable[[#This Row],[Currency]]="CHF", IF(ValidationTable[[#This Row],[Exchange_Rate]]<>1,"Fail","Pass"), IF(ValidationTable[[#This Row],[Exchange_Rate]]<=0,"Fail","Pass") ) -> Pass | T350: =IF(ValidationTable[[#This Row],[VAT_Applicable]]="Yes", IF( ROUND(ValidationTable[[#This Row],[Net_Amount]]*ValidationTable[[#This Row],[VAT_Rate]],2)<>ROUND(ValidationTable[[#This Row],[VAT_Amount]],2), "Fail", "Pass" ), IF( OR(ValidationTable[[#This Row],[VAT_Rate]]<>0,ValidationTable[[#This Row],[VAT_Amount]]<>0 ), "Fail", "Pass" ) ) -> Pass | U350: =IF(LEN(TRIM(ValidationTable[[#This Row],[Bank_Account]]))=0,"Fail","Pass") -> Pass | V350: =IF( COUNTIF(ValidationTable[Record_ID],ValidationTable[[#This Row],[Record_ID]])>1, "Fail", "Pass" ) -> Pass | W350: =IF( COUNTIF(ValidationTable[[#This Row],[RequiredField_Validation]]:ValidationTable[[#This Row],[Duplicate_Validation]],"Fail")>0, "Fail", "Pass" ) -> Pass | X350: =IF(ValidationTable[[#This Row],[Validation_Result]]="Pass","Yes","No") -> Yes
A351: =RawTable[[#This Row],[Record_ID]] -> 350 | B351: =RawTable[[#This Row],[Payment_Type]] -> Grant_Disbursement | C351: =RawTable[[#This Row],[Entity_Type]] -> Sub-Grantee | D351: =RawTable[[#This Row],[Country]] -> Jordan | E351: =RawTable[[#This Row],[Name]] -> Youth Empowerment Center | F351: =RawTable[[#This Row],[Bank_Account]] -> DE890000000001452953 | H351: =RawTable[[#This Row],[Currency]] -> JOD | I351: =RawTable[[#This Row],[Net_Amount]] -> 15804 | J351: =RawTable[[#This Row],[VAT_Applicable]] -> No | K351: =RawTable[[#This Row],[VAT_Rate]] -> 0 | L351: =RawTable[[#This Row],[VAT_Amount]] -> 0 | M351: =RawTable[[#This Row],[Gross_Amount]] -> 15804 | N351: =RawTable[[#This Row],[Exchange_Rate]] -> 1.08643 | O351: =RawTable[[#This Row],[Amount_CHF]] -> 17169.94 | P351: =IF( OR(ValidationTable[[#This Row],[Record_ID]]="",ValidationTable[[#This Row],[Payment_Type]]="",ValidationTable[[#This Row],[Entity_Type]]="", ValidationTable[[#This Row],[Country]]="", ValidationTable[[#This Row],[Name]]="", ValidationTable[[#This Row],[Month]]="", ValidationTable[[#This Row],[Currency]]="" ), "Fail", "Pass" ) -> Fail | Q351: =IF( OR(ValidationTable[[#This Row],[Net_Amount]]<=0, ROUND(ValidationTable[[#This Row],[Net_Amount]]+ValidationTable[[#This Row],[VAT_Amount]],2)<>ROUND(ValidationTable[[#This Row],[Gross_Amount]],2) ), "Fail", "Pass" ) -> Pass | R351: =IF(ValidationTable[[#This Row],[Currency]]="","Fail","Pass") -> Pass | S351: =IF( ValidationTable[[#This Row],[Currency]]="CHF", IF(ValidationTable[[#This Row],[Exchange_Rate]]<>1,"Fail","Pass"), IF(ValidationTable[[#This Row],[Exchange_Rate]]<=0,"Fail","Pass") ) -> Pass | T351: =IF(ValidationTable[[#This Row],[VAT_Applicable]]="Yes", IF( ROUND(ValidationTable[[#This Row],[Net_Amount]]*ValidationTable[[#This Row],[VAT_Rate]],2)<>ROUND(ValidationTable[[#This Row],[VAT_Amount]],2), "Fail", "Pass" ), IF( OR(ValidationTable[[#This Row],[VAT_Rate]]<>0,ValidationTable[[#This Row],[VAT_Amount]]<>0 ), "Fail", "Pass" ) ) -> Pass | U351: =IF(LEN(TRIM(ValidationTable[[#This Row],[Bank_Account]]))=0,"Fail","Pass") -> Pass | V351: =IF( COUNTIF(ValidationTable[Record_ID],ValidationTable[[#This Row],[Record_ID]])>1, "Fail", "Pass" ) -> Pass | W351: =IF( COUNTIF(ValidationTable[[#This Row],[RequiredField_Validation]]:ValidationTable[[#This Row],[Duplicate_Validation]],"Fail")>0, "Fail", "Pass" ) -> Fail | X351: =IF(ValidationTable[[#This Row],[Validation_Result]]="Pass","Yes","No") -> No

Sheet 01_Raw_Input
A1: Record_ID | B1: Month | C1: Entity_Type | D1: Payment_Type | E1: Country | F1: Name | G1: Bank_Account | H1: Invoice_Number | I1: Invoice_Date | J1: Due_Date | K1: Currency | L1: Net_Amount | M1: VAT_Applicable | N1: VAT_Rate | O1: VAT_Amount | P1: Gross_Amount | Q1: Exchange_Rate | R1: Amount_CHF | S1: Employment_Model | T1: EOR_Provider | U1: Created_Timestamp | V1: Created_By
