Workbook

Sheet Customers
A1: CustomerID | B1: CustomerName | C1: Industry | D1: Country | E1: PaymentTerms | F1: CreditLimit | G1: CustomerSince
A2: CUST-001 | B2: BrightCart | C2: E-commerce | D2: USA | E2: Net 60 | F2: 30000 | G2: 45691
A3: CUST-002 | B3: NexaSoft | C3: SaaS | D3: UK | E3: Net 60 | F3: 10000 | G3: 45912
A4: CUST-003 | B4: UrbanRetail | C4: Education | D4: USA | E4: Net 60 | F4: 50000 | G4: 45582
A5: CUST-004 | B5: LaunchLabs | C5: E-commerce | D5: USA | E5: Net 30 | F5: 20000 | G5: 45824
A6: CUST-005 | B6: DataHive | C6: Education | D6: USA | E6: Net 60 | F6: 20000 | G6: 45932
A7: CUST-006 | B7: ShopOrbit | C7: Education | D7: UAE | E7: Net 30 | F7: 50000 | G7: 45867
A8: CUST-007 | B8: EduNova | C8: Retail | D8: USA | E8: Net 30 | F8: 50000 | G8: 45740
A9: CUST-008 | B9: MarketPulse | C9: Retail | D9: UK | E9: Net 30 | F9: 30000 | G9: 45618
A10: CUST-009 | B10: CloudScale | C10: E-commerce | D10: UAE | E10: Net 30 | F10: 30000 | G10: 45999
A11: CUST-010 | B11: RetailHub | C11: Retail | D11: Canada | E11: Net 45 | F11: 10000 | G11: 45939
A12: CUST-011 | B12: AlphaCommerce | C12: Startup | D12: Canada | E12: Net 30 | F12: 50000 | G12: 45606
A13: CUST-012 | B13: BluePeak Systems | C13: Education | D13: Germany | E13: Net 60 | F13: 30000 | G13: 45861
... A119: CUST-118 | B119: RetailOrbitGlobal | C119: E-commerce | D119: UAE | E119: Net 30 | F119: 20000 | G119: 45977

Sheet Vendors
A1: VendorID | B1: VendorName | C1: Category | D1: Country | E1: PaymentTerms | F1: VendorSince
A2: VEN-001 | B2: Google Ads | C2: Consulting | D2: USA | E2: Net 60 | F2: 45693
A3: VEN-002 | B3: Meta Ads | C3: Freelancer | D3: UAE | E3: Net 30 | F3: 45976
A4: VEN-003 | B4: TikTok Ads | C4: Consulting | D4: Australia | E4: Net 60 | F4: 45852
A5: VEN-004 | B5: LinkedIn Ads | C5: Software | D5: UAE | E5: Net 60 | F5: 45983
A6: VEN-005 | B6: HubSpot | C6: Consulting | D6: Canada | E6: Net 45 | F6: 45647
A7: VEN-006 | B7: Salesforce | C7: Consulting | D7: UAE | E7: Net 45 | F7: 45950
A8: VEN-007 | B8: Mailchimp | C8: Advertising | D8: Australia | E8: Net 45 | F8: 45958
A9: VEN-008 | B9: Ahrefs | C9: Consulting | D9: Australia | E9: Net 30 | F9: 45706
A10: VEN-009 | B10: SEMrush | C10: Consulting | D10: USA | E10: Net 60 | F10: 45712
A11: VEN-010 | B11: Adobe Creative Cloud | C11: Advertising | D11: Germany | E11: Net 45 | F11: 45729
A12: VEN-011 | B12: AWS | C12: Freelancer | D12: UK | E12: Net 30 | F12: 45684
A13: VEN-012 | B13: Google Cloud | C13: Consulting | D13: Australia | E13: Net 30 | F13: 45927
... A41: VEN-040 | B41: Digital Performance Lab | C41: Consulting | D41: UAE | E41: Net 60 | F41: 45667

Sheet Services
A1: ServiceID | B1: ServiceName | C1: StandardPrice | D1: EstimatedCost
A2: SER-001 | B2: SEO Management | C2: 3000 | D2: 1200
A3: SER-002 | B3: Paid Ads Management | C3: 5000 | D3: 2200
A4: SER-003 | B4: Social Media Marketing | C4: 2500 | D4: 900
A5: SER-004 | B5: Website Development | C5: 12000 | D5: 6500
A6: SER-005 | B6: Content Marketing | C6: 3500 | D6: 1500
A7: SER-006 | B7: Email Marketing | C7: 1800 | D7: 700

Sheet Sales_Invoices
A1: InvoiceID | B1: CustomerID | C1: ServiceID | D1: InvoiceDate | E1: DueDate | F1: TotalAmount | G1: Status
A2: INV-00001 | B2: CUST-090 | C2: SER-001 | D2: 46097 | E2: 46127 | F2: 3110.52 | G2: Paid
A3: INV-00002 | B3: CUST-073 | C3: SER-003 | D3: 45987 | E3: 46017 | F3: 2850.29 | G3: Open
A4: INV-00003 | B4: CUST-065 | C4: SER-001 | D4: 46094 | E4: 46124 | F4: 2816.64 | G4: Paid
A5: INV-00004 | B5: CUST-014 | C5: SER-006 | D5: 45971 | E5: 46001 | F5: 1685.69 | G5: Open
A6: INV-00005 | B6: CUST-056 | C6: SER-004 | D6: 46099 | E6: 46129 | F6: 14211.78 | G6: Paid
A7: INV-00006 | B7: CUST-118 | C7: SER-002 | D7: 45982 | E7: 46012 | F7: 5467.59 | G7: Paid
A8: INV-00007 | B8: CUST-076 | C8: SER-005 | D8: 46074 | E8: 46104 | F8: 3884.5 | G8: Open
A9: INV-00008 | B9: CUST-058 | C9: SER-003 | D9: 46047 | E9: 46077 | F9: 2322.3 | G9: Paid
A10: INV-00009 | B10: CUST-044 | C10: SER-002 | D10: 46096 | E10: 46126 | F10: 5500.95 | G10: Paid
A11: INV-00010 | B11: CUST-046 | C11: SER-001 | D11: 46009 | E11: 46039 | F11: 2993.17 | G11: Paid
A12: INV-00011 | B12: CUST-036 | C12: SER-003 | D12: 46008 | E12: 46038 | F12: 2340.34 | G12: Paid
A13: INV-00012 | B13: CUST-053 | C13: SER-005 | D13: 46008 | E13: 46038 | F13: 2814.21 | G13: Paid
... A2801: INV-02800 | B2801: CUST-009 | C2801: SER-005 | D2801: 46083 | E2801: 46113 | F2801: 2878.2 | G2801: Paid

Sheet Customer_Payments
A1: PaymentID | B1: InvoiceID | C1: CustomerID | D1: PaymentDate | E1: PaymentAmount | F1: Method
A2: PAY-00001 | B2: INV-00001 | C2: CUST-090 | D2: 46091 | E2: 3110.52 | F2: Credit Card
A3: PAY-00002 | B3: INV-00003 | C3: CUST-065 | D3: 45887 | E3: 2816.64 | F3: Credit Card
A4: PAY-00003 | B4: INV-00005 | C4: CUST-056 | D4: 46006 | E4: 14211.78 | F4: Stripe
A5: PAY-00004 | B5: INV-00006 | C5: CUST-118 | D5: 46017 | E5: 5467.59 | F5: Stripe
A6: PAY-00005 | B6: INV-00008 | C6: CUST-058 | D6: 45798 | E6: 2322.3 | F6: PayPal
A7: PAY-00006 | B7: INV-00009 | C7: CUST-044 | D7: 45982 | E7: 5500.95 | F7: PayPal
A8: PAY-00007 | B8: INV-00010 | C8: CUST-046 | D8: 45836 | E8: 2993.17 | F8: Credit Card
A9: PAY-00008 | B9: INV-00011 | C9: CUST-036 | D9: 46113 | E9: 2340.34 | F9: Credit Card
A10: PAY-00009 | B10: INV-00012 | C10: CUST-053 | D10: 45758 | E10: 2814.21 | F10: Stripe
A11: PAY-00010 | B11: INV-00013 | C11: CUST-092 | D11: 45784 | E11: 12264.85 | F11: Bank Transfer
A12: PAY-00011 | B12: INV-00014 | C12: CUST-052 | D12: 45673 | E12: 7672.01 | F12: PayPal
A13: PAY-00012 | B13: INV-00014 | C13: CUST-052 | D13: 45674 | E13: 4079.23 | F13: Bank Transfer
... A2242: PAY-02241 | B2242: INV-02800 | C2242: CUST-009 | D2242: 46075 | E2242: 2878.2 | F2242: Bank Transfer

Sheet AR_Aging
A1: CustomerID | B1: CustomerName | C1: InvoiceID | D1: InvoiceDate | E1: DueDate | F1: InvoiceAmount | G1: AmountPaid | H1: OutstandingAmount | I1: DaysOutstanding | J1: AgingBucket
A2: CUST-090 | B2: =VLOOKUP(A2,Customers!A:B,2,FALSE) -> RetailLabs | C2: INV-00001 | D2: 46097 | E2: 46127 | F2: 3110.52 | G2: =SUMIF(Customer_Payments!B:B,C2,Customer_Payments!E:E) -> 3110.52 | H2: =MAX(F2-G2,0) -> 0 | I2: =$L$2-E2 -> -36 | J2: =IF(I2<=0,"Current", IF(I2<=30,"1-30", IF(I2<=60,"31-60", IF(I2<=90,"61-90","90+")))) -> Current | L2: 46091
A3: CUST-073 | B3: =VLOOKUP(A3,Customers!A:B,2,FALSE) -> RetailBoostX | C3: INV-00002 | D3: 45987 | E3: 46017 | F3: 2850.29 | G3: 2000 | H3: =MAX(F3-G3,0) -> 850.29 | I3: =$L$2-E3 -> 74 | J3: =IF(I3<=0,"Current", IF(I3<=30,"1-30", IF(I3<=60,"31-60", IF(I3<=90,"61-90","90+")))) -> 61-90
A4: CUST-065 | B4: =VLOOKUP(A4,Customers!A:B,2,FALSE) -> RetailPulse | C4: INV-00003 | D4: 46094 | E4: 46124 | F4: 2816.64 | G4: =SUMIF(Customer_Payments!B:B,C4,Customer_Payments!E:E) -> 2816.64 | H4: =MAX(F4-G4,0) -> 0 | I4: =$L$2-E4 -> -33 | J4: =IF(I4<=0,"Current", IF(I4<=30,"1-30", IF(I4<=60,"31-60", IF(I4<=90,"61-90","90+")))) -> Current
A5: CUST-014 | B5: =VLOOKUP(A5,Customers!A:B,2,FALSE) -> GrowthSphere | C5: INV-00004 | D5: 45971 | E5: 46001 | F5: 1685.69 | G5: =SUMIF(Customer_Payments!B:B,C5,Customer_Payments!E:E) -> 0 | H5: =MAX(F5-G5,0) -> 1685.69 | I5: =$L$2-E5 -> 90 | J5: =IF(I5<=0,"Current", IF(I5<=30,"1-30", IF(I5<=60,"31-60", IF(I5<=90,"61-90","90+")))) -> 61-90
A6: CUST-056 | B6: =VLOOKUP(A6,Customers!A:B,2,FALSE) -> MarketNova | C6: INV-00005 | D6: 46099 | E6: 46129 | F6: 14211.78 | G6: =SUMIF(Customer_Payments!B:B,C6,Customer_Payments!E:E) -> 14211.78 | H6: =MAX(F6-G6,0) -> 0 | I6: =$L$2-E6 -> -38 | J6: =IF(I6<=0,"Current", IF(I6<=30,"1-30", IF(I6<=60,"31-60", IF(I6<=90,"61-90","90+")))) -> Current
A7: CUST-118 | B7: =VLOOKUP(A7,Customers!A:B,2,FALSE) -> RetailOrbitGlobal | C7: INV-00006 | D7: 45982 | E7: 46012 | F7: 5467.59 | G7: =SUMIF(Customer_Payments!B:B,C7,Customer_Payments!E:E) -> 5467.59 | H7: =MAX(F7-G7,0) -> 0 | I7: =$L$2-E7 -> 79 | J7: =IF(I7<=0,"Current", IF(I7<=30,"1-30", IF(I7<=60,"31-60", IF(I7<=90,"61-90","90+")))) -> 61-90
A8: CUST-076 | B8: =VLOOKUP(A8,Customers!A:B,2,FALSE) -> RetailNovaX | C8: INV-00007 | D8: 46074 | E8: 46104 | F8: 3884.5 | G8: =SUMIF(Customer_Payments!B:B,C8,Customer_Payments!E:E) -> 0 | H8: =MAX(F8-G8,0) -> 3884.5 | I8: =$L$2-E8 -> -13 | J8: =IF(I8<=0,"Current", IF(I8<=30,"1-30", IF(I8<=60,"31-60", IF(I8<=90,"61-90","90+")))) -> Current
A9: CUST-058 | B9: =VLOOKUP(A9,Customers!A:B,2,FALSE) -> MarketScale | C9: INV-00008 | D9: 46047 | E9: 46077 | F9: 2322.3 | G9: =SUMIF(Customer_Payments!B:B,C9,Customer_Payments!E:E) -> 2322.3 | H9: =MAX(F9-G9,0) -> 0 | I9: =$L$2-E9 -> 14 | J9: =IF(I9<=0,"Current", IF(I9<=30,"1-30", IF(I9<=60,"31-60", IF(I9<=90,"61-90","90+")))) -> 1-30
A10: CUST-044 | B10: =VLOOKUP(A10,Customers!A:B,2,FALSE) -> RetailNexus | C10: INV-00009 | D10: 46096 | E10: 46126 | F10: 5500.95 | G10: =SUMIF(Customer_Payments!B:B,C10,Customer_Payments!E:E) -> 5500.95 | H10: =MAX(F10-G10,0) -> 0 | I10: =$L$2-E10 -> -35 | J10: =IF(I10<=0,"Current", IF(I10<=30,"1-30", IF(I10<=60,"31-60", IF(I10<=90,"61-90","90+")))) -> Current
A11: CUST-046 | B11: =VLOOKUP(A11,Customers!A:B,2,FALSE) -> RetailShift | C11: INV-00010 | D11: 46009 | E11: 46039 | F11: 2993.17 | G11: =SUMIF(Customer_Payments!B:B,C11,Customer_Payments!E:E) -> 2993.17 | H11: =MAX(F11-G11,0) -> 0 | I11: =$L$2-E11 -> 52 | J11: =IF(I11<=0,"Current", IF(I11<=30,"1-30", IF(I11<=60,"31-60", IF(I11<=90,"61-90","90+")))) -> 31-60
A12: CUST-036 | B12: =VLOOKUP(A12,Customers!A:B,2,FALSE) -> RetailWorks | C12: INV-00011 | D12: 46008 | E12: 46038 | F12: 2340.34 | G12: =SUMIF(Customer_Payments!B:B,C12,Customer_Payments!E:E) -> 2340.34 | H12: =MAX(F12-G12,0) -> 0 | I12: =$L$2-E12 -> 53 | J12: =IF(I12<=0,"Current", IF(I12<=30,"1-30", IF(I12<=60,"31-60", IF(I12<=90,"61-90","90+")))) -> 31-60
A13: CUST-053 | B13: =VLOOKUP(A13,Customers!A:B,2,FALSE) -> MarketBridge | C13: INV-00012 | D13: 46008 | E13: 46038 | F13: 2814.21 | G13: =SUMIF(Customer_Payments!B:B,C13,Customer_Payments!E:E) -> 2814.21 | H13: =MAX(F13-G13,0) -> 0 | I13: =$L$2-E13 -> 53 | J13: =IF(I13<=0,"Current", IF(I13<=30,"1-30", IF(I13<=60,"31-60", IF(I13<=90,"61-90","90+")))) -> 31-60
A14: CUST-092 | B14: =VLOOKUP(A14,Customers!A:B,2,FALSE) -> RetailEdgePro | C14: INV-00013 | D14: 46001 | E14: 46031 | F14: 12264.85 | G14: =SUMIF(Customer_Payments!B:B,C14,Customer_Payments!E:E) -> 12264.85 | H14: =MAX(F14-G14,0) -> 0 | I14: =$L$2-E14 -> 60 | J14: =IF(I14<=0,"Current", IF(I14<=30,"1-30", IF(I14<=60,"31-60", IF(I14<=90,"61-90","90+")))) -> 31-60
A15: CUST-052 | B15: =VLOOKUP(A15,Customers!A:B,2,FALSE) -> RetailAxis | C15: INV-00014 | D15: 46098 | E15: 46128 | F15: 11751.24 | G15: =SUMIF(Customer_Payments!B:B,C15,Customer_Payments!E:E) -> 11751.24 | H15: =MAX(F15-G15,0) -> 0 | I15: =$L$2-E15 -> -37 | J15: =IF(I15<=0,"Current", IF(I15<=30,"1-30", IF(I15<=60,"31-60", IF(I15<=90,"61-90","90+")))) -> Current
... A19: CUST-028 | B19: =VLOOKUP(A19,Customers!A:B,2,FALSE) -> OptiCommerce | C19: INV-00018 | D19: 45979 | E19: 46009 | F19: 2119.55 | G19: =SUMIF(Customer_Payments!B:B,C19,Customer_Payments!E:E) -> 2119.55 | H19: =MAX(F19-G19,0) -> 0 | I19: =$L$2-E19 -> 82 | J19: =IF(I19<=0,"Current", IF(I19<=30,"1-30", IF(I19<=60,"31-60", IF(I19<=90,"61-90","90+")))) -> 61-90
A20: CUST-068 | B20: =VLOOKUP(A20,Customers!A:B,2,FALSE) -> RetailPrime | C20: INV-00019 | D20: 45988 | E20: 46018 | F20: 1788.62 | G20: 700 | H20: =MAX(F20-G20,0) -> 1088.62 | I20: =$L$2-E20 -> 73 | J20: =IF(I20<=0,"Current", IF(I20<=30,"1-30", IF(I20<=60,"31-60", IF(I20<=90,"61-90","90+")))) -> 61-90
A21: CUST-047 | B21: =VLOOKUP(A21,Customers!A:B,2,FALSE) -> PrimeCart | C21: INV-00020 | D21: 46054 | E21: 46084 | F21: 3196.2 | G21: =SUMIF(Customer_Payments!B:B,C21,Customer_Payments!E:E) -> 3196.2 | H21: =MAX(F21-G21,0) -> 0 | I21: =$L$2-E21 -> 7 | J21: =IF(I21<=0,"Current", IF(I21<=30,"1-30", IF(I21<=60,"31-60", IF(I21<=90,"61-90","90+")))) -> 1-30
A22: CUST-006 | B22: =VLOOKUP(A22,Customers!A:B,2,FALSE) -> ShopOrbit | C22: INV-00021 | D22: 46080 | E22: 46110 | F22: 4604.54 | G22: =SUMIF(Customer_Payments!B:B,C22,Customer_Payments!E:E) -> 4604.54 | H22: =MAX(F22-G22,0) -> 0 | I22: =$L$2-E22 -> -19 | J22: =IF(I22<=0,"Current", IF(I22<=30,"1-30", IF(I22<=60,"31-60", IF(I22<=90,"61-90","90+")))) -> Current
A23: CUST-097 | B23: =VLOOKUP(A23,Customers!A:B,2,FALSE) -> RetailVisionPro | C23: INV-00022 | D23: 46082 | E23: 46112 | F23: 3064.03 | G23: =SUMIF(Customer_Payments!B:B,C23,Customer_Payments!E:E) -> 3064.03 | H23: =MAX(F23-G23,0) -> 0 | I23: =$L$2-E23 -> -21 | J23: =IF(I23<=0,"Current", IF(I23<=30,"1-30", IF(I23<=60,"31-60", IF(I23<=90,"61-90","90+")))) -> Current
A24: CUST-062 | B24: =VLOOKUP(A24,Customers!A:B,2,FALSE) -> RetailVision | C24: INV-00023 | D24: 46026 | E24: 46056 | F24: 10092.42 | G24: =SUMIF(Customer_Payments!B:B,C24,Customer_Payments!E:E) -> 10092.42 | H24: =MAX(F24-G24,0) -> 0 | I24: =$L$2-E24 -> 35 | J24: =IF(I24<=0,"Current", IF(I24<=30,"1-30", IF(I24<=60,"31-60", IF(I24<=90,"61-90","90+")))) -> 31-60
A25: CUST-062 | B25: =VLOOKUP(A25,Customers!A:B,2,FALSE) -> RetailVision | C25: INV-00024 | D25: 46022 | E25: 46052 | F25: 11235.39 | G25: =SUMIF(Customer_Payments!B:B,C25,Customer_Payments!E:E) -> 0 | H25: =MAX(F25-G25,0) -> 11235.39 | I25: =$L$2-E25 -> 39 | J25: =IF(I25<=0,"Current", IF(I25<=30,"1-30", IF(I25<=60,"31-60", IF(I25<=90,"61-90","90+")))) -> 31-60
A26: CUST-081 | B26: =VLOOKUP(A26,Customers!A:B,2,FALSE) -> RetailStreamX | C26: INV-00025 | D26: 45968 | E26: 45998 | F26: 3386.54 | G26: =SUMIF(Customer_Payments!B:B,C26,Customer_Payments!E:E) -> 3386.54 | H26: =MAX(F26-G26,0) -> 0 | I26: =$L$2-E26 -> 93 | J26: =IF(I26<=0,"Current", IF(I26<=30,"1-30", IF(I26<=60,"31-60", IF(I26<=90,"61-90","90+")))) -> 90+
A27: CUST-011 | B27: =VLOOKUP(A27,Customers!A:B,2,FALSE) -> AlphaCommerce | C27: INV-00026 | D27: 45997 | E27: 46027 | F27: 1478.6 | G27: =SUMIF(Customer_Payments!B:B,C27,Customer_Payments!E:E) -> 0 | H27: =MAX(F27-G27,0) -> 1478.6 | I27: =$L$2-E27 -> 64 | J27: =IF(I27<=0,"Current", IF(I27<=30,"1-30", IF(I27<=60,"31-60", IF(I27<=90,"61-90","90+")))) -> 61-90
A28: CUST-102 | B28: =VLOOKUP(A28,Customers!A:B,2,FALSE) -> RetailNextPro | C28: INV-00027 | D28: 46022 | E28: 46052 | F28: 4236.9 | G28: =SUMIF(Customer_Payments!B:B,C28,Customer_Payments!E:E) -> 4236.9 | H28: =MAX(F28-G28,0) -> 0 | I28: =$L$2-E28 -> 39 | J28: =IF(I28<=0,"Current", IF(I28<=30,"1-30", IF(I28<=60,"31-60", IF(I28<=90,"61-90","90+")))) -> 31-60
A29: CUST-057 | B29: =VLOOKUP(A29,Customers!A:B,2,FALSE) -> RetailCore | C29: INV-00028 | D29: 46045 | E29: 46075 | F29: 3115.96 | G29: =SUMIF(Customer_Payments!B:B,C29,Customer_Payments!E:E) -> 3115.96 | H29: =MAX(F29-G29,0) -> 0 | I29: =$L$2-E29 -> 16 | J29: =IF(I29<=0,"Current", IF(I29<=30,"1-30", IF(I29<=60,"31-60", IF(I29<=90,"61-90","90+")))) -> 1-30
A30: CUST-008 | B30: =VLOOKUP(A30,Customers!A:B,2,FALSE) -> MarketPulse | C30: INV-00029 | D30: 46068 | E30: 46098 | F30: 2860.17 | G30: =SUMIF(Customer_Payments!B:B,C30,Customer_Payments!E:E) -> 2860.17 | H30: =MAX(F30-G30,0) -> 0 | I30: =$L$2-E30 -> -7 | J30: =IF(I30<=0,"Current", IF(I30<=30,"1-30", IF(I30<=60,"31-60", IF(I30<=90,"61-90","90+")))) -> Current
A31: CUST-034 | B31: =VLOOKUP(A31,Customers!A:B,2,FALSE) -> GlobalCart | C31: INV-00030 | D31: 46066 | E31: 46096 | F31: 4144.15 | G31: =SUMIF(Customer_Payments!B:B,C31,Customer_Payments!E:E) -> 4144.15 | H31: =MAX(F31-G31,0) -> 0 | I31: =$L$2-E31 -> -5 | J31: =IF(I31<=0,"Current", IF(I31<=30,"1-30", IF(I31<=60,"31-60", IF(I31<=90,"61-90","90+")))) -> Current
A32: CUST-021 | B32: =VLOOKUP(A32,Customers!A:B,2,FALSE) -> Skyline Commerce | C32: INV-00031 | D32: 45982 | E32: 46012 | F32: 1498.45 | G32: =SUMIF(Customer_Payments!B:B,C32,Customer_Payments!E:E) -> 1498.45 | H32: =MAX(F32-G32,0) -> 0 | I32: =$L$2-E32 -> 79 | J32: =IF(I32<=0,"Current", IF(I32<=30,"1-30", IF(I32<=60,"31-60", IF(I32<=90,"61-90","90+")))) -> 61-90
... A41: CUST-074 | B41: =VLOOKUP(A41,Customers!A:B,2,FALSE) -> RetailEdgeX | C41: INV-00040 | D41: 46100 | E41: 46130 | F41: 2025.86 | G41: =SUMIF(Customer_Payments!B:B,C41,Customer_Payments!E:E) -> 0 | H41: =MAX(F41-G41,0) -> 2025.86 | I41: =$L$2-E41 -> -39 | J41: =IF(I41<=0,"Current", IF(I41<=30,"1-30", IF(I41<=60,"31-60", IF(I41<=90,"61-90","90+")))) -> Current
A42: CUST-074 | B42: =VLOOKUP(A42,Customers!A:B,2,FALSE) -> RetailEdgeX | C42: INV-00041 | D42: 46022 | E42: 46052 | F42: 4131.1 | G42: 2500 | H42: =MAX(F42-G42,0) -> 1631.1 | I42: =$L$2-E42 -> 39 | J42: =IF(I42<=0,"Current", IF(I42<=30,"1-30", IF(I42<=60,"31-60", IF(I42<=90,"61-90","90+")))) -> 31-60
A43: CUST-057 | B43: =VLOOKUP(A43,Customers!A:B,2,FALSE) -> RetailCore | C43: INV-00042 | D43: 46101 | E43: 46131 | F43: 3315.73 | G43: =SUMIF(Customer_Payments!B:B,C43,Customer_Payments!E:E) -> 3315.73 | H43: =MAX(F43-G43,0) -> 0 | I43: =$L$2-E43 -> -40 | J43: =IF(I43<=0,"Current", IF(I43<=30,"1-30", IF(I43<=60,"31-60", IF(I43<=90,"61-90","90+")))) -> Current
A44: CUST-063 | B44: =VLOOKUP(A44,Customers!A:B,2,FALSE) -> RetailNext | C44: INV-00043 | D44: 45982 | E44: 46012 | F44: 2181.49 | G44: =SUMIF(Customer_Payments!B:B,C44,Customer_Payments!E:E) -> 2181.49 | H44: =MAX(F44-G44,0) -> 0 | I44: =$L$2-E44 -> 79 | J44: =IF(I44<=0,"Current", IF(I44<=30,"1-30", IF(I44<=60,"31-60", IF(I44<=90,"61-90","90+")))) -> 61-90
A45: CUST-014 | B45: =VLOOKUP(A45,Customers!A:B,2,FALSE) -> GrowthSphere | C45: INV-00044 | D45: 46041 | E45: 46071 | F45: 2964.01 | G45: =SUMIF(Customer_Payments!B:B,C45,Customer_Payments!E:E) -> 2964.01 | H45: =MAX(F45-G45,0) -> 0 | I45: =$L$2-E45 -> 20 | J45: =IF(I45<=0,"Current", IF(I45<=30,"1-30", IF(I45<=60,"31-60", IF(I45<=90,"61-90","90+")))) -> 1-30
A46: CUST-052 | B46: =VLOOKUP(A46,Customers!A:B,2,FALSE) -> RetailAxis | C46: INV-00045 | D46: 46112 | E46: 46142 | F46: 4659.61 | G46: =SUMIF(Customer_Payments!B:B,C46,Customer_Payments!E:E) -> 4659.61 | H46: =MAX(F46-G46,0) -> 0 | I46: =$L$2-E46 -> -51 | J46: =IF(I46<=0,"Current", IF(I46<=30,"1-30", IF(I46<=60,"31-60", IF(I46<=90,"61-90","90+")))) -> Current
A47: CUST-015 | B47: =VLOOKUP(A47,Customers!A:B,2,FALSE) -> InsightLoop | C47: INV-00046 | D47: 45970 | E47: 46000 | F47: 2851.38 | G47: =SUMIF(Customer_Payments!B:B,C47,Customer_Payments!E:E) -> 2851.38 | H47: =MAX(F47-G47,0) -> 0 | I47: =$L$2-E47 -> 91 | J47: =IF(I47<=0,"Current", IF(I47<=30,"1-30", IF(I47<=60,"31-60", IF(I47<=90,"61-90","90+")))) -> 90+
A48: CUST-070 | B48: =VLOOKUP(A48,Customers!A:B,2,FALSE) -> RetailSphere | C48: INV-00047 | D48: 46071 | E48: 46101 | F48: 13751.57 | G48: =SUMIF(Customer_Payments!B:B,C48,Customer_Payments!E:E) -> 13751.57 | H48: =MAX(F48-G48,0) -> 0 | I48: =$L$2-E48 -> -10 | J48: =IF(I48<=0,"Current", IF(I48<=30,"1-30", IF(I48<=60,"31-60", IF(I48<=90,"61-90","90+")))) -> Current
A49: CUST-097 | B49: =VLOOKUP(A49,Customers!A:B,2,FALSE) -> RetailVisionPro | C49: INV-00048 | D49: 45985 | E49: 46015 | F49: 11583.59 | G49: =SUMIF(Customer_Payments!B:B,C49,Customer_Payments!E:E) -> 11583.59 | H49: =MAX(F49-G49,0) -> 0 | I49: =$L$2-E49 -> 76 | J49: =IF(I49<=0,"Current", IF(I49<=30,"1-30", IF(I49<=60,"31-60", IF(I49<=90,"61-90","90+")))) -> 61-90
A50: CUST-071 | B50: =VLOOKUP(A50,Customers!A:B,2,FALSE) -> RetailBridge | C50: INV-00049 | D50: 45971 | E50: 46001 | F50: 12601.96 | G50: =SUMIF(Customer_Payments!B:B,C50,Customer_Payments!E:E) -> 12601.96 | H50: =MAX(F50-G50,0) -> 0 | I50: =$L$2-E50 -> 90 | J50: =IF(I50<=0,"Current", IF(I50<=30,"1-30", IF(I50<=60,"31-60", IF(I50<=90,"61-90","90+")))) -> 61-90
A51: CUST-004 | B51: =VLOOKUP(A51,Customers!A:B,2,FALSE) -> LaunchLabs | C51: INV-00050 | D51: 46071 | E51: 46101 | F51: 5855.35 | G51: =SUMIF(Customer_Payments!B:B,C51,Customer_Payments!E:E) -> 5855.35 | H51: =MAX(F51-G51,0) -> 0 | I51: =$L$2-E51 -> -10 | J51: =IF(I51<=0,"Current", IF(I51<=30,"1-30", IF(I51<=60,"31-60", IF(I51<=90,"61-90","90+")))) -> Current
A52: CUST-071 | B52: =VLOOKUP(A52,Customers!A:B,2,FALSE) -> RetailBridge | C52: INV-00051 | D52: 46033 | E52: 46063 | F52: 1878.39 | G52: =SUMIF(Customer_Payments!B:B,C52,Customer_Payments!E:E) -> 1878.39 | H52: =MAX(F52-G52,0) -> 0 | I52: =$L$2-E52 -> 28 | J52: =IF(I52<=0,"Current", IF(I52<=30,"1-30", IF(I52<=60,"31-60", IF(I52<=90,"61-90","90+")))) -> 1-30
A53: CUST-117 | B53: =VLOOKUP(A53,Customers!A:B,2,FALSE) -> RetailFlowGlobal | C53: INV-00052 | D53: 46014 | E53: 46044 | F53: 3062.7 | G53: 2000 | H53: =MAX(F53-G53,0) -> 1062.7 | I53: =$L$2-E53 -> 47 | J53: =IF(I53<=0,"Current", IF(I53<=30,"1-30", IF(I53<=60,"31-60", IF(I53<=90,"61-90","90+")))) -> 31-60
A54: CUST-064 | B54: =VLOOKUP(A54,Customers!A:B,2,FALSE) -> RetailPath | C54: INV-00053 | D54: 46042 | E54: 46072 | F54: 2953.74 | G54: 1500 | H54: =MAX(F54-G54,0) -> 1453.74 | I54: =$L$2-E54 -> 19 | J54: =IF(I54<=0,"Current", IF(I54<=30,"1-30", IF(I54<=60,"31-60", IF(I54<=90,"61-90","90+")))) -> 1-30
A55: CUST-062 | B55: =VLOOKUP(A55,Customers!A:B,2,FALSE) -> RetailVision | C55: INV-00054 | D55: 46005 | E55: 46035 | F55: 1650.14 | G55: =SUMIF(Customer_Payments!B:B,C55,Customer_Payments!E:E) -> 1650.14 | H55: =MAX(F55-G55,0) -> 0 | I55: =$L$2-E55 -> 56 | J55: =IF(I55<=0,"Current", IF(I55<=30,"1-30", IF(I55<=60,"31-60", IF(I55<=90,"61-90","90+")))) -> 31-60
A56: CUST-118 | B56: =VLOOKUP(A56,Customers!A:B,2,FALSE) -> RetailOrbitGlobal | C56: INV-00055 | D56: 45986 | E56: 46016 | F56: 10769.91 | G56: =SUMIF(Customer_Payments!B:B,C56,Customer_Payments!E:E) -> 10769.91 | H56: =MAX(F56-G56,0) -> 0 | I56: =$L$2-E56 -> 75 | J56: =IF(I56<=0,"Current", IF(I56<=30,"1-30", IF(I56<=60,"31-60", IF(I56<=90,"61-90","90+")))) -> 61-90
A57: CUST-036 | B57: =VLOOKUP(A57,Customers!A:B,2,FALSE) -> RetailWorks | C57: INV-00056 | D57: 45963 | E57: 45993 | F57: 3511.54 | G57: 1440 | H57: =MAX(F57-G57,0) -> 2071.54 | I57: =$L$2-E57 -> 98 | J57: =IF(I57<=0,"Current", IF(I57<=30,"1-30", IF(I57<=60,"31-60", IF(I57<=90,"61-90","90+")))) -> 90+
A58: CUST-001 | B58: =VLOOKUP(A58,Customers!A:B,2,FALSE) -> BrightCart | C58: INV-00057 | D58: 46037 | E58: 46067 | F58: 11231.4 | G58: =SUMIF(Customer_Payments!B:B,C58,Customer_Payments!E:E) -> 11231.4 | H58: =MAX(F58-G58,0) -> 0 | I58: =$L$2-E58 -> 24 | J58: =IF(I58<=0,"Current", IF(I58<=30,"1-30", IF(I58<=60,"31-60", IF(I58<=90,"61-90","90+")))) -> 1-30
A59: CUST-085 | B59: =VLOOKUP(A59,Customers!A:B,2,FALSE) -> RetailBridgeX | C59: INV-00058 | D59: 46000 | E59: 46030 | F59: 2726.05 | G59: =SUMIF(Customer_Payments!B:B,C59,Customer_Payments!E:E) -> 2726.05 | H59: =MAX(F59-G59,0) -> 0 | I59: =$L$2-E59 -> 61 | J59: =IF(I59<=0,"Current", IF(I59<=30,"1-30", IF(I59<=60,"31-60", IF(I59<=90,"61-90","90+")))) -> 61-90
A60: CUST-043 | B60: =VLOOKUP(A60,Customers!A:B,2,FALSE) -> CommercePilot | C60: INV-00059 | D60: 46015 | E60: 46045 | F60: 13753.25 | G60: =SUMIF(Customer_Payments!B:B,C60,Customer_Payments!E:E) -> 13753.25 | H60: =MAX(F60-G60,0) -> 0 | I60: =$L$2-E60 -> 46 | J60: =IF(I60<=0,"Current", IF(I60<=30,"1-30", IF(I60<=60,"31-60", IF(I60<=90,"61-90","90+")))) -> 31-60
A61: CUST-112 | B61: =VLOOKUP(A61,Customers!A:B,2,FALSE) -> RetailEdgeGlobal | C61: INV-00060 | D61: 46047 | E61: 46077 | F61: 3868.02 | G61: 1220 | H61: =MAX(F61-G61,0) -> 2648.02 | I61: =$L$2-E61 -> 14 | J61: =IF(I61<=0,"Current", IF(I61<=30,"1-30", IF(I61<=60,"31-60", IF(I61<=90,"61-90","90+")))) -> 1-30
A62: CUST-110 | B62: =VLOOKUP(A62,Customers!A:B,2,FALSE) -> RetailLabsPro | C62: INV-00061 | D62: 46073 | E62: 46103 | F62: 5961.55 | G62: =SUMIF(Customer_Payments!B:B,C62,Customer_Payments!E:E) -> 5961.55 | H62: =MAX(F62-G62,0) -> 0 | I62: =$L$2-E62 -> -12 | J62: =IF(I62<=0,"Current", IF(I62<=30,"1-30", IF(I62<=60,"31-60", IF(I62<=90,"61-90","90+")))) -> Current
A63: CUST-104 | B63: =VLOOKUP(A63,Customers!A:B,2,FALSE) -> RetailAxisPro | C63: INV-00062 | D63: 45989 | E63: 46019 | F63: 9809.51 | G63: =SUMIF(Customer_Payments!B:B,C63,Customer_Payments!E:E) -> 9809.51 | H63: =MAX(F63-G63,0) -> 0 | I63: =$L$2-E63 -> 72 | J63: =IF(I63<=0,"Current", IF(I63<=30,"1-30", IF(I63<=60,"31-60", IF(I63<=90,"61-90","90+")))) -> 61-90
A64: CUST-064 | B64: =VLOOKUP(A64,Customers!A:B,2,FALSE) -> RetailPath | C64: INV-00063 | D64: 45975 | E64: 46005 | F64: 11453.18 | G64: 7000 | H64: =MAX(F64-G64,0) -> 4453.18 | I64: =$L$2-E64 -> 86 | J64: =IF(I64<=0,"Current", IF(I64<=30,"1-30", IF(I64<=60,"31-60", IF(I64<=90,"61-90","90+")))) -> 61-90
A65: CUST-112 | B65: =VLOOKUP(A65,Customers!A:B,2,FALSE) -> RetailEdgeGlobal | C65: INV-00064 | D65: 46032 | E65: 46062 | F65: 2551.5 | G65: 899 | H65: =MAX(F65-G65,0) -> 1652.5 | I65: =$L$2-E65 -> 29 | J65: =IF(I65<=0,"Current", IF(I65<=30,"1-30", IF(I65<=60,"31-60", IF(I65<=90,"61-90","90+")))) -> 1-30
A66: CUST-053 | B66: =VLOOKUP(A66,Customers!A:B,2,FALSE) -> MarketBridge | C66: INV-00065 | D66: 45970 | E66: 46000 | F66: 10078.62 | G66: =SUMIF(Customer_Payments!B:B,C66,Customer_Payments!E:E) -> 10078.62 | H66: =MAX(F66-G66,0) -> 0 | I66: =$L$2-E66 -> 91 | J66: =IF(I66<=0,"Current", IF(I66<=30,"1-30", IF(I66<=60,"31-60", IF(I66<=90,"61-90","90+")))) -> 90+
A67: CUST-034 | B67: =VLOOKUP(A67,Customers!A:B,2,FALSE) -> GlobalCart | C67: INV-00066 | D67: 46044 | E67: 46074 | F67: 2138.37 | G67: =SUMIF(Customer_Payments!B:B,C67,Customer_Payments!E:E) -> 0 | H67: =MAX(F67-G67,0) -> 2138.37 | I67: =$L$2-E67 -> 17 | J67: =IF(I67<=0,"Current", IF(I67<=30,"1-30", IF(I67<=60,"31-60", IF(I67<=90,"61-90","90+")))) -> 1-30
A68: CUST-043 | B68: =VLOOKUP(A68,Customers!A:B,2,FALSE) -> CommercePilot | C68: INV-00067 | D68: 46107 | E68: 46137 | F68: 2623.26 | G68: =SUMIF(Customer_Payments!B:B,C68,Customer_Payments!E:E) -> 2623.26 | H68: =MAX(F68-G68,0) -> 0 | I68: =$L$2-E68 -> -46 | J68: =IF(I68<=0,"Current", IF(I68<=30,"1-30", IF(I68<=60,"31-60", IF(I68<=90,"61-90","90+")))) -> Current
A69: CUST-114 | B69: =VLOOKUP(A69,Customers!A:B,2,FALSE) -> RetailPrimeGlobal | C69: INV-00068 | D69: 46073 | E69: 46103 | F69: 2058.73 | G69: =SUMIF(Customer_Payments!B:B,C69,Customer_Payments!E:E) -> 2058.73 | H69: =MAX(F69-G69,0) -> 0 | I69: =$L$2-E69 -> -12 | J69: =IF(I69<=0,"Current", IF(I69<=30,"1-30", IF(I69<=60,"31-60", IF(I69<=90,"61-90","90+")))) -> Current
A70: CUST-081 | B70: =VLOOKUP(A70,Customers!A:B,2,FALSE) -> RetailStreamX | C70: INV-00069 | D70: 46088 | E70: 46118 | F70: 13787.44 | G70: =SUMIF(Customer_Payments!B:B,C70,Customer_Payments!E:E) -> 13787.44 | H70: =MAX(F70-G70,0) -> 0 | I70: =$L$2-E70 -> -27 | J70: =IF(I70<=0,"Current", IF(I70<=30,"1-30", IF(I70<=60,"31-60", IF(I70<=90,"61-90","90+")))) -> Current
A71: CUST-013 | B71: =VLOOKUP(A71,Customers!A:B,2,FALSE) -> NextWave Digital | C71: INV-00070 | D71: 46048 | E71: 46078 | F71: 2103.07 | G71: =SUMIF(Customer_Payments!B:B,C71,Customer_Payments!E:E) -> 2103.07 | H71: =MAX(F71-G71,0) -> 0 | I71: =$L$2-E71 -> 13 | J71: =IF(I71<=0,"Current", IF(I71<=30,"1-30", IF(I71<=60,"31-60", IF(I71<=90,"61-90","90+")))) -> 1-30
A72: CUST-039 | B72: =VLOOKUP(A72,Customers!A:B,2,FALSE) -> EdgeRetail | C72: INV-00071 | D72: 45974 | E72: 46004 | F72: 1946.8 | G72: =SUMIF(Customer_Payments!B:B,C72,Customer_Payments!E:E) -> 1946.8 | H72: =MAX(F72-G72,0) -> 0 | I72: =$L$2-E72 -> 87 | J72: =IF(I72<=0,"Current", IF(I72<=30,"1-30", IF(I72<=60,"31-60", IF(I72<=90,"61-90","90+")))) -> 61-90
A73: CUST-048 | B73: =VLOOKUP(A73,Customers!A:B,2,FALSE) -> RetailEdge | C73: INV-00072 | D73: 46049 | E73: 46079 | F73: 2455.19 | G73: =SUMIF(Customer_Payments!B:B,C73,Customer_Payments!E:E) -> 2455.19 | H73: =MAX(F73-G73,0) -> 0 | I73: =$L$2-E73 -> 12 | J73: =IF(I73<=0,"Current", IF(I73<=30,"1-30", IF(I73<=60,"31-60", IF(I73<=90,"61-90","90+")))) -> 1-30
A74: CUST-102 | B74: =VLOOKUP(A74,Customers!A:B,2,FALSE) -> RetailNextPro | C74: INV-00073 | D74: 46099 | E74: 46129 | F74: 10298.74 | G74: =SUMIF(Customer_Payments!B:B,C74,Customer_Payments!E:E) -> 10298.74 | H74: =MAX(F74-G74,0) -> 0 | I74: =$L$2-E74 -> -38 | J74: =IF(I74<=0,"Current", IF(I74<=30,"1-30", IF(I74<=60,"31-60", IF(I74<=90,"61-90","90+")))) -> Current
A75: CUST-080 | B75: =VLOOKUP(A75,Customers!A:B,2,FALSE) -> RetailNextX | C75: INV-00074 | D75: 46090 | E75: 46120 | F75: 4339.97 | G75: =SUMIF(Customer_Payments!B:B,C75,Customer_Payments!E:E) -> 0 | H75: =MAX(F75-G75,0) -> 4339.97 | I75: =$L$2-E75 -> -29 | J75: =IF(I75<=0,"Current", IF(I75<=30,"1-30", IF(I75<=60,"31-60", IF(I75<=90,"61-90","90+")))) -> Current
A76: CUST-082 | B76: =VLOOKUP(A76,Customers!A:B,2,FALSE) -> RetailPrimeX | C76: INV-00075 | D76: 46102 | E76: 46132 | F76: 1613.4 | G76: =SUMIF(Customer_Payments!B:B,C76,Customer_Payments!E:E) -> 1613.4 | H76: =MAX(F76-G76,0) -> 0 | I76: =$L$2-E76 -> -41 | J76: =IF(I76<=0,"Current", IF(I76<=30,"1-30", IF(I76<=60,"31-60", IF(I76<=90,"61-90","90+")))) -> Current
A77: CUST-060 | B77: =VLOOKUP(A77,Customers!A:B,2,FALSE) -> MarketWorks | C77: INV-00076 | D77: 46006 | E77: 46036 | F77: 2459.57 | G77: =SUMIF(Customer_Payments!B:B,C77,Customer_Payments!E:E) -> 0 | H77: =MAX(F77-G77,0) -> 2459.57 | I77: =$L$2-E77 -> 55 | J77: =IF(I77<=0,"Current", IF(I77<=30,"1-30", IF(I77<=60,"31-60", IF(I77<=90,"61-90","90+")))) -> 31-60
... A83: CUST-116 | B83: =VLOOKUP(A83,Customers!A:B,2,FALSE) -> RetailCoreGlobal | C83: INV-00082 | D83: 46060 | E83: 46090 | F83: 2140.99 | G83: =SUMIF(Customer_Payments!B:B,C83,Customer_Payments!E:E) -> 2140.99 | H83: =MAX(F83-G83,0) -> 0 | I83: =$L$2-E83 -> 1 | J83: =IF(I83<=0,"Current", IF(I83<=30,"1-30", IF(I83<=60,"31-60", IF(I83<=90,"61-90","90+")))) -> 1-30
A84: CUST-029 | B84: =VLOOKUP(A84,Customers!A:B,2,FALSE) -> FusionRetail | C84: INV-00083 | D84: 46010 | E84: 46040 | F84: 2775.74 | G84: 1400 | H84: =MAX(F84-G84,0) -> 1375.74 | I84: =$L$2-E84 -> 51 | J84: =IF(I84<=0,"Current", IF(I84<=30,"1-30", IF(I84<=60,"31-60", IF(I84<=90,"61-90","90+")))) -> 31-60
A85: CUST-099 | B85: =VLOOKUP(A85,Customers!A:B,2,FALSE) -> RetailFlowPro | C85: INV-00084 | D85: 46067 | E85: 46097 | F85: 1576.9 | G85: 770 | H85: =MAX(F85-G85,0) -> 806.9 | I85: =$L$2-E85 -> -6 | J85: =IF(I85<=0,"Current", IF(I85<=30,"1-30", IF(I85<=60,"31-60", IF(I85<=90,"61-90","90+")))) -> Current
A86: CUST-081 | B86: =VLOOKUP(A86,Customers!A:B,2,FALSE) -> RetailStreamX | C86: INV-00085 | D86: 46104 | E86: 46134 | F86: 1930.22 | G86: =SUMIF(Customer_Payments!B:B,C86,Customer_Payments!E:E) -> 1930.22 | H86: =MAX(F86-G86,0) -> 0 | I86: =$L$2-E86 -> -43 | J86: =IF(I86<=0,"Current", IF(I86<=30,"1-30", IF(I86<=60,"31-60", IF(I86<=90,"61-90","90+")))) -> Current
A87: CUST-047 | B87: =VLOOKUP(A87,Customers!A:B,2,FALSE) -> PrimeCart | C87: INV-00086 | D87: 46021 | E87: 46051 | F87: 1468.38 | G87: =SUMIF(Customer_Payments!B:B,C87,Customer_Payments!E:E) -> 1468.38 | H87: =MAX(F87-G87,0) -> 0 | I87: =$L$2-E87 -> 40 | J87: =IF(I87<=0,"Current", IF(I87<=30,"1-30", IF(I87<=60,"31-60", IF(I87<=90,"61-90","90+")))) -> 31-60
A88: CUST-023 | B88: =VLOOKUP(A88,Customers!A:B,2,FALSE) -> DigitalBridge | C88: INV-00087 | D88: 46084 | E88: 46114 | F88: 1534.62 | G88: =SUMIF(Customer_Payments!B:B,C88,Customer_Payments!E:E) -> 1534.62 | H88: =MAX(F88-G88,0) -> 0 | I88: =$L$2-E88 -> -23 | J88: =IF(I88<=0,"Current", IF(I88<=30,"1-30", IF(I88<=60,"31-60", IF(I88<=90,"61-90","90+")))) -> Current
A89: CUST-117 | B89: =VLOOKUP(A89,Customers!A:B,2,FALSE) -> RetailFlowGlobal | C89: INV-00088 | D89: 46022 | E89: 46052 | F89: 4264.32 | G89: =SUMIF(Customer_Payments!B:B,C89,Customer_Payments!E:E) -> 4264.32 | H89: =MAX(F89-G89,0) -> 0 | I89: =$L$2-E89 -> 39 | J89: =IF(I89<=0,"Current", IF(I89<=30,"1-30", IF(I89<=60,"31-60", IF(I89<=90,"61-90","90+")))) -> 31-60
A90: CUST-038 | B90: =VLOOKUP(A90,Customers!A:B,2,FALSE) -> BrightMarket | C90: INV-00089 | D90: 45975 | E90: 46005 | F90: 2830.47 | G90: 1100 | H90: =MAX(F90-G90,0) -> 1730.47 | I90: =$L$2-E90 -> 86 | J90: =IF(I90<=0,"Current", IF(I90<=30,"1-30", IF(I90<=60,"31-60", IF(I90<=90,"61-90","90+")))) -> 61-90
A91: CUST-010 | B91: =VLOOKUP(A91,Customers!A:B,2,FALSE) -> RetailHub | C91: INV-00090 | D91: 45971 | E91: 46001 | F91: 2066.69 | G91: =SUMIF(Customer_Payments!B:B,C91,Customer_Payments!E:E) -> 2066.69 | H91: =MAX(F91-G91,0) -> 0 | I91: =$L$2-E91 -> 90 | J91: =IF(I91<=0,"Current", IF(I91<=30,"1-30", IF(I91<=60,"31-60", IF(I91<=90,"61-90","90+")))) -> 61-90
A92: CUST-051 | B92: =VLOOKUP(A92,Customers!A:B,2,FALSE) -> MarketGenius | C92: INV-00091 | D92: 45967 | E92: 45997 | F92: 5508.3 | G92: =SUMIF(Customer_Payments!B:B,C92,Customer_Payments!E:E) -> 5508.3 | H92: =MAX(F92-G92,0) -> 0 | I92: =$L$2-E92 -> 94 | J92: =IF(I92<=0,"Current", IF(I92<=30,"1-30", IF(I92<=60,"31-60", IF(I92<=90,"61-90","90+")))) -> 90+
A93: CUST-069 | B93: =VLOOKUP(A93,Customers!A:B,2,FALSE) -> RetailMatrix | C93: INV-00092 | D93: 45986 | E93: 46016 | F93: 3312.09 | G93: =SUMIF(Customer_Payments!B:B,C93,Customer_Payments!E:E) -> 3312.09 | H93: =MAX(F93-G93,0) -> 0 | I93: =$L$2-E93 -> 75 | J93: =IF(I93<=0,"Current", IF(I93<=30,"1-30", IF(I93<=60,"31-60", IF(I93<=90,"61-90","90+")))) -> 61-90
A94: CUST-075 | B94: =VLOOKUP(A94,Customers!A:B,2,FALSE) -> RetailFlowX | C94: INV-00093 | D94: 45990 | E94: 46020 | F94: 2945.74 | G94: =SUMIF(Customer_Payments!B:B,C94,Customer_Payments!E:E) -> 2945.74 | H94: =MAX(F94-G94,0) -> 0 | I94: =$L$2-E94 -> 71 | J94: =IF(I94<=0,"Current", IF(I94<=30,"1-30", IF(I94<=60,"31-60", IF(I94<=90,"61-90","90+")))) -> 61-90
A95: CUST-061 | B95: =VLOOKUP(A95,Customers!A:B,2,FALSE) -> RetailDynamics | C95: INV-00094 | D95: 46112 | E95: 46142 | F95: 13547.6 | G95: =SUMIF(Customer_Payments!B:B,C95,Customer_Payments!E:E) -> 13547.6 | H95: =MAX(F95-G95,0) -> 0 | I95: =$L$2-E95 -> -51 | J95: =IF(I95<=0,"Current", IF(I95<=30,"1-30", IF(I95<=60,"31-60", IF(I95<=90,"61-90","90+")))) -> Current
A96: CUST-029 | B96: =VLOOKUP(A96,Customers!A:B,2,FALSE) -> FusionRetail | C96: INV-00095 | D96: 46052 | E96: 46082 | F96: 3143.46 | G96: 980 | H96: =MAX(F96-G96,0) -> 2163.46 | I96: =$L$2-E96 -> 9 | J96: =IF(I96<=0,"Current", IF(I96<=30,"1-30", IF(I96<=60,"31-60", IF(I96<=90,"61-90","90+")))) -> 1-30
A97: CUST-039 | B97: =VLOOKUP(A97,Customers!A:B,2,FALSE) -> EdgeRetail | C97: INV-00096 | D97: 46076 | E97: 46106 | F97: 1485.52 | G97: 300 | H97: =MAX(F97-G97,0) -> 1185.52 | I97: =$L$2-E97 -> -15 | J97: =IF(I97<=0,"Current", IF(I97<=30,"1-30", IF(I97<=60,"31-60", IF(I97<=90,"61-90","90+")))) -> Current
A98: CUST-039 | B98: =VLOOKUP(A98,Customers!A:B,2,FALSE) -> EdgeRetail | C98: INV-00097 | D98: 45982 | E98: 46012 | F98: 1733.97 | G98: 700 | H98: =MAX(F98-G98,0) -> 1033.97 | I98: =$L$2-E98 -> 79 | J98: =IF(I98<=0,"Current", IF(I98<=30,"1-30", IF(I98<=60,"31-60", IF(I98<=90,"61-90","90+")))) -> 61-90
A99: CUST-059 | B99: =VLOOKUP(A99,Customers!A:B,2,FALSE) -> RetailFlow | C99: INV-00098 | D99: 46079 | E99: 46109 | F99: 10157.38 | G99: =SUMIF(Customer_Payments!B:B,C99,Customer_Payments!E:E) -> 10157.38 | H99: =MAX(F99-G99,0) -> 0 | I99: =$L$2-E99 -> -18 | J99: =IF(I99<=0,"Current", IF(I99<=30,"1-30", IF(I99<=60,"31-60", IF(I99<=90,"61-90","90+")))) -> Current
A100: CUST-054 | B100: =VLOOKUP(A100,Customers!A:B,2,FALSE) -> RetailSpark | C100: INV-00099 | D100: 46089 | E100: 46119 | F100: 2670.49 | G100: 1670 | H100: =MAX(F100-G100,0) -> 1000.49 | I100: =$L$2-E100 -> -28 | J100: =IF(I100<=0,"Current", IF(I100<=30,"1-30", IF(I100<=60,"31-60", IF(I100<=90,"61-90","90+")))) -> Current
A101: CUST-107 | B101: =VLOOKUP(A101,Customers!A:B,2,FALSE) -> RetailSpherePro | C101: INV-00100 | D101: 46096 | E101: 46126 | F101: 3839.18 | G101: =SUMIF(Customer_Payments!B:B,C101,Customer_Payments!E:E) -> 3839.18 | H101: =MAX(F101-G101,0) -> 0 | I101: =$L$2-E101 -> -35 | J101: =IF(I101<=0,"Current", IF(I101<=30,"1-30", IF(I101<=60,"31-60", IF(I101<=90,"61-90","90+")))) -> Current
A102: CUST-028 | B102: =VLOOKUP(A102,Customers!A:B,2,FALSE) -> OptiCommerce | C102: INV-00101 | D102: 46049 | E102: 46079 | F102: 12555.13 | G102: =SUMIF(Customer_Payments!B:B,C102,Customer_Payments!E:E) -> 12555.13 | H102: =MAX(F102-G102,0) -> 0 | I102: =$L$2-E102 -> 12 | J102: =IF(I102<=0,"Current", IF(I102<=30,"1-30", IF(I102<=60,"31-60", IF(I102<=90,"61-90","90+")))) -> 1-30
A103: CUST-088 | B103: =VLOOKUP(A103,Customers!A:B,2,FALSE) -> RetailDynamicsX | C103: INV-00102 | D103: 46052 | E103: 46082 | F103: 11734.54 | G103: =SUMIF(Customer_Payments!B:B,C103,Customer_Payments!E:E) -> 11734.54 | H103: =MAX(F103-G103,0) -> 0 | I103: =$L$2-E103 -> 9 | J103: =IF(I103<=0,"Current", IF(I103<=30,"1-30", IF(I103<=60,"31-60", IF(I103<=90,"61-90","90+")))) -> 1-30
A104: CUST-036 | B104: =VLOOKUP(A104,Customers!A:B,2,FALSE) -> RetailWorks | C104: INV-00103 | D104: 45962 | E104: 45992 | F104: 2544.47 | G104: =SUMIF(Customer_Payments!B:B,C104,Customer_Payments!E:E) -> 2544.47 | H104: =MAX(F104-G104,0) -> 0 | I104: =$L$2-E104 -> 99 | J104: =IF(I104<=0,"Current", IF(I104<=30,"1-30", IF(I104<=60,"31-60", IF(I104<=90,"61-90","90+")))) -> 90+
A105: CUST-028 | B105: =VLOOKUP(A105,Customers!A:B,2,FALSE) -> OptiCommerce | C105: INV-00104 | D105: 46053 | E105: 46083 | F105: 5936.41 | G105: =SUMIF(Customer_Payments!B:B,C105,Customer_Payments!E:E) -> 5936.41 | H105: =MAX(F105-G105,0) -> 0 | I105: =$L$2-E105 -> 8 | J105: =IF(I105<=0,"Current", IF(I105<=30,"1-30", IF(I105<=60,"31-60", IF(I105<=90,"61-90","90+")))) -> 1-30
A106: CUST-032 | B106: =VLOOKUP(A106,Customers!A:B,2,FALSE) -> RetailForge | C106: INV-00105 | D106: 45969 | E106: 45999 | F106: 1900.43 | G106: =SUMIF(Customer_Payments!B:B,C106,Customer_Payments!E:E) -> 0 | H106: =MAX(F106-G106,0) -> 1900.43 | I106: =$L$2-E106 -> 92 | J106: =IF(I106<=0,"Current", IF(I106<=30,"1-30", IF(I106<=60,"31-60", IF(I106<=90,"61-90","90+")))) -> 90+
A107: CUST-071 | B107: =VLOOKUP(A107,Customers!A:B,2,FALSE) -> RetailBridge | C107: INV-00106 | D107: 46048 | E107: 46078 | F107: 5573.96 | G107: =SUMIF(Customer_Payments!B:B,C107,Customer_Payments!E:E) -> 0 | H107: =MAX(F107-G107,0) -> 5573.96 | I107: =$L$2-E107 -> 13 | J107: =IF(I107<=0,"Current", IF(I107<=30,"1-30", IF(I107<=60,"31-60", IF(I107<=90,"61-90","90+")))) -> 1-30
A108: CUST-019 | B108: =VLOOKUP(A108,Customers!A:B,2,FALSE) -> OrbitEdge | C108: INV-00107 | D108: 46068 | E108: 46098 | F108: 5172.77 | G108: =SUMIF(Customer_Payments!B:B,C108,Customer_Payments!E:E) -> 5172.77 | H108: =MAX(F108-G108,0) -> 0 | I108: =$L$2-E108 -> -7 | J108: =IF(I108<=0,"Current", IF(I108<=30,"1-30", IF(I108<=60,"31-60", IF(I108<=90,"61-90","90+")))) -> Current
A109: CUST-070 | B109: =VLOOKUP(A109,Customers!A:B,2,FALSE) -> RetailSphere | C109: INV-00108 | D109: 46106 | E109: 46136 | F109: 2803.97 | G109: =SUMIF(Customer_Payments!B:B,C109,Customer_Payments!E:E) -> 0 | H109: =MAX(F109-G109,0) -> 2803.97 | I109: =$L$2-E109 -> -45 | J109: =IF(I109<=0,"Current", IF(I109<=30,"1-30", IF(I109<=60,"31-60", IF(I109<=90,"61-90","90+")))) -> Current
A110: CUST-017 | B110: =VLOOKUP(A110,Customers!A:B,2,FALSE) -> VertexCommerce | C110: INV-00109 | D110: 45969 | E110: 45999 | F110: 2798.51 | G110: =SUMIF(Customer_Payments!B:B,C110,Customer_Payments!E:E) -> 0 | H110: =MAX(F110-G110,0) -> 2798.51 | I110: =$L$2-E110 -> 92 | J110: =IF(I110<=0,"Current", IF(I110<=30,"1-30", IF(I110<=60,"31-60", IF(I110<=90,"61-90","90+")))) -> 90+
A111: CUST-003 | B111: =VLOOKUP(A111,Customers!A:B,2,FALSE) -> UrbanRetail | C111: INV-00110 | D111: 45962 | E111: 45992 | F111: 2829.89 | G111: =SUMIF(Customer_Payments!B:B,C111,Customer_Payments!E:E) -> 2829.89 | H111: =MAX(F111-G111,0) -> 0 | I111: =$L$2-E111 -> 99 | J111: =IF(I111<=0,"Current", IF(I111<=30,"1-30", IF(I111<=60,"31-60", IF(I111<=90,"61-90","90+")))) -> 90+
A112: CUST-015 | B112: =VLOOKUP(A112,Customers!A:B,2,FALSE) -> InsightLoop | C112: INV-00111 | D112: 46012 | E112: 46042 | F112: 4530.74 | G112: =SUMIF(Customer_Payments!B:B,C112,Customer_Payments!E:E) -> 4530.74 | H112: =MAX(F112-G112,0) -> 0 | I112: =$L$2-E112 -> 49 | J112: =IF(I112<=0,"Current", IF(I112<=30,"1-30", IF(I112<=60,"31-60", IF(I112<=90,"61-90","90+")))) -> 31-60
... A124: CUST-012 | B124: =VLOOKUP(A124,Customers!A:B,2,FALSE) -> BluePeak Systems | C124: INV-00123 | D124: 46067 | E124: 46097 | F124: 2104.55 | G124: =SUMIF(Customer_Payments!B:B,C124,Customer_Payments!E:E) -> 0 | H124: =MAX(F124-G124,0) -> 2104.55 | I124: =$L$2-E124 -> -6 | J124: =IF(I124<=0,"Current", IF(I124<=30,"1-30", IF(I124<=60,"31-60", IF(I124<=90,"61-90","90+")))) -> Current
A125: CUST-072 | B125: =VLOOKUP(A125,Customers!A:B,2,FALSE) -> RetailOrbitX | C125: INV-00124 | D125: 46088 | E125: 46118 | F125: 10063.51 | G125: 4000 | H125: =MAX(F125-G125,0) -> 6063.51 | I125: =$L$2-E125 -> -27 | J125: =IF(I125<=0,"Current", IF(I125<=30,"1-30", IF(I125<=60,"31-60", IF(I125<=90,"61-90","90+")))) -> Current
A126: CUST-016 | B126: =VLOOKUP(A126,Customers!A:B,2,FALSE) -> QuantumRetail | C126: INV-00125 | D126: 46086 | E126: 46116 | F126: 3103.76 | G126: =SUMIF(Customer_Payments!B:B,C126,Customer_Payments!E:E) -> 3103.76 | H126: =MAX(F126-G126,0) -> 0 | I126: =$L$2-E126 -> -25 | J126: =IF(I126<=0,"Current", IF(I126<=30,"1-30", IF(I126<=60,"31-60", IF(I126<=90,"61-90","90+")))) -> Current
A127: CUST-093 | B127: =VLOOKUP(A127,Customers!A:B,2,FALSE) -> RetailNovaPro | C127: INV-00126 | D127: 45999 | E127: 46029 | F127: 11297.27 | G127: 10000 | H127: =MAX(F127-G127,0) -> 1297.27 | I127: =$L$2-E127 -> 62 | J127: =IF(I127<=0,"Current", IF(I127<=30,"1-30", IF(I127<=60,"31-60", IF(I127<=90,"61-90","90+")))) -> 61-90
...

Sheet AR_Aging_Summary
A1: ACCOUNTS RECEIVABLE AGING SUMMARY
A2: Report Date: March 10, 2026
A4: Aging Bucket | B4: Outstanding Balance | C4: % of Total AR
A5: Current | B5: =SUMIF(AR_Aging!J:J,"Current",AR_Aging!H:H) -> 1042557.4 | C5: =B5/$B$10 -> 0.32534504
A6: 1-30 Days | B6: =SUMIF(AR_Aging!J:J,"1-30",AR_Aging!H:H) -> 699592.25 | C6: =B6/$B$10 -> 0.21831783
A7: 31-60 Days | B7: =SUMIF(AR_Aging!J:J,"31-60",AR_Aging!H:H) -> 589117.49 | C7: =B7/$B$10 -> 0.18384259
A8: 61-90 Days | B8: =SUMIF(AR_Aging!J:J,"61-90",AR_Aging!H:H) -> 702523.27 | C8: =B8/$B$10 -> 0.21923249
A9: 90+ Days | B9: =SUMIF(AR_Aging!J:J,"90+",AR_Aging!H:H) -> 170676.46 | C9: =B9/$B$10 -> 0.053262044
A10: Total | B10: =SUM(B5:B9) -> 3204466.9 | C10: =SUM(C5:C9) -> 1
B20: Aging Bucket | C20: % of Total AR
B21: Current | C21: 0.32534504
B22: 1-30 Days | C22: 0.21831783
B23: 31-60 Days | C23: 0.18384259
B24: 61-90 Days | C24: 0.21923249
B25: 90+ Days | C25: 0.053262044
B26: Total | C26: 1

Sheet Vendor_Bills
A1: BillID | B1: VendorID | C1: BillDate | D1: DueDate | E1: BillAmount | F1: Status
A2: BILL-00001 | B2: VEN-016 | C2: 46065 | D2: 46095 | E2: 5918.09 | F2: Paid
A3: BILL-00002 | B3: VEN-028 | C3: 46035 | D3: 46065 | E3: 6605.3 | F3: Paid
A4: BILL-00003 | B4: VEN-012 | C4: 45964 | D4: 45994 | E4: 5834.93 | F4: Paid
A5: BILL-00004 | B5: VEN-031 | C5: 46004 | D5: 46034 | E5: 4168.49 | F5: Paid
A6: BILL-00005 | B6: VEN-028 | C6: 46063 | D6: 46093 | E6: 1940.52 | F6: Paid
A7: BILL-00006 | B7: VEN-008 | C7: 46059 | D7: 46089 | E7: 3560.06 | F7: Paid
A8: BILL-00007 | B8: VEN-014 | C8: 45986 | D8: 46016 | E8: 6544.81 | F8: Open
A9: BILL-00008 | B9: VEN-004 | C9: 45996 | D9: 46026 | E9: 1429.47 | F9: Paid
A10: BILL-00009 | B10: VEN-028 | C10: 45979 | D10: 46009 | E10: 5050.47 | F10: Paid
A11: BILL-00010 | B11: VEN-032 | C11: 46002 | D11: 46032 | E11: 1343.26 | F11: Paid
A12: BILL-00011 | B12: VEN-011 | C12: 45976 | D12: 46006 | E12: 4473.44 | F12: Paid
A13: BILL-00012 | B13: VEN-015 | C13: 46027 | D13: 46057 | E13: 2101.38 | F13: Paid
... A1401: BILL-01400 | B1401: VEN-026 | C1401: 45968 | D1401: 45998 | E1401: 5542.46 | F1401: Paid

Sheet Vendor_Payments
A1: PaymentID | B1: VendorID | C1: BillID | D1: PaymentDate | E1: PaymentAmount | F1: Method
A2: VPAY-00001 | B2: VEN-016 | C2: BILL-00001 | D2: 46082 | E2: 5918.09 | F2: ACH
A3: VPAY-00002 | B3: VEN-028 | C3: BILL-00002 | D3: 46036 | E3: 6605.3 | F3: Bank Transfer
A4: VPAY-00003 | B4: VEN-012 | C4: BILL-00003 | D4: 45967 | E4: 5834.93 | F4: Bank Transfer
A5: VPAY-00004 | B5: VEN-031 | C5: BILL-00004 | D5: 46015 | E5: 4168.49 | F5: ACH
A6: VPAY-00005 | B6: VEN-028 | C6: BILL-00005 | D6: 46059 | E6: 1940.52 | F6: Bank Transfer
A7: VPAY-00006 | B7: VEN-008 | C7: BILL-00006 | D7: 46066 | E7: 3560.06 | F7: Bank Transfer
A8: VPAY-00007 | B8: VEN-004 | C8: BILL-00008 | D8: 46009 | E8: 1429.47 | F8: Credit Card
A9: VPAY-00008 | B9: VEN-028 | C9: BILL-00009 | D9: 45999 | E9: 5050.47 | F9: ACH
A10: VPAY-00009 | B10: VEN-032 | C10: BILL-00010 | D10: 46012 | E10: 1343.26 | F10: Bank Transfer
A11: VPAY-00010 | B11: VEN-011 | C11: BILL-00011 | D11: 45995 | E11: 4473.44 | F11: Credit Card
A12: VPAY-00011 | B12: VEN-015 | C12: BILL-00012 | D12: 46029 | E12: 2101.38 | F12: Bank Transfer
A13: VPAY-00012 | B13: VEN-037 | C13: BILL-00013 | D13: 46061 | E13: 2393.11 | F13: Credit Card
... A989: VPAY-00988 | B989: VEN-026 | C989: BILL-01400 | D989: 45982 | E989: 5542.46 | F989: ACH

Sheet AP_Aging
A1: BillID | B1: VendorID | C1: VendorName | D1: BillDate | E1: DueDate | F1: BillAmount | G1: AmountPaid | H1: OutstandingBalance | I1: DaysOutstanding | J1: AgingBucket | L1: 46091
A2: =Table3[[#This Row],[BillID]] -> BILL-00001 | B2: =Table3[[#This Row],[VendorID]] -> VEN-016 | C2: =VLOOKUP(B2,Vendors!A:B,2,FALSE) -> Stripe | D2: =Table3[[#This Row],[BillDate]] -> 46065 | E2: =Table3[[#This Row],[DueDate]] -> 46095 | F2: =Table3[[#This Row],[BillAmount]] -> 5918.09 | G2: =SUMIF(Vendor_Payments!C:C,A2,Vendor_Payments!E:E) -> 5918.09 | H2: =F2-G2 -> 0 | I2: =$L$1-E2 -> -4 | J2: =IF(I2<=0,"Current",IF(I2<=30,"1-30",IF(I2<=60,"31-60",IF(I2<=90,"61-90","90+")))) -> Current
A3: =Table3[[#This Row],[BillID]] -> BILL-00002 | B3: =Table3[[#This Row],[VendorID]] -> VEN-028 | C3: =VLOOKUP(B3,Vendors!A:B,2,FALSE) -> MarketEdge Consulting | D3: =Table3[[#This Row],[BillDate]] -> 46035 | E3: =Table3[[#This Row],[DueDate]] -> 46065 | F3: =Table3[[#This Row],[BillAmount]] -> 6605.3 | G3: =SUMIF(Vendor_Payments!C:C,A3,Vendor_Payments!E:E) -> 6605.3 | H3: =F3-G3 -> 0 | I3: =$L$1-E3 -> 26 | J3: =IF(I3<=0,"Current",IF(I3<=30,"1-30",IF(I3<=60,"31-60",IF(I3<=90,"61-90","90+")))) -> 1-30
A4: =Table3[[#This Row],[BillID]] -> BILL-00003 | B4: =Table3[[#This Row],[VendorID]] -> VEN-012 | C4: =VLOOKUP(B4,Vendors!A:B,2,FALSE) -> Google Cloud | D4: =Table3[[#This Row],[BillDate]] -> 45964 | E4: =Table3[[#This Row],[DueDate]] -> 45994 | F4: =Table3[[#This Row],[BillAmount]] -> 5834.93 | G4: =SUMIF(Vendor_Payments!C:C,A4,Vendor_Payments!E:E) -> 5834.93 | H4: =F4-G4 -> 0 | I4: =$L$1-E4 -> 97 | J4: =IF(I4<=0,"Current",IF(I4<=30,"1-30",IF(I4<=60,"31-60",IF(I4<=90,"61-90","90+")))) -> 90+
A5: =Table3[[#This Row],[BillID]] -> BILL-00004 | B5: =Table3[[#This Row],[VendorID]] -> VEN-031 | C5: =VLOOKUP(B5,Vendors!A:B,2,FALSE) -> DataInsight Analytics | D5: =Table3[[#This Row],[BillDate]] -> 46004 | E5: =Table3[[#This Row],[DueDate]] -> 46034 | F5: =Table3[[#This Row],[BillAmount]] -> 4168.49 | G5: =SUMIF(Vendor_Payments!C:C,A5,Vendor_Payments!E:E) -> 4168.49 | H5: =F5-G5 -> 0 | I5: =$L$1-E5 -> 57 | J5: =IF(I5<=0,"Current",IF(I5<=30,"1-30",IF(I5<=60,"31-60",IF(I5<=90,"61-90","90+")))) -> 31-60
A6: =Table3[[#This Row],[BillID]] -> BILL-00005 | B6: =Table3[[#This Row],[VendorID]] -> VEN-028 | C6: =VLOOKUP(B6,Vendors!A:B,2,FALSE) -> MarketEdge Consulting | D6: =Table3[[#This Row],[BillDate]] -> 46063 | E6: =Table3[[#This Row],[DueDate]] -> 46093 | F6: =Table3[[#This Row],[BillAmount]] -> 1940.52 | G6: =SUMIF(Vendor_Payments!C:C,A6,Vendor_Payments!E:E) -> 1940.52 | H6: =F6-G6 -> 0 | I6: =$L$1-E6 -> -2 | J6: =IF(I6<=0,"Current",IF(I6<=30,"1-30",IF(I6<=60,"31-60",IF(I6<=90,"61-90","90+")))) -> Current
A7: =Table3[[#This Row],[BillID]] -> BILL-00006 | B7: =Table3[[#This Row],[VendorID]] -> VEN-008 | C7: =VLOOKUP(B7,Vendors!A:B,2,FALSE) -> Ahrefs | D7: =Table3[[#This Row],[BillDate]] -> 46059 | E7: =Table3[[#This Row],[DueDate]] -> 46089 | F7: =Table3[[#This Row],[BillAmount]] -> 3560.06 | G7: =SUMIF(Vendor_Payments!C:C,A7,Vendor_Payments!E:E) -> 3560.06 | H7: =F7-G7 -> 0 | I7: =$L$1-E7 -> 2 | J7: =IF(I7<=0,"Current",IF(I7<=30,"1-30",IF(I7<=60,"31-60",IF(I7<=90,"61-90","90+")))) -> 1-30
A8: =Table3[[#This Row],[BillID]] -> BILL-00007 | B8: =Table3[[#This Row],[VendorID]] -> VEN-014 | C8: =VLOOKUP(B8,Vendors!A:B,2,FALSE) -> Figma | D8: =Table3[[#This Row],[BillDate]] -> 45986 | E8: =Table3[[#This Row],[DueDate]] -> 46016 | F8: =Table3[[#This Row],[BillAmount]] -> 6544.81 | G8: =SUMIF(Vendor_Payments!C:C,A8,Vendor_Payments!E:E) -> 0 | H8: =F8-G8 -> 6544.81 | I8: =$L$1-E8 -> 75 | J8: =IF(I8<=0,"Current",IF(I8<=30,"1-30",IF(I8<=60,"31-60",IF(I8<=90,"61-90","90+")))) -> 61-90
A9: =Table3[[#This Row],[BillID]] -> BILL-00008 | B9: =Table3[[#This Row],[VendorID]] -> VEN-004 | C9: =VLOOKUP(B9,Vendors!A:B,2,FALSE) -> LinkedIn Ads | D9: =Table3[[#This Row],[BillDate]] -> 45996 | E9: =Table3[[#This Row],[DueDate]] -> 46026 | F9: =Table3[[#This Row],[BillAmount]] -> 1429.47 | G9: =SUMIF(Vendor_Payments!C:C,A9,Vendor_Payments!E:E) -> 1429.47 | H9: =F9-G9 -> 0 | I9: =$L$1-E9 -> 65 | J9: =IF(I9<=0,"Current",IF(I9<=30,"1-30",IF(I9<=60,"31-60",IF(I9<=90,"61-90","90+")))) -> 61-90
A10: =Table3[[#This Row],[BillID]] -> BILL-00009 | B10: =Table3[[#This Row],[VendorID]] -> VEN-028 | C10: =VLOOKUP(B10,Vendors!A:B,2,FALSE) -> MarketEdge Consulting | D10: =Table3[[#This Row],[BillDate]] -> 45979 | E10: =Table3[[#This Row],[DueDate]] -> 46009 | F10: =Table3[[#This Row],[BillAmount]] -> 5050.47 | G10: =SUMIF(Vendor_Payments!C:C,A10,Vendor_Payments!E:E) -> 5050.47 | H10: =F10-G10 -> 0 | I10: =$L$1-E10 -> 82 | J10: =IF(I10<=0,"Current",IF(I10<=30,"1-30",IF(I10<=60,"31-60",IF(I10<=90,"61-90","90+")))) -> 61-90
A11: =Table3[[#This Row],[BillID]] -> BILL-00010 | B11: =Table3[[#This Row],[VendorID]] -> VEN-032 | C11: =VLOOKUP(B11,Vendors!A:B,2,FALSE) -> Marketing Automation Labs | D11: =Table3[[#This Row],[BillDate]] -> 46002 | E11: =Table3[[#This Row],[DueDate]] -> 46032 | F11: =Table3[[#This Row],[BillAmount]] -> 1343.26 | G11: =SUMIF(Vendor_Payments!C:C,A11,Vendor_Payments!E:E) -> 1343.26 | H11: =F11-G11 -> 0 | I11: =$L$1-E11 -> 59 | J11: =IF(I11<=0,"Current",IF(I11<=30,"1-30",IF(I11<=60,"31-60",IF(I11<=90,"61-90","90+")))) -> 31-60
A12: =Table3[[#This Row],[BillID]] -> BILL-00011 | B12: =Table3[[#This Row],[VendorID]] -> VEN-011 | C12: =VLOOKUP(B12,Vendors!A:B,2,FALSE) -> AWS | D12: =Table3[[#This Row],[BillDate]] -> 45976 | E12: =Table3[[#This Row],[DueDate]] -> 46006 | F12: =Table3[[#This Row],[BillAmount]] -> 4473.44 | G12: =SUMIF(Vendor_Payments!C:C,A12,Vendor_Payments!E:E) -> 4473.44 | H12: =F12-G12 -> 0 | I12: =$L$1-E12 -> 85 | J12: =IF(I12<=0,"Current",IF(I12<=30,"1-30",IF(I12<=60,"31-60",IF(I12<=90,"61-90","90+")))) -> 61-90
A13: =Table3[[#This Row],[BillID]] -> BILL-00012 | B13: =Table3[[#This Row],[VendorID]] -> VEN-015 | C13: =VLOOKUP(B13,Vendors!A:B,2,FALSE) -> Zapier | D13: =Table3[[#This Row],[BillDate]] -> 46027 | E13: =Table3[[#This Row],[DueDate]] -> 46057 | F13: =Table3[[#This Row],[BillAmount]] -> 2101.38 | G13: =SUMIF(Vendor_Payments!C:C,A13,Vendor_Payments!E:E) -> 2101.38 | H13: =F13-G13 -> 0 | I13: =$L$1-E13 -> 34 | J13: =IF(I13<=0,"Current",IF(I13<=30,"1-30",IF(I13<=60,"31-60",IF(I13<=90,"61-90","90+")))) -> 31-60
... A1401: =Table3[[#This Row],[BillID]] -> BILL-01400 | B1401: =Table3[[#This Row],[VendorID]] -> VEN-026 | C1401: =VLOOKUP(B1401,Vendors!A:B,2,FALSE) -> PixelForge Studio | D1401: =Table3[[#This Row],[BillDate]] -> 45968 | E1401: =Table3[[#This Row],[DueDate]] -> 45998 | F1401: =Table3[[#This Row],[BillAmount]] -> 5542.46 | G1401: =SUMIF(Vendor_Payments!C:C,A1401,Vendor_Payments!E:E) -> 5542.46 | H1401: =F1401-G1401 -> 0 | I1401: =$L$1-E1401 -> 93 | J1401: =IF(I1401<=0,"Current",IF(I1401<=30,"1-30",IF(I1401<=60,"31-60",IF(I1401<=90,"61-90","90+")))) -> 90+

Sheet AP_Aging_Summary
A1: NovaTech Commerce Ltd
A2: Accounts Payable Aging Summary
A3: As of March 10, 2026
A6: Aging Brucket | B6: Outstanding Balance | C6: % of Total AP | G6: Current | H6: 0.23398967
A7: Current | B7: =SUMIF(AP_Aging!J:J,"Current",AP_Aging!H:H) -> 369681.95 | C7: =B7/$B$12 -> 0.23398967 | G7: 1-30 Days | H7: 0.23022568
A8: 1-30 Days | B8: =SUMIF(AP_Aging!J:J,"1-30",AP_Aging!H:H) -> 363735.19 | C8: =B8/$B$12 -> 0.23022568 | G8: 31-60 Days | H8: 0.23326672
A9: 31-60 Days | B9: =SUMIF(AP_Aging!J:J,"31-60",AP_Aging!H:H) -> 368539.75 | C9: =B9/$B$12 -> 0.23326672 | G9: 61-90 Days | H9: 0.21919067
A10: 61-90 Days | B10: =SUMIF(AP_Aging!J:J,"61-90",AP_Aging!H:H) -> 346300.91 | C10: =B10/$B$12 -> 0.21919067 | G10: 90+ Days | H10: 0.083327264
A11: 90+ Days | B11: =SUMIF(AP_Aging!J:J,"90+",AP_Aging!H:H) -> 131649.34 | C11: =B11/$B$12 -> 0.083327264
A12: Total AP | B12: =SUM(B7:B11) -> 1579907.1 | C12: =SUM(C7:C11) -> 1
B18: 0=

Sheet Bank_Transactions
A1: TransactionDate | B1: Description | C1: Amount | D1: Type | E1: ReferenceID
A2: 46056 | B2: Payroll | C2: -94788.88 | D2: Withdrawal | E2: PAYROLL
A3: 46077 | B3: Vendor Payment | C3: -4415.61 | D3: Withdrawal | E3: VPAY-00622
A4: 46039 | B4: Customer Payment | C4: 2106.55 | D4: Deposit | E4: PAY-00306
A5: 46043 | B5: Customer Payment | C5: 13480.07 | D5: Deposit | E5: PAY-01413
A6: 46025 | B6: Customer Payment | C6: 3572.3 | D6: Deposit | E6: PAY-00292
A7: 46015 | B7: Customer Payment | C7: 9844.43 | D7: Deposit | E7: PAY-01114
A8: 46017 | B8: Vendor Payment | C8: -6110.16 | D8: Withdrawal | E8: VPAY-00220
A9: 46080 | B9: Customer Payment | C9: 2818.9 | D9: Deposit | E9: PAY-01473
A10: 46022 | B10: Customer Payment | C10: 3428.41 | D10: Deposit | E10: PAY-01208
A11: 45966 | B11: Vendor Payment | C11: -2049.86 | D11: Withdrawal | E11: VPAY-00531
A12: 46070 | B12: Customer Payment | C12: 13804.52 | D12: Deposit | E12: PAY-02010
A13: 46081 | B13: Vendor Payment | C13: -4912.69 | D13: Withdrawal | E13: VPAY-00712
... A3245: 46064 | B3245: Vendor Payment | C3245: -5139.03 | D3245: Withdrawal | E3245: VPAY-00492

Sheet Finance_KPIs
A1: NovaTech Commerce Ltd
A2: Financial Performance Dashboard
A3: Period: Nov 2025 - Mar 2026
A6: Revenue & Profitability
A7: Total Revenue | B7: =SUM(Sales_Invoices!F:F) -> 13108097
A8: Cost of Goods Sold | B8: =SUM(Vendor_Bills!E:E) -> 5427727.9
A9: Gross Profit | B9: =B7-B8 -> 7680369.3
A10: Gross Margin | B10: =B9/B7 -> 0.58592557
A12: Working Capital
A13: Total Accounts Receivable | B13: =SUM(AR_Aging!H:H) -> 3204466.9
A14: Total Accounts Payable | B14: =SUM(AP_Aging!H:H) -> 1579907.1
A15: Cash Balance | B15: =SUM(Bank_Transactions!C:C) -> 4320290.8
A17: Efficiency Metrics
A18: Days Sales Outstanding (DSO) | B18: =B13/(B7/365) -> 89.229611
A19: Days Payable Outstanding (DPO) | B19: =B14/(B8/365) -> 106.24448
A20: Cash Conversion Cycle (CCC) | B20: =B18-B19 -> -17.014865
